Workbook

Sheet Acompanhamento
A2: WEEK | B2: 2023 | C2: 1 | D2: 2 | E2: 3 | F2: 4 | G2: 5 | H2: 6 | I2: 7 | J2: 8 | K2: 9 | L2: 10 | M2: 11 | N2: 12 | O2: 13 | P2: 14 | Q2: 15 | R2: 16 | S2: 17 | T2: 18 | U2: 19 | V2: 20 | W2: 21 | X2: 22 | Y2: 23 | Z2: 24 | AA2: 25 | AB2: 26 | AC2: 27 | AD2: 28 | AE2: 29 | AF2: 30 | AG2: 31 | AH2: 32 | AI2: 33 | AJ2: 34 | AK2: 35 | AL2: 36 | AM2: 37 | AN2: 38 | AO2: 39 | AP2: 40 | AQ2: 41 | AR2: 42 | AS2: 43 | AT2: 44 | AU2: 45 | AV2: 46 | AW2: 47 | AX2: 48 | AY2: 49 | AZ2: 50 | BA2: 51 | BB2: 52 | BC2: Total | BE2: Recebido GEM 2023 | BF2: =SUM($C$3:$BB$3) -> 235
A3: GEM | B3: Recebido | C3: =COUNTIFS('Controle de CR'!$A:$A,Acompanhamento!$B$2,'Controle de CR'!$B:$B,Acompanhamento!C$2,'Controle de CR'!$G:$G,Acompanhamento!$A$3) -> 3 | D3: =COUNTIFS('Controle de CR'!$A:$A,Acompanhamento!$B$2,'Controle de CR'!$B:$B,Acompanhamento!D$2,'Controle de CR'!$G:$G,Acompanhamento!$A$3) -> 4 | E3: =COUNTIFS('Controle de CR'!$A:$A,Acompanhamento!$B$2,'Controle de CR'!$B:$B,Acompanhamento!E$2,'Controle de CR'!$G:$G,Acompanhamento!$A$3) -> 8 | F3: =COUNTIFS('Controle de CR'!$A:$A,Acompanhamento!$B$2,'Controle de CR'!$B:$B,Acompanhamento!F$2,'Controle de CR'!$G:$G,Acompanhamento!$A$3) -> 5 | G3: =COUNTIFS('Controle de CR'!$A:$A,Acompanhamento!$B$2,'Controle de CR'!$B:$B,Acompanhamento!G$2,'Controle de CR'!$G:$G,Acompanhamento!$A$3) -> 4 | H3: =COUNTIFS('Controle de CR'!$A:$A,Acompanhamento!$B$2,'Controle de CR'!$B:$B,Acompanhamento!H$2,'Controle de CR'!$G:$G,Acompanhamento!$A$3) -> 2 | I3: =COUNTIFS('Controle de CR'!$A:$A,Acompanhamento!$B$2,'Controle de CR'!$B:$B,Acompanhamento!I$2,'Controle de CR'!$G:$G,Acompanhamento!$A$3) -> 1 | J3: =COUNTIFS('Controle de CR'!$A:$A,Acompanhamento!$B$2,'Controle de CR'!$B:$B,Acompanhamento!J$2,'Controle de CR'!$G:$G,Acompanhamento!$A$3) -> 5 | ... BB3: =COUNTIFS('Controle de CR'!$A:$A,Acompanhamento!$B$2,'Controle de CR'!$B:$B,Acompanhamento!BB$2,'Controle de CR'!$G:$G,Acompanhamento!$A$3) -> 0 | BC3: =SUM(C3:BB3) -> 235 | BE3: Respondido GEM 2023 | BF3: =SUM($C$4:$BB$4) -> 237
A4: GEM | B4: Respondido | C4: =COUNTIFS('Controle de CR'!$A:$A,Acompanhamento!$B$2,'Controle de CR'!$C:$C,Acompanhamento!C$2,'Controle de CR'!$G:$G,Acompanhamento!$A$4) -> 5 | D4: =COUNTIFS('Controle de CR'!$A:$A,Acompanhamento!$B$2,'Controle de CR'!$C:$C,Acompanhamento!D$2,'Controle de CR'!$G:$G,Acompanhamento!$A$4) -> 2 | E4: =COUNTIFS('Controle de CR'!$A:$A,Acompanhamento!$B$2,'Controle de CR'!$C:$C,Acompanhamento!E$2,'Controle de CR'!$G:$G,Acompanhamento!$A$4) -> 4 | F4: =COUNTIFS('Controle de CR'!$A:$A,Acompanhamento!$B$2,'Controle de CR'!$C:$C,Acompanhamento!F$2,'Controle de CR'!$G:$G,Acompanhamento!$A$4) -> 10 | G4: =COUNTIFS('Controle de CR'!$A:$A,Acompanhamento!$B$2,'Controle de CR'!$C:$C,Acompanhamento!G$2,'Controle de CR'!$G:$G,Acompanhamento!$A$4) -> 1 | H4: =COUNTIFS('Controle de CR'!$A:$A,Acompanhamento!$B$2,'Controle de CR'!$C:$C,Acompanhamento!H$2,'Controle de CR'!$G:$G,Acompanhamento!$A$4) -> 6 | I4: =COUNTIFS('Controle de CR'!$A:$A,Acompanhamento!$B$2,'Controle de CR'!$C:$C,Acompanhamento!I$2,'Controle de CR'!$G:$G,Acompanhamento!$A$4) -> 0 | J4: =COUNTIFS('Controle de CR'!$A:$A,Acompanhamento!$B$2,'Controle de CR'!$C:$C,Acompanhamento!J$2,'Controle de CR'!$G:$G,Acompanhamento!$A$4) -> 6 | ... BB4: =COUNTIFS('Controle de CR'!$A:$A,Acompanhamento!$B$2,'Controle de CR'!$C:$C,Acompanhamento!BB$2,'Controle de CR'!$G:$G,Acompanhamento!$A$4) -> 2 | BC4: =SUM(C4:BB4) -> 237 | BE4: RecebidoVS30 2023 | BF4: =SUM($C$7:$BB$7) -> 88
A5: GEM | B5: Falta Responder | C5: =C3-C4 -> -2 | D5: =D3-D4 -> 2 | E5: =E3-E4 -> 4 | F5: =F3-F4 -> -5 | G5: =G3-G4 -> 3 | H5: =H3-H4 -> -4 | I5: =I3-I4 -> 1 | J5: =J3-J4 -> -1 | ... BB5: =BB3-BB4 -> -2 | BC5: =SUM(C5:BB5) -> -2 | BE5: Respondido VS30 2023 | BF5: =SUM($C$8:$BB$8) -> 88
A7: VS30 | B7: Recebido | C7: =COUNTIFS('Controle de CR'!$A:$A,Acompanhamento!$B$2,'Controle de CR'!$B:$B,Acompanhamento!C$2,'Controle de CR'!$G:$G,Acompanhamento!$A$7) -> 0 | D7: =COUNTIFS('Controle de CR'!$A:$A,Acompanhamento!$B$2,'Controle de CR'!$B:$B,Acompanhamento!D$2,'Controle de CR'!$G:$G,Acompanhamento!$A$7) -> 1 | E7: =COUNTIFS('Controle de CR'!$A:$A,Acompanhamento!$B$2,'Controle de CR'!$B:$B,Acompanhamento!E$2,'Controle de CR'!$G:$G,Acompanhamento!$A$7) -> 0 | F7: =COUNTIFS('Controle de CR'!$A:$A,Acompanhamento!$B$2,'Controle de CR'!$B:$B,Acompanhamento!F$2,'Controle de CR'!$G:$G,Acompanhamento!$A$7) -> 0 | G7: =COUNTIFS('Controle de CR'!$A:$A,Acompanhamento!$B$2,'Controle de CR'!$B:$B,Acompanhamento!G$2,'Controle de CR'!$G:$G,Acompanhamento!$A$7) -> 0 | H7: =COUNTIFS('Controle de CR'!$A:$A,Acompanhamento!$B$2,'Controle de CR'!$B:$B,Acompanhamento!H$2,'Controle de CR'!$G:$G,Acompanhamento!$A$7) -> 2 | I7: =COUNTIFS('Controle de CR'!$A:$A,Acompanhamento!$B$2,'Controle de CR'!$B:$B,Acompanhamento!I$2,'Controle de CR'!$G:$G,Acompanhamento!$A$7) -> 0 | J7: =COUNTIFS('Controle de CR'!$A:$A,Acompanhamento!$B$2,'Controle de CR'!$B:$B,Acompanhamento!J$2,'Controle de CR'!$G:$G,Acompanhamento!$A$7) -> 0 | ... BB7: =COUNTIFS('Controle de CR'!$A:$A,Acompanhamento!$B$2,'Controle de CR'!$B:$B,Acompanhamento!BB$2,'Controle de CR'!$G:$G,Acompanhamento!$A$7) -> 0 | BC7: =SUM(C7:BB7) -> 88
A8: VS30 | B8: Respondido | C8: =COUNTIFS('Controle de CR'!$A:$A,Acompanhamento!$B$2,'Controle de CR'!$C:$C,Acompanhamento!C$2,'Controle de CR'!$G:$G,Acompanhamento!$A$8) -> 0 | D8: =COUNTIFS('Controle de CR'!$A:$A,Acompanhamento!$B$2,'Controle de CR'!$C:$C,Acompanhamento!D$2,'Controle de CR'!$G:$G,Acompanhamento!$A$8) -> 0 | E8: =COUNTIFS('Controle de CR'!$A:$A,Acompanhamento!$B$2,'Controle de CR'!$C:$C,Acompanhamento!E$2,'Controle de CR'!$G:$G,Acompanhamento!$A$8) -> 1 | F8: =COUNTIFS('Controle de CR'!$A:$A,Acompanhamento!$B$2,'Controle de CR'!$C:$C,Acompanhamento!F$2,'Controle de CR'!$G:$G,Acompanhamento!$A$8) -> 0 | G8: =COUNTIFS('Controle de CR'!$A:$A,Acompanhamento!$B$2,'Controle de CR'!$C:$C,Acompanhamento!G$2,'Controle de CR'!$G:$G,Acompanhamento!$A$8) -> 1 | H8: =COUNTIFS('Controle de CR'!$A:$A,Acompanhamento!$B$2,'Controle de CR'!$C:$C,Acompanhamento!H$2,'Controle de CR'!$G:$G,Acompanhamento!$A$8) -> 2 | I8: =COUNTIFS('Controle de CR'!$A:$A,Acompanhamento!$B$2,'Controle de CR'!$C:$C,Acompanhamento!I$2,'Controle de CR'!$G:$G,Acompanhamento!$A$8) -> 1 | J8: =COUNTIFS('Controle de CR'!$A:$A,Acompanhamento!$B$2,'Controle de CR'!$C:$C,Acompanhamento!J$2,'Controle de CR'!$G:$G,Acompanhamento!$A$8) -> 0 | ... BB8: =COUNTIFS('Controle de CR'!$A:$A,Acompanhamento!$B$2,'Controle de CR'!$C:$C,Acompanhamento!BB$2,'Controle de CR'!$G:$G,Acompanhamento!$A$8) -> 0 | BC8: =SUM(C8:BB8) -> 88
A9: VS30 | B9: Falta Responder | C9: =C7-C8 -> 0 | D9: =D7-D8 -> 1 | E9: =E7-E8 -> -1 | F9: =F7-F8 -> 0 | G9: =G7-G8 -> -1 | H9: =H7-H8 -> 0 | I9: =I7-I8 -> -1 | J9: =J7-J8 -> 0 | ... BB9: =BB7-BB8 -> 0 | BC9: =SUM(C9:BB9) -> 0
A11: SPIN | B11: Recebido | C11: =COUNTIFS('Controle de CR'!$A:$A,Acompanhamento!$B$2,'Controle de CR'!$B:$B,Acompanhamento!C$2,'Controle de CR'!$G:$G,Acompanhamento!$A$11) -> 1 | D11: =COUNTIFS('Controle de CR'!$A:$A,Acompanhamento!$B$2,'Controle de CR'!$B:$B,Acompanhamento!D$2,'Controle de CR'!$G:$G,Acompanhamento!$A$11) -> 6 | E11: =COUNTIFS('Controle de CR'!$A:$A,Acompanhamento!$B$2,'Controle de CR'!$B:$B,Acompanhamento!E$2,'Controle de CR'!$G:$G,Acompanhamento!$A$11) -> 11 | F11: =COUNTIFS('Controle de CR'!$A:$A,Acompanhamento!$B$2,'Controle de CR'!$B:$B,Acompanhamento!F$2,'Controle de CR'!$G:$G,Acompanhamento!$A$11) -> 13 | G11: =COUNTIFS('Controle de CR'!$A:$A,Acompanhamento!$B$2,'Controle de CR'!$B:$B,Acompanhamento!G$2,'Controle de CR'!$G:$G,Acompanhamento!$A$11) -> 7 | H11: =COUNTIFS('Controle de CR'!$A:$A,Acompanhamento!$B$2,'Controle de CR'!$B:$B,Acompanhamento!H$2,'Controle de CR'!$G:$G,Acompanhamento!$A$11) -> 14 | I11: =COUNTIFS('Controle de CR'!$A:$A,Acompanhamento!$B$2,'Controle de CR'!$B:$B,Acompanhamento!I$2,'Controle de CR'!$G:$G,Acompanhamento!$A$11) -> 15 | J11: =COUNTIFS('Controle de CR'!$A:$A,Acompanhamento!$B$2,'Controle de CR'!$B:$B,Acompanhamento!J$2,'Controle de CR'!$G:$G,Acompanhamento!$A$11) -> 2 | ... BB11: =COUNTIFS('Controle de CR'!$A:$A,Acompanhamento!$B$2,'Controle de CR'!$B:$B,Acompanhamento!BB$2,'Controle de CR'!$G:$G,Acompanhamento!$A$11) -> 0 | BC11: =SUM(C11:BB11) -> 219
A12: SPIN | B12: Respondido | C12: =COUNTIFS('Controle de CR'!$A:$A,Acompanhamento!$B$2,'Controle de CR'!$C:$C,Acompanhamento!C$2,'Controle de CR'!$G:$G,Acompanhamento!$A$12) -> 5 | D12: =COUNTIFS('Controle de CR'!$A:$A,Acompanhamento!$B$2,'Controle de CR'!$C:$C,Acompanhamento!D$2,'Controle de CR'!$G:$G,Acompanhamento!$A$12) -> 5 | E12: =COUNTIFS('Controle de CR'!$A:$A,Acompanhamento!$B$2,'Controle de CR'!$C:$C,Acompanhamento!E$2,'Controle de CR'!$G:$G,Acompanhamento!$A$12) -> 4 | F12: =COUNTIFS('Controle de CR'!$A:$A,Acompanhamento!$B$2,'Controle de CR'!$C:$C,Acompanhamento!F$2,'Controle de CR'!$G:$G,Acompanhamento!$A$12) -> 7 | G12: =COUNTIFS('Controle de CR'!$A:$A,Acompanhamento!$B$2,'Controle de CR'!$C:$C,Acompanhamento!G$2,'Controle de CR'!$G:$G,Acompanhamento!$A$12) -> 18 | H12: =COUNTIFS('Controle de CR'!$A:$A,Acompanhamento!$B$2,'Controle de CR'!$C:$C,Acompanhamento!H$2,'Controle de CR'!$G:$G,Acompanhamento!$A$12) -> 16 | I12: =COUNTIFS('Controle de CR'!$A:$A,Acompanhamento!$B$2,'Controle de CR'!$C:$C,Acompanhamento!I$2,'Controle de CR'!$G:$G,Acompanhamento!$A$12) -> 11 | J12: =COUNTIFS('Controle de CR'!$A:$A,Acompanhamento!$B$2,'Controle de CR'!$C:$C,Acompanhamento!J$2,'Controle de CR'!$G:$G,Acompanhamento!$A$12) -> 3 | ... BB12: =COUNTIFS('Controle de CR'!$A:$A,Acompanhamento!$B$2,'Controle de CR'!$C:$C,Acompanhamento!BB$2,'Controle de CR'!$G:$G,Acompanhamento!$A$12) -> 0 | BC12: =SUM(C12:BB12) -> 223
A13: VS30 | B13: Falta Responder | C13: =C11-C12 -> -4 | D13: =D11-D12 -> 1 | E13: =E11-E12 -> 7 | F13: =F11-F12 -> 6 | G13: =G11-G12 -> -11 | H13: =H11-H12 -> -2 | I13: =I11-I12 -> 4 | J13: =J11-J12 -> -1 | ... BB13: =BB11-BB12 -> 0 | BC13: =SUM(C13:BB13) -> -4
BC15: Total
B16: Marcelo Santos | C16: =COUNTIFS('Controle de CR'!$A:$A,Acompanhamento!$B$2,'Controle de CR'!$K:$K,Acompanhamento!$B$16,'Controle de CR'!$C:$C,Acompanhamento!C$2) -> 5 | D16: =COUNTIFS('Controle de CR'!$A:$A,Acompanhamento!$B$2,'Controle de CR'!$K:$K,Acompanhamento!$B$16,'Controle de CR'!$C:$C,Acompanhamento!D$2) -> 2 | E16: =COUNTIFS('Controle de CR'!$A:$A,Acompanhamento!$B$2,'Controle de CR'!$K:$K,Acompanhamento!$B$16,'Controle de CR'!$C:$C,Acompanhamento!E$2) -> 9 | F16: =COUNTIFS('Controle de CR'!$A:$A,Acompanhamento!$B$2,'Controle de CR'!$K:$K,Acompanhamento!$B$16,'Controle de CR'!$C:$C,Acompanhamento!F$2) -> 15 | G16: =COUNTIFS('Controle de CR'!$A:$A,Acompanhamento!$B$2,'Controle de CR'!$K:$K,Acompanhamento!$B$16,'Controle de CR'!$C:$C,Acompanhamento!G$2) -> 10 | H16: =COUNTIFS('Controle de CR'!$A:$A,Acompanhamento!$B$2,'Controle de CR'!$K:$K,Acompanhamento!$B$16,'Controle de CR'!$C:$C,Acompanhamento!H$2) -> 5 | I16: =COUNTIFS('Controle de CR'!$A:$A,Acompanhamento!$B$2,'Controle de CR'!$K:$K,Acompanhamento!$B$16,'Controle de CR'!$C:$C,Acompanhamento!I$2) -> 0 | J16: =COUNTIFS('Controle de CR'!$A:$A,Acompanhamento!$B$2,'Controle de CR'!$K:$K,Acompanhamento!$B$16,'Controle de CR'!$C:$C,Acompanhamento!J$2) -> 0 | ... BB16: =COUNTIFS('Controle de CR'!$A:$A,Acompanhamento!$B$2,'Controle de CR'!$K:$K,Acompanhamento!$B$16,'Controle de CR'!$C:$C,Acompanhamento!BB$2) -> 2 | BC16: =SUM(C16:BB16) -> 216
B17: Paulo Lima | C17: =COUNTIFS('Controle de CR'!$A:$A,Acompanhamento!$B$2,'Controle de CR'!$K:$K,Acompanhamento!$B$17,'Controle de CR'!$C:$C,Acompanhamento!C$2) -> 5 | D17: =COUNTIFS('Controle de CR'!$A:$A,Acompanhamento!$B$2,'Controle de CR'!$K:$K,Acompanhamento!$B$17,'Controle de CR'!$C:$C,Acompanhamento!D$2) -> 5 | E17: =COUNTIFS('Controle de CR'!$A:$A,Acompanhamento!$B$2,'Controle de CR'!$K:$K,Acompanhamento!$B$17,'Controle de CR'!$C:$C,Acompanhamento!E$2) -> 0 | F17: =COUNTIFS('Controle de CR'!$A:$A,Acompanhamento!$B$2,'Controle de CR'!$K:$K,Acompanhamento!$B$17,'Controle de CR'!$C:$C,Acompanhamento!F$2) -> 2 | G17: =COUNTIFS('Controle de CR'!$A:$A,Acompanhamento!$B$2,'Controle de CR'!$K:$K,Acompanhamento!$B$17,'Controle de CR'!$C:$C,Acompanhamento!G$2) -> 10 | H17: =COUNTIFS('Controle de CR'!$A:$A,Acompanhamento!$B$2,'Controle de CR'!$K:$K,Acompanhamento!$B$17,'Controle de CR'!$C:$C,Acompanhamento!H$2) -> 19 | I17: =COUNTIFS('Controle de CR'!$A:$A,Acompanhamento!$B$2,'Controle de CR'!$K:$K,Acompanhamento!$B$17,'Controle de CR'!$C:$C,Acompanhamento!I$2) -> 12 | J17: =COUNTIFS('Controle de CR'!$A:$A,Acompanhamento!$B$2,'Controle de CR'!$K:$K,Acompanhamento!$B$17,'Controle de CR'!$C:$C,Acompanhamento!J$2) -> 9 | ... BB17: =COUNTIFS('Controle de CR'!$A:$A,Acompanhamento!$B$2,'Controle de CR'!$K:$K,Acompanhamento!$B$17,'Controle de CR'!$C:$C,Acompanhamento!BB$2) -> 0 | BC17: =SUM(C17:BB17) -> 333

Sheet Controle de CR
A1: Ano | B1: Recebida Week | C1: Respondida Week | D1: DCN | E1: CR | F1: IP | G1: Projeto | H1: Nome Resp. CR | I1: Data | J1: Hora | K1: Avaliado | L1: Data | M1: Hora | N1: OBSERVAÇÃO | O1: OBSERVAÇÃO 02
A2: =YEAR(L2) -> 1900 | B2: =WEEKNUM(I2) -> 37 | C2: =WEEKNUM(L2) -> 0 | E2: CR-0110061-00 | H2: Marcio Militani | I2: 44447 | J2: 0.38472222 | K2: Paulo Lima | N2: Sem impacto em Lead Prep! Implementação condicionada à aprovação da aplicação sob a norma GMW 17136
A3: =YEAR(L3) -> 1900 | B3: =WEEKNUM(I3) -> 37 | C3: =WEEKNUM(L3) -> 0 | E3: - | F3: ISS-026302 | H3: Gabriel conceição | I3: 44447 | J3: 0.24375 | K3: Paulo Lima
A4: =YEAR(L4) -> 1900 | B4: =WEEKNUM(I4) -> 35 | C4: =WEEKNUM(L4) -> 0 | E4: CR-0109316-00 | G4: VS30 | H4: Marcio Militani | I4: 44435 | J4: 0.67430556 | K4: Paulo Lima | N4: Sem Impacto
A5: =YEAR(L5) -> 1900 | B5: =WEEKNUM(I5) -> 35 | C5: =WEEKNUM(L5) -> 0 | E5: CR-0109284-00 | G5: VS30 | H5: Marcio Militani | I5: 44435 | J5: 0.67152778 | K5: Paulo Lima | N5: Sem Impacto
A6: =YEAR(L6) -> 1900 | B6: =WEEKNUM(I6) -> 35 | C6: =WEEKNUM(L6) -> 0 | E6: CR-0109320-00 | G6: VS30 | H6: Marcio Militani | I6: 44435 | J6: 0.67638889 | K6: Paulo Lima | N6: Sem Impacto
A7: =YEAR(L7) -> 1900 | B7: =WEEKNUM(I7) -> 35 | C7: =WEEKNUM(L7) -> 0 | E7: CR-0109534-00 | G7: GEM | H7: Marcio Militani | I7: 44435 | J7: 0.68680556 | K7: Paulo Lima | N7: Sem Impacto
A8: =YEAR(L8) -> 1900 | B8: =WEEKNUM(I8) -> 35 | C8: =WEEKNUM(L8) -> 0 | E8: CR-0109404-00 | G8: GEM | H8: Marcio Militani | I8: 44435 | J8: 0.69027778 | K8: Paulo Lima | N8: Sem Impacto
A9: =YEAR(L9) -> 1900 | B9: =WEEKNUM(I9) -> 36 | C9: =WEEKNUM(L9) -> 0 | E9: CR-0109163-00 | G9: VS30 | H9: Marcio Militani | I9: 44439 | J9: 0.37777778 | K9: Paulo Lima | N9: Sem Impacto
A10: =YEAR(L10) -> 1900 | B10: =WEEKNUM(I10) -> 36 | C10: =WEEKNUM(L10) -> 0 | E10: CR-0108981-00 | G10: GEM MY 22 e 22/5 | H10: Marcio Militani | I10: 44439 | J10: 0.37916667 | K10: Paulo Lima | N10: Sem Impacto
A11: =YEAR(L11) -> 1900 | B11: =WEEKNUM(I11) -> 36 | C11: =WEEKNUM(L11) -> 0 | E11: CR-0109174-00 | G11: GEM MY 22.5 | H11: Marcio Militani | I11: 44439 | J11: 0.37708333 | K11: Paulo Lima | N11: Due to the transfer of machinery of GMI to Camanducaia, we do not have a machine to cut the E03239500 tube and it is necessary to replace it with the E21429600. Verificar esta CR com relação a esta troca de tubo | O11: OK
A12: =YEAR(L12) -> 1900 | B12: =WEEKNUM(I12) -> 36 | C12: =WEEKNUM(L12) -> 0 | E12: CR-0109003-00 | G12: GEM | H12: Marcio Militani | I12: 44439 | J12: 0.38055556 | K12: Paulo Lima | N12: Sem Impacto
A13: =YEAR(L13) -> 1900 | B13: =WEEKNUM(I13) -> 36 | C13: =WEEKNUM(L13) -> 0 | E13: CR's PENDENTES | H13: Marcio Militani | I13: 44439 | J13: 0.38125 | K13: Paulo Lima | N13: Verificar com o Márcio sobre as CR'spendentes
A14: =YEAR(L14) -> 1900 | B14: =WEEKNUM(I14) -> 36 | C14: =WEEKNUM(L14) -> 0 | E14: CR's PENDENTES | H14: Marcio Militani | I14: 44439 | J14: 0.3875 | K14: Paulo Lima | N14: Verificar com o Márcio sobre as CR'spendentes
A15: =YEAR(L15) -> 1900 | B15: =WEEKNUM(I15) -> 36 | C15: =WEEKNUM(L15) -> 0 | E15: CR-0109151-00 | G15: GEM MY 22.5 | H15: Marcio Militani | I15: 44439 | J15: 0.39791667 | K15: Paulo Lima | N15: Due to the transfer of machinery of GMI to Camanducaia, we do not have a machine to cut the E03239500 tube and it is necessary to replace it with the E21429700.Verificar esta CR com relação a esta troca de tubo | O15: Não tem matéria prima para efetuar o teste
A16: =YEAR(L16) -> 1900 | B16: =WEEKNUM(I16) -> 36 | C16: =WEEKNUM(L16) -> 0 | D16: DCN-2021-0010462-VS30-4 | E16: CR-0107176-01 | G16: VS30 | H16: Robson Avelino | I16: 44439 | J16: 0.83680556 | K16: Paulo Lima | N16: Sem Impacto
A17: =YEAR(L17) -> 1900 | B17: =WEEKNUM(I17) -> 36 | C17: =WEEKNUM(L17) -> 0 | D17: DCN-2021-0010464-VS30-4 | E17: CR-0107174-00 | G17: VS30 | H17: Robson Avelino | I17: 44439 | J17: 0.83680556 | K17: Paulo Lima | N17: Sem Impacto
A18: =YEAR(L18) -> 1900 | B18: =WEEKNUM(I18) -> 36 | C18: =WEEKNUM(L18) -> 0 | D18: DCN-2021-0010465-VS30-4 | E18: CR-0107964-00 | G18: VS30 | H18: Robson Avelino | I18: 44439 | J18: 0.83680556 | K18: Paulo Lima | N18: Sem Impacto
A19: =YEAR(L19) -> 1900 | B19: =WEEKNUM(I19) -> 36 | C19: =WEEKNUM(L19) -> 0 | D19: DCN-2021-0010466-VS30-4 | E19: CR-0107970-00/ | G19: VS30 | H19: Robson Avelino | I19: 44439 | J19: 0.83680556 | K19: Paulo Lima | N19: Não achei na lista de terminal, favor avaliar | O19: Sendo avaliado pelo Rogerio
A20: =YEAR(L20) -> 1900 | B20: =WEEKNUM(I20) -> 36 | C20: =WEEKNUM(L20) -> 0 | D20: DCN-2021-0010467-VS30-4 | E20: CR-0107590-00 | G20: VS30 | H20: Robson Avelino | I20: 44439 | J20: 0.83680556 | K20: Paulo Lima | N20: Sem Impacto
A21: =YEAR(L21) -> 1900 | B21: =WEEKNUM(I21) -> 36 | C21: =WEEKNUM(L21) -> 0 | D21: DCN-2021-0010126-GEM-4 | E21: CR-0102325-00 | G21: GEM | H21: Rogerio Naus | I21: 44441 | J21: 0.36458333 | K21: Paulo Lima | N21: Alteração de termo retrátil de GPN-E15828200/GPN-E02090100 (27mm) para GPN-E30547700 (40mm) do terminal olhal X633G108_DIRTY_X1. Complementado a CR-0102835-00 é necessário adição de mastic de GPN-E24835800 no terminal olhal X633G108_DIRTY_X1. Utilizar 1g (grama) de mastic para cada aplicação do termo retrátil GPN-E30547700 + mastic GPN-E24835800
A22: =YEAR(L22) -> 1900 | B22: =WEEKNUM(I22) -> 36 | C22: =WEEKNUM(L22) -> 0 | D22: DCN-2021-0010127-GEM-4 | E22: CR-0102325-00 | G22: GEM | H22: Rogerio Naus | I22: 44441 | J22: 0.36458333 | K22: Paulo Lima | N22: Alteração de termo retrátil de GPN-E15828200/GPN-E02090100 (27mm) para GPN-E30547700 (40mm) do terminal olhal X633G108_DIRTY_X1. Complementado a CR-0102835-00 é necessário adição de mastic de GPN-E24835800 no terminal olhal X633G108_DIRTY_X1. Utilizar 1g (grama) de mastic para cada aplicação do termo retrátil GPN-E30547700 + mastic GPN-E24835800.
A23: =YEAR(L23) -> 1900 | B23: =WEEKNUM(I23) -> 36 | C23: =WEEKNUM(L23) -> 0 | D23: DCN-2021-0010128-GEM-4 | E23: CR-0102325-00 | G23: GEM | H23: Rogerio Naus | I23: 44441 | J23: 0.36458333 | K23: Paulo Lima | N23: Sem Impacto
A24: =YEAR(L24) -> 1900 | B24: =WEEKNUM(I24) -> 36 | C24: =WEEKNUM(L24) -> 0 | D24: DCN-2021-0010129-GEM-4 | E24: CR-0102325-00 | G24: GEM | H24: Rogerio Naus | I24: 44441 | J24: 0.36458333 | K24: Paulo Lima | N24: Sem Impacto
A25: =YEAR(L25) -> 1900 | B25: =WEEKNUM(I25) -> 36 | C25: =WEEKNUM(L25) -> 0 | D25: DCN-2021-0010171-GEM-4 | E25: CR-0102205-00 / CR-0102594-00 | G25: GEM | H25: Rogerio Naus | I25: 44441 | J25: 0.36666667 | K25: Paulo Lima | N25: Sem Impacto
A26: =YEAR(L26) -> 1900 | B26: =WEEKNUM(I26) -> 36 | C26: =WEEKNUM(L26) -> 0 | D26: DCN-2021-0010148-GEM-4 | E26: CR-0102545-00,CR-0102565-00,CR-0102567-00,CR-0102603-00,CR-0102849-01 e CR-0102839-01 | G26: GEM | H26: Rogerio Naus | I26: 44441 | J26: 0.36805556 | K26: Paulo Lima | N26: Oficializando troca do terminal de E14568800 para E21821100 RN234. | O26: Já temos este terminal validado
A27: =YEAR(L27) -> 1900 | B27: =WEEKNUM(I27) -> 36 | C27: =WEEKNUM(L27) -> 0 | D27: DCN-2021-0010150-GEM-4 | E27: CR-0102546-00 | G27: GEM | H27: Rogerio Naus | I27: 44441 | J27: 0.36805556 | K27: Paulo Lima | N27: Oficializando troca do terminal de E14568800 para E21821100 RN243.
A28: =YEAR(L28) -> 1900 | B28: =WEEKNUM(I28) -> 38 | C28: =WEEKNUM(L28) -> 0 | E28: CR-0110114-00 | F28: ISS-026053 | G28: GEM | H28: Márcio Pericles Militani | I28: 44452 | J28: 0.45972222 | K28: Paulo Lima | N28: TW117_5 aumetando o comprimento de 720mm para 750 mm
A29: =YEAR(L29) -> 1900 | B29: =WEEKNUM(I29) -> 38 | C29: =WEEKNUM(L29) -> 0 | E29: CR-0110178-00 | G29: GEM | H29: Márcio Pericles Militani | I29: 44452 | J29: 0.47569444 | K29: Paulo Lima | N29: sem impacto
A30: =YEAR(L30) -> 1900 | B30: =WEEKNUM(I30) -> 38 | C30: =WEEKNUM(L30) -> 0 | E30: CR-0110179-00 | G30: GEM | H30: Márcio Pericles Militani | I30: 44452 | J30: 0.49305556 | K30: Paulo Lima | N30: WLL, STOCK IN USER
A31: =YEAR(L31) -> 1900 | B31: =WEEKNUM(I31) -> 38 | C31: =WEEKNUM(L31) -> 0 | E31: CR-0110382-00. | G31: VS30 | H31: Márcio Pericles Militani | I31: 44454 | J31: 0.31944444 | K31: Paulo Lima | N31: circuito 6651B-terminal de E09199300 para E11424400 / circuito 6652B - 6653B-6654B- terminal de 3201511A1 para E11225200 /
A32: =YEAR(L32) -> 1900 | B32: =WEEKNUM(I32) -> 39 | C32: =WEEKNUM(L32) -> 0 | E32: CR-0110673-00. | G32: VS30 | H32: Márcio Pericles Militani | I32: 44462 | J32: 0.48333333 | K32: Paulo Lima | N32: WLL DE SPLICE, MULTICRIMP E CIRCUITOS COMUNS. Sem necessidade de investimento
A33: =YEAR(L33) -> 1900 | B33: =WEEKNUM(I33) -> 39 | C33: =WEEKNUM(L33) -> 0 | E33: CR-0110672-00 | G33: GEM | H33: Márcio Pericles Militani | I33: 44462 | J33: 0.48888889 | K33: Paulo Lima | N33: Alteração de WLL e TLL. SEM NECESSIDADE DE INVESTIMENTO
A34: =YEAR(L34) -> 1900 | B34: =WEEKNUM(I34) -> 52 | C34: =WEEKNUM(L34) -> 0 | E34: CR-0115570-00 | G34: GEM | H34: Márcio Pericles Militani | I34: 44550 | J34: 0.63402778 | K34: Paulo Lima | N34: Troca do termoencolhível de E02000700 (65mm/135°C) para E16718500 (50mm/125°C) | O34: Necessário validação de todas as splices para aprovação. Total de 60 splices para fazer aa validação. Custo de R$2678,1 para as amostras
A35: =YEAR(L35) -> 1900 | B35: =WEEKNUM(I35) -> 52 | C35: =WEEKNUM(L35) -> 0 | E35: CR-0115703-00 | G35: GEM | H35: Marcelo | I35: 44551 | J35: 0.47777778 | K35: Paulo Lima | N35: Troca do terminal 3202532V5 para 3202650S8 | O35: Necessário investimento de um miniapicador, validação e peças de reposição. Aplicador novo
A36: =YEAR(L36) -> 1900 | B36: =WEEKNUM(I36) -> 52 | C36: =WEEKNUM(L36) -> 0 | E36: CR-0115655-00 | G36: GEM | H36: Marcelo | I36: 44552 | J36: 0.47986111 | K36: Paulo Lima | N36: Troca de posicionamento da presilha | O36: sem impacto
A37: =YEAR(L37) -> 1900 | B37: =WEEKNUM(I37) -> 52 | C37: =WEEKNUM(L37) -> 0 | E37: CR-0115594-00 | G37: GEM | H37: Marcelo | I37: 44552 | J37: 0.48333333 | K37: Paulo Lima | N37: Troca do tubo liso de E12128600 para E14165400 | O37: Sem necessidade de investimento
A38: =YEAR(L38) -> 1900 | B38: =WEEKNUM(I38) -> 52 | C38: =WEEKNUM(L38) -> 0 | E38: CR-0116167-00 | G38: VS30 | H38: Márcio Pericles Militani | I38: 44551 | J38: 0.65763889 | K38: Paulo Lima | N38: Novo Chicote da bomba do limpador do parabrisa. | O38: Necessidade de 02 miniaplicadores para o terminal 32025Y1G5 e 32025Y1G6
A39: =YEAR(L39) -> 2022 | B39: =WEEKNUM(I39) -> 51 | C39: =WEEKNUM(L39) -> 2 | E39: CR-0115838-00 | G39: VS30 | H39: Márcio Pericles Militani | I39: 44546 | J39: 0.69305556 | K39: Marcelo Santos | L39: 44564 | M39: 0.45763889 | N39: Sem impacto par corte e Lead prep. analise feita base WLL , entrando 4 circuitos diretos novos.
A40: =YEAR(L40) -> 2022 | B40: =WEEKNUM(I40) -> 51 | C40: =WEEKNUM(L40) -> 2 | E40: CR-0115976-00 | G40: VS30 | H40: Márcio Pericles Militani | I40: 44546 | J40: 0.70208333 | K40: Marcelo Santos | L40: 44564 | M40: 0.475 | N40: Sem impacto para corte e Lead prep.Alteração do cabo 16AC12020 Para E25180500 no SAP para adequação da unidade de medida.
A41: =YEAR(L41) -> 2022 | B41: =WEEKNUM(I41) -> 51 | C41: =WEEKNUM(L41) -> 2 | E41: CR-0115570-00 | G41: GEM | H41: William Naves | I41: 44545 | J41: 0.68055556 | K41: Marcelo Santos | L41: 44565 | M41: 0.30347222 | N41: 8horas de operacional 16 horas técnicas de engenharia 10 validações conforme Norma GMW17136 ( Bubble Test ) R$2.932,80 scrap das amostras de validação
A42: =YEAR(L42) -> 2022 | B42: =WEEKNUM(I42) -> 51 | C42: =WEEKNUM(L42) -> 2 | E42: CR-0115251-00 | G42: GEM | H42: William Naves | I42: 44548 | J42: 0.42361111 | K42: Marcelo Santos | L42: 44565 | M42: 0.40138889 | N42: Sem investimento, Condicionado a aprovação dos investimentos reportados na CR-0115083-00, Troca do terminal 3202574I6 para 3202538H3,1 Validação de terminal conforme norma USCAR21 2 validações Multicrimp conforme norma USCAR 38,2 validações conforme Norma GMW17136 ( Bubble Test )
A43: =YEAR(L43) -> 2021 | B43: =WEEKNUM(I43) -> 51 | C43: =WEEKNUM(L43) -> 52 | E43: CR-0115590-00 | G43: GEM | H43: Márcio Pericles Militani | I43: 44548 | J43: 15:49 | K43: Marcelo Santos | L43: 44552 | M43: 0.42152778 | N43: Esse já é item implementado favor desconsiderar os investimentos.
A44: =YEAR(L44) -> 2022 | B44: =WEEKNUM(I44) -> 51 | C44: =WEEKNUM(L44) -> 2 | E44: CR-0115440-00 | G44: GEM | H44: William Naves | I44: 44548 | J44: 0.43611111 | K44: Marcelo Santos | L44: 44565 | M44: 0.60763889 | N44: 2 Aplicadores modelo mecal MRSJ1 para o terminal 320257A99 1 Aplicadores modelo mecal MRSJ1 para o terminal E04322000,2 Validações de terminal conforme norma USCAR21.
A45: =YEAR(L45) -> 2021 | B45: =WEEKNUM(I45) -> 51 | C45: =WEEKNUM(L45) -> 52 | E45: CR-0115702-00 | G45: GEM | H45: Márcio Pericles Militani | I45: 44548 | J45: 0.65555556 | K45: Marcelo Santos | L45: 44552 | M45: 0.58333333 | N45: Condicionado a aprovação das validações solicitadas na CR-0110967-00
A46: =YEAR(L46) -> 2021 | B46: =WEEKNUM(I46) -> 51 | C46: =WEEKNUM(L46) -> 52 | E46: CR-0115589-01 | G46: GEM | H46: Márcio Pericles Militani | I46: 44548 | J46: 0.64444444 | K46: Marcelo Santos | L46: 44552 | N46: 3 validações de Splice conforme norma USCAR 45. sem necessidde de investimento para a CR. Emial enviado no dia 17/02/2022 às 09:45 hs. Já temos estas validações de USCAR 45
A47: =YEAR(L47) -> 2021 | B47: =WEEKNUM(I47) -> 51 | C47: =WEEKNUM(L47) -> 51 | E47: CR-0115274-00 | G47: GEM | H47: Márcio Pericles Militani | I47: 44543 | J47: 0.70486111 | K47: Marcelo Santos | L47: 44546 | N47: ! Sem impacto em Lead Prep! Implementação condicionada à aprovação da aplicação sob a norma GMW 17136
A48: =YEAR(L48) -> 2021 | B48: =WEEKNUM(I48) -> 51 | C48: =WEEKNUM(L48) -> 51 | E48: CR-0115111-00 | G48: GEM | H48: Márcio Pericles Militani | I48: 44545 | J48: 0.71666667 | K48: Marcelo Santos | L48: 44545 | N48: Sem impacto para corte e lead prep. Alteração do clip E02498200 Para E07869100.
A49: =YEAR(L49) -> 2022 | B49: =WEEKNUM(I49) -> 52 | C49: =WEEKNUM(L49) -> 2 | E49: CR-0115728-00 | G49: GEM | H49: William Naves | I49: 44550 | K49: Marcelo Santos | L49: 44566 | N49: 1 hora operacional 3horas técnicas de engenharia 2 validações conforme Norma GMW17136 ( Bubble Test ), condicionada a aprovação das validações comuns com essa CR, Solicitado na CR-0115688-00Scrap R$ 475,00 de amostras de validação.
A50: =YEAR(L50) -> 2022 | B50: =WEEKNUM(I50) -> 50 | C50: =WEEKNUM(L50) -> 2 | E50: CR-0115699-00 | F50: IP | G50: GEM | H50: William Naves | I50: 44535 | J50: 0.47430556 | K50: Marcelo Santos | L50: 44567 | M50: 0.45833333 | N50: Sem impacto para corte e Lead prep.
A51: =YEAR(L51) -> 2022 | B51: =WEEKNUM(I51) -> 50 | C51: =WEEKNUM(L51) -> 2 | E51: CR-0115700-00 | F51: IP | G51: GEM | H51: William Naves | I51: 44535 | J51: 0.48541667 | K51: Marcelo Santos | L51: 44567 | M51: 0.46388889 | N51: Sem impacto para corte e Lead Prep.
A52: =YEAR(L52) -> 2022 | B52: =WEEKNUM(I52) -> 50 | C52: =WEEKNUM(L52) -> 2 | E52: CR-0115706-00 | F52: ip | G52: GEM | H52: William Naves | I52: 44535 | J52: 0.49444444 | K52: Marcelo Santos | L52: 44567 | M52: 0.52916667 | N52: Sem impacto para corte e Lead Prep.
A53: =YEAR(L53) -> 2022 | B53: =WEEKNUM(I53) -> 2 | C53: =WEEKNUM(L53) -> 2 | E53: CR-0115337-00 | F53: BODY | G53: GEM | H53: William Naves | I53: 44568 | J53: 0.5125 | K53: Paulo Lima | L53: 44569 | N53: 01 - Aplicador modelo Mecal MRSJ1 para o terminal 320250AC7. 02 - Validações de terminal conforme norma USCAR21. 02 – Validações de Multicrimp conforme USCAR 38.
A54: =YEAR(L54) -> 2022 | B54: =WEEKNUM(I54) -> 2 | C54: =WEEKNUM(L54) -> 2 | E54: CR-0115566-00 | F54: FrontDoor | G54: GEM | H54: William Naves | I54: 44568 | J54: 0.48472222 | K54: Paulo Lima | L54: 44569 | N54: CR reprovada até o momento. Cabo de 1,00 mm² é incompatível para a aplicação do terminal E15834400. Para o terminal 320257WX8 é necessário uma validação para avaliar as condições de crimpagem e de detecção para uma maior confiabilidade.
A55: =YEAR(L55) -> 2022 | B55: =WEEKNUM(I55) -> 2 | C55: =WEEKNUM(L55) -> 2 | E55: CR-0115340-00 | F55: BODY | G55: GEM | H55: William Naves | I55: 44568 | J55: 0.51944444 | K55: Paulo Lima | L55: 44569 | N55: Uma validação USCAR – 21 para o terminal 3202538H3. Duas validações Multicrimp conforme norma USCAR 38 um aplicador modelo mecal MRSJ1 para o terminal 3202538H3.
A56: =YEAR(L56) -> 2022 | B56: =WEEKNUM(I56) -> 2 | C56: =WEEKNUM(L56) -> 2 | E56: CR-0115342-00 | F56: FrontDoor | G56: GEM | H56: William Naves | I56: 44568 | J56: 0.53333333 | K56: Paulo Lima | L56: 44569 | N56: Um Aplicador modelo mecal MRSJ1 para o terminal 3202537J9; Uma validação de terminal conforme nora USCAR 21.
A57: =YEAR(L57) -> 2022 | B57: =WEEKNUM(I57) -> 3 | C57: =WEEKNUM(L57) -> 3 | E57: CR-0115450-00 | F57: Engine | G57: GEM | H57: William Naves | I57: 44571 | J57: 0.45763889 | K57: Paulo Lima | L57: 44572 | N57: Sem impacto de investimento para a CR
A58: =YEAR(L58) -> 2022 | B58: =WEEKNUM(I58) -> 3 | C58: =WEEKNUM(L58) -> 3 | E58: CR-0115834-00 | F58: FRONTBUMPER | G58: GEM | H58: William Naves | I58: 44571 | J58: 0.44444444 | K58: Paulo Lima | L58: 44572 | N58: Sem impacto de investimento para a CR
A59: =YEAR(L59) -> 2022 | B59: =WEEKNUM(I59) -> 3 | C59: =WEEKNUM(L59) -> 3 | E59: CR-0116167-01 | F59: AUTARK | G59: VS30 | H59: William Naves | I59: 44571 | J59: 0.675 | K59: Marcelo Santos | L59: 44575 | N59: Considerar 1 aplicador TE para terminal E13167400 Considerar 2 validações de Terminais conforme norma VS30. | O59: Gilço falou que o Autark não vai mais ser feito, FOI CANCELADO A COMPRA DESTE APLICADOR
A60: =YEAR(L60) -> 2022 | B60: =WEEKNUM(I60) -> 3 | C60: =WEEKNUM(L60) -> 3 | E60: CR-0115834-00 | F60: FRONTBUMPER | G60: GEM | H60: William Naves | I60: 44571 | J60: 0.44444444 | K60: Marcelo Santos | L60: 44575 | N60: Sem impacto de investimento para a CR
A61: =YEAR(L61) -> 1900 | B61: =WEEKNUM(I61) -> 3 | C61: =WEEKNUM(L61) -> 0 | E61: CR-0116274-00 | F61: IP | G61: VS30 | H61: William Naves | I61: 44571 | J61: 0.68125 | K61: Marcelo Santos | N61: Sem impacto para corte e Lead prep.
A62: =YEAR(L62) -> 2022 | B62: =WEEKNUM(I62) -> 3 | C62: =WEEKNUM(L62) -> 3 | E62: CR-0115450-00 | F62: Engine | G62: GEM | H62: William Naves | I62: 44571 | J62: 0.45763889 | K62: Marcelo Santos | L62: 44575 | N62: 2 validações de Splice conforme norma USCAR 45 2 validações conforme Norma GMW17136 ( Bubble Test )
A63: =YEAR(L63) -> 2022 | B63: =WEEKNUM(I63) -> 2 | C63: =WEEKNUM(L63) -> 3 | E63: CR-0115344-00 | F63: FrontDoor | G63: GEM | H63: William Naves | I63: 44568 | J63: 0.51319444 | K63: Marcelo Santos | L63: 44575 | N63: 1 Aplicador modelo mecal MRSJ1 para o terminal 3202537M3 1 Validações de terminal conforme norma USCAR21.
A64: =YEAR(L64) -> 2022 | B64: =WEEKNUM(I64) -> 3 | C64: =WEEKNUM(L64) -> 3 | E64: CR-0116544-00 | F64: Body | G64: VS30 | H64: William Naves | I64: 44571 | J64: 0.71527778 | K64: Marcelo Santos | L64: 44575 | N64: 1 aplicador TE para terminal 3202505N8 1 calha de selo Modelo Schleuniger para selo 320452667 1 calha de selo Modelo Schleuniger para selo 320453616 1 calha de selo Modelo Schleuniger para selo 3204542E9 2 validação de terminal conforme norma VS30
A65: =YEAR(L65) -> 2022 | B65: =WEEKNUM(I65) -> 4 | C65: =WEEKNUM(L65) -> 4 | E65: CR-0115662-02 | F65: IP | G65: GEM | H65: William Naves | I65: 44578 | J65: 0.42430556 | K65: Marcelo Santos | L65: 44581 | N65: Sem impacto de investimento para a CR
A66: =YEAR(L66) -> 2022 | B66: =WEEKNUM(I66) -> 3 | C66: =WEEKNUM(L66) -> 4 | E66: CR-0116994-00 | F66: Body | G66: GEM | H66: William Naves | I66: 44574 | J66: 0.43263889 | K66: Marcelo Santos | L66: 44581 | N66: 2 validações Multicrimp conforme norma USCAR 38 | O66: CR's com erros de informação, foi enviado um e-mail no dia 20/01/2022 para o Willian Naves relatando o problema quese encontrava nas CR's
A67: =YEAR(L67) -> 2022 | B67: =WEEKNUM(I67) -> 3 | C67: =WEEKNUM(L67) -> 4 | E67: CR-0117003-00 | F67: Body | G67: GEM | H67: William Naves | I67: 44574 | J67: 0.44027778 | K67: Marcelo Santos | L67: 44581 | N67: Sem impacto para corte e Lead Prep. condicionado á aprovação dos investimentos reportados na CR-0116994-00 | O67: CR's com erros de informação, foi enviado um e-mail no dia 20/01/2022 para o Willian Naves relatando o problema quese encontrava nas CR's
A68: =YEAR(L68) -> 2022 | B68: =WEEKNUM(I68) -> 3 | C68: =WEEKNUM(L68) -> 4 | E68: CR-0117008-00 | F68: Body | G68: GEM | H68: William Naves | I68: 44574 | J68: 0.45069444 | K68: Marcelo Santos | L68: 44581 | N68: Sem impacto para corte e Lead Prep. condicionado á aprovação dos investimentos reportados na CR-0116994-00 | O68: CR's com erros de informação, foi enviado um e-mail no dia 20/01/2022 para o Willian Naves relatando o problema quese encontrava nas CR's
A69: =YEAR(L69) -> 2022 | B69: =WEEKNUM(I69) -> 3 | C69: =WEEKNUM(L69) -> 4 | E69: CR-0117005-00 | F69: Body | G69: GEM | H69: William Naves | I69: 44574 | J69: 0.45416667 | K69: Marcelo Santos | L69: 44581 | N69: 2 validações Multicrimp conforme norma USCAR45 | O69: CR's com erros de informação, foi enviado um e-mail no dia 20/01/2022 para o Willian Naves relatando o problema quese encontrava nas CR's
A70: =YEAR(L70) -> 2022 | B70: =WEEKNUM(I70) -> 3 | C70: =WEEKNUM(L70) -> 4 | E70: CR-0116995-00 | F70: Body | G70: GEM | H70: William Naves | I70: 44574 | J70: 0.45833333 | K70: Marcelo Santos | L70: 44581 | N70: Sem impacto para corte e Lead Prep. condicionado a aprovação dos investimentos solicitados na CR-0116994-00. | O70: CR's com erros de informação, foi enviado um e-mail no dia 20/01/2022 para o Willian Naves relatando o problema quese encontrava nas CR's
A71: =YEAR(L71) -> 2022 | B71: =WEEKNUM(I71) -> 3 | C71: =WEEKNUM(L71) -> 4 | E71: CR-0116996-00 | F71: Body | G71: GEM | H71: William Naves | I71: 44574 | J71: 0.46111111 | K71: Marcelo Santos | L71: 44581 | N71: Sem impacto para corte e Lead Prep. condicionado a aprovação dos investimentos solicitados na CR-0116994-00. | O71: CR's com erros de informação, foi enviado um e-mail no dia 20/01/2022 para o Willian Naves relatando o problema quese encontrava nas CR's
A72: =YEAR(L72) -> 2022 | B72: =WEEKNUM(I72) -> 3 | C72: =WEEKNUM(L72) -> 4 | E72: CR-0117009-00 | F72: Body | G72: GEM | H72: William Naves | I72: 44574 | J72: 0.67361111 | K72: Marcelo Santos | L72: 44581 | N72: Sem impacto para corte e Lead Prep. condicionado a aprovação dos investimentos solicitados na CR-0116994-00.
A73: =YEAR(L73) -> 2022 | B73: =WEEKNUM(I73) -> 3 | C73: =WEEKNUM(L73) -> 4 | E73: CR-0117006-00 | F73: Body | G73: GEM | H73: William Naves | I73: 44575 | J73: 0.67708333 | K73: Marcelo Santos | L73: 44581 | N73: Sem impacto para corte e Lead Prep. condicionado a aprovação dos investimentos solicitados na CR-0116994-00.
A74: =YEAR(L74) -> 2022 | B74: =WEEKNUM(I74) -> 3 | C74: =WEEKNUM(L74) -> 4 | E74: CR-0117011-00 | F74: Body | G74: GEM | H74: William Naves | I74: 44575 | J74: 0.68333333 | K74: Marcelo Santos | L74: 44581 | N74: Sem impacto para corte e Lead Prep. condicionado a aprovação dos investimentos solicitados na CR-0116994-00. | O74: CR's com erros de informação, foi enviado um e-mail no dia 20/01/2022 para o Willian Naves relatando o problema quese encontrava nas CR's
A75: =YEAR(L75) -> 2022 | B75: =WEEKNUM(I75) -> 3 | C75: =WEEKNUM(L75) -> 4 | E75: CR-0117012-00 | F75: Body | G75: GEM | H75: William Naves | I75: 44575 | J75: 0.68958333 | K75: Marcelo Santos | L75: 44581 | N75: Sem impacto para corte e Lead Prep. condicionado a aprovação dos investimentos solicitados na CR-0116994-00. | O75: CR's com erros de informação, foi enviado um e-mail no dia 20/01/2022 para o Willian Naves relatando o problema quese encontrava nas CR's
A76: =YEAR(L76) -> 2022 | B76: =WEEKNUM(I76) -> 4 | C76: =WEEKNUM(L76) -> 4 | E76: CR-0116997-00 | F76: Body | G76: GEM | H76: William Naves | I76: 44578 | J76: 0.43194444 | K76: Marcelo Santos | L76: 44581 | N76: Sem impacto para corte e Lead Prep. condicionado a aprovação dos investimentos solicitados na CR-0116994-00. | O76: CR's com erros de informação, foi enviado um e-mail no dia 20/01/2022 para o Willian Naves relatando o problema quese encontrava nas CR's
A77: =YEAR(L77) -> 2022 | B77: =WEEKNUM(I77) -> 4 | C77: =WEEKNUM(L77) -> 4 | E77: CR-0116999-00 | F77: Body | G77: GEM | H77: William Naves | I77: 44578 | J77: 0.46111111 | K77: Marcelo Santos | L77: 44581 | N77: Sem impacto para corte e Lead Prep. condicionado a aprovação dos investimentos solicitados na CR-0116994-00.
A78: =YEAR(L78) -> 2022 | B78: =WEEKNUM(I78) -> 4 | C78: =WEEKNUM(L78) -> 4 | E78: CR-0117013-00 | F78: Body | G78: GEM | H78: William Naves | I78: 44578 | J78: 0.46111111 | K78: Marcelo Santos | L78: 44581 | N78: Sem impacto para corte e Lead Prep. condicionado a aprovação dos investimentos solicitados na CR-0116994-00. | O78: CR's com erros de informação, foi enviado um e-mail no dia 20/01/2022 para o Willian Naves relatando o problema quese encontrava nas CR's
A79: =YEAR(L79) -> 2022 | B79: =WEEKNUM(I79) -> 4 | C79: =WEEKNUM(L79) -> 4 | E79: CR-0117000-00 | F79: Body | G79: GEM | H79: William Naves | I79: 44578 | J79: 0.47013889 | K79: Marcelo Santos | L79: 44581 | N79: Sem impacto para corte e Lead Prep. condicionado a aprovação dos investimentos solicitados na CR-0116994-00. | O79: CR's com erros de informação, foi enviado um e-mail no dia 20/01/2022 para o Willian Naves relatando o problema quese encontrava nas CR's
A80: =YEAR(L80) -> 2022 | B80: =WEEKNUM(I80) -> 4 | C80: =WEEKNUM(L80) -> 4 | E80: CR-0117001-00 | F80: Body | G80: GEM | H80: William Naves | I80: 44578 | J80: 0.48888889 | K80: Marcelo Santos | L80: 44581 | N80: Sem impacto para corte e Lead Prep. condicionado a aprovação dos investimentos solicitados na CR-0116994-00. | O80: CR's com erros de informação, foi enviado um e-mail no dia 20/01/2022 para o Willian Naves relatando o problema quese encontrava nas CR's
A81: =YEAR(L81) -> 2022 | B81: =WEEKNUM(I81) -> 4 | C81: =WEEKNUM(L81) -> 4 | E81: CR-0117007-00 | F81: Body | G81: GEM | H81: William Naves | I81: 44578 | J81: 0.50069444 | K81: Marcelo Santos | L81: 44581 | N81: 2 validações Splice conforme norma USCAR45 | O81: CR's com erros de informação, foi enviado um e-mail no dia 20/01/2022 para o Willian Naves relatando o problema quese encontrava nas CR's
A82: =YEAR(L82) -> 2022 | B82: =WEEKNUM(I82) -> 0 | C82: =WEEKNUM(L82) -> 4 | E82: CR-0116544-01 | F82: Body | G82: GEM | H82: William Naves | K82: Paulo Lima | L82: 44581 | N82: 1 aplicador TE para terminal 3202505N8 1 calha de selo Modelo Schleuniger para selo 320452667 1 calha de selo Modelo Schleuniger para selo 320453616 1 calha de selo Modelo Schleuniger para selo 3204542E9 2 validação de terminal conforme norma VS30 | O82: Previsto entrar em abril /2022, foi enviado um e-mail da Aline Teodoro no dia 24/01/2022 as 13:50 sobre a planilha dos investimentos de scrap que será jogado fora para a implementação desta CR. Foi retirado os investimentos de calha de selo, devido a não ser um novo selo no projeto.
A83: =YEAR(L83) -> 2022 | B83: =WEEKNUM(I83) -> 4 | C83: =WEEKNUM(L83) -> 4 | E83: CR-0116842-00 | F83: Body | G83: GEM | H83: William Naves | I83: 44581 | J83: 0.70069444 | K83: Paulo Lima | L83: 44581 | O83: CR's com erros de informação, foi enviado um e-mail no dia 20/01/2022 para o Willian Naves relatando o problema quese encontrava nas CR's
A84: =YEAR(L84) -> 2022 | B84: =WEEKNUM(I84) -> 4 | C84: =WEEKNUM(L84) -> 4 | E84: CR-0116844-00 | F84: Body | G84: GEM | H84: William Naves | I84: 44581 | J84: 0.70416667 | K84: Paulo Lima | L84: 44581 | O84: CR's com erros de informação, foi enviado um e-mail no dia 20/01/2022 para o Willian Naves relatando o problema quese encontrava nas CR's
A85: =YEAR(L85) -> 2022 | B85: =WEEKNUM(I85) -> 4 | C85: =WEEKNUM(L85) -> 4 | E85: CR-0116845-00 | F85: Body | G85: GEM | H85: William Naves | I85: 44581 | J85: 0.70625 | K85: Paulo Lima | L85: 44581 | O85: CR's com erros de informação, foi enviado um e-mail no dia 20/01/2022 para o Willian Naves relatando o problema quese encontrava nas CR's
A86: =YEAR(L86) -> 2022 | B86: =WEEKNUM(I86) -> 4 | C86: =WEEKNUM(L86) -> 4 | E86: CR-0116847-00 | F86: Body | G86: GEM | H86: Naves, William da Silva | I86: 44579 | J86: 0.70833333 | K86: Paulo Lima | L86: 44581 | O86: CR's com erros de informação, foi enviado um e-mail no dia 20/01/2022 para o Willian Naves relatando o problema quese encontrava nas CR's
A87: =YEAR(L87) -> 2022 | B87: =WEEKNUM(I87) -> 4 | C87: =WEEKNUM(L87) -> 4 | E87: CR-0116848-00 | F87: Body | G87: GEM | H87: Naves, William da Silva | I87: 44579 | J87: 0.70833333 | K87: Paulo Lima | L87: 44581 | O87: CR's com erros de informação, foi enviado um e-mail no dia 20/01/2022 para o Willian Naves relatando o problema quese encontrava nas CR's
A88: =YEAR(L88) -> 2022 | B88: =WEEKNUM(I88) -> 4 | C88: =WEEKNUM(L88) -> 4 | E88: CR-0116849-00 | F88: Body | G88: GEM | H88: Naves, William da Silva | I88: 44579 | J88: 0.71458333 | K88: Paulo Lima | L88: 44581 | O88: CR's com erros de informação, foi enviado um e-mail no dia 20/01/2022 para o Willian Naves relatando o problema quese encontrava nas CR's
A89: =YEAR(L89) -> 2022 | B89: =WEEKNUM(I89) -> 4 | C89: =WEEKNUM(L89) -> 4 | E89: CR-0116851-00 | F89: Body | G89: GEM | H89: Naves, William da Silva | I89: 44579 | J89: 0.71597222 | K89: Paulo Lima | L89: 44581 | O89: CR's com erros de informação, foi enviado um e-mail no dia 20/01/2022 para o Willian Naves relatando o problema quese encontrava nas CR's
A90: =YEAR(L90) -> 2022 | B90: =WEEKNUM(I90) -> 4 | C90: =WEEKNUM(L90) -> 4 | E90: CR-0116852-00 | F90: Body | G90: GEM | H90: Naves, William da Silva | I90: 44579 | J90: 0.71875 | K90: Paulo Lima | L90: 44581 | O90: CR's com erros de informação, foi enviado um e-mail no dia 20/01/2022 para o Willian Naves relatando o problema quese encontrava nas CR's
A91: =YEAR(L91) -> 2022 | B91: =WEEKNUM(I91) -> 4 | C91: =WEEKNUM(L91) -> 4 | E91: CR-0116854-00 | F91: Body | G91: GEM | H91: Naves, William da Silva | I91: 44579 | J91: 0.72222222 | K91: Paulo Lima | L91: 44581 | O91: CR's com erros de informação, foi enviado um e-mail no dia 20/01/2022 para o Willian Naves relatando o problema quese encontrava nas CR's
A92: =YEAR(L92) -> 2022 | B92: =WEEKNUM(I92) -> 4 | C92: =WEEKNUM(L92) -> 4 | E92: CR-0116855-00 | F92: Body | G92: GEM | H92: Naves, William da Silva | I92: 44579 | J92: 0.72430556 | K92: Paulo Lima | L92: 44581 | O92: CR's com erros de informação, foi enviado um e-mail no dia 20/01/2022 para o Willian Naves relatando o problema quese encontrava nas CR's
A93: =YEAR(L93) -> 2022 | B93: =WEEKNUM(I93) -> 4 | C93: =WEEKNUM(L93) -> 4 | E93: CR-0115790-01 | F93: Body | G93: GEM | H93: Naves, William da Silva | I93: 44580 | J93: 0.32222222 | K93: Paulo Lima | L93: 44581 | O93: CR's com erros de informação, foi enviado um e-mail no dia 20/01/2022 para o Willian Naves relatando o problema quese encontrava nas CR's
A94: =YEAR(L94) -> 2022 | B94: =WEEKNUM(I94) -> 4 | C94: =WEEKNUM(L94) -> 4 | E94: CR-0117504-00 | F94: Body2021-02/SORP | G94: VS30 | H94: Naves, William da Silva | I94: 44581 | J94: 0.37083333 | K94: Paulo Lima | L94: 44582 | M94: 0.41319444 | N94: Sem necessidade de investimento (Replace connector 3216738C2 with 32165K41K. Change does not affect CUT and Labor.)
A95: =YEAR(L95) -> 2022 | B95: =WEEKNUM(I95) -> 4 | C95: =WEEKNUM(L95) -> 5 | E95: CR-0117505-00 | F95: Body2021-02/SORP | G95: VS30 | H95: Naves, William da Silva | I95: 44581 | J95: 0.37291667 | K95: Paulo Lima | L95: 44585 | M95: 0.30972222 | N95: Sem necessidade de investimetno ( apenas substituição da capa do terminal)
A96: =YEAR(L96) -> 2022 | B96: =WEEKNUM(I96) -> 4 | C96: =WEEKNUM(L96) -> 5 | E96: CR-0117530-00 | F96: Body2021-02/SORP | G96: VS30 | H96: Naves, William da Silva | I96: 44581 | J96: 0.37638889 | K96: Paulo Lima | L96: 44585 | M96: 0.36111111 | N96: Sem necessidade de investimento( troca apenas alguns fios de módulo)
A97: =YEAR(L97) -> 2022 | B97: =WEEKNUM(I97) -> 4 | C97: =WEEKNUM(L97) -> 5 | E97: CR-0117536-00 | F97: Body2021-02/SORP | G97: VS30 | H97: Naves, William da Silva | I97: 44581 | J97: 0.38333333 | K97: Paulo Lima | L97: 44585 | M97: 0.42083333 | N97: Sem necessidade de investimento( troca apenas alguns fios de módulo)
A98: =YEAR(L98) -> 2022 | B98: =WEEKNUM(I98) -> 4 | C98: =WEEKNUM(L98) -> 5 | E98: CR-0117699-00 | F98: Body2021-02/SORP | G98: VS30 | H98: Naves, William da Silva | I98: 44581 | J98: 0.68263889 | K98: Paulo Lima | L98: 44585 | M98: 0.4375 | N98: Troca do terminal de E03457800 para 320272164 ( necessidade de compra de uma ferramenta para aplicação do novo terminal)e necessidade de duas vlidações
A99: =YEAR(L99) -> 2022 | B99: =WEEKNUM(I99) -> 4 | C99: =WEEKNUM(L99) -> 5 | E99: CR-0115566-01 | F99: Body–MY2023/MVBS | G99: GEM | H99: Naves, William da Silva | I99: 44579 | J99: 0.69652778 | K99: Marcelo Santos | L99: 44585 | M99: 0.45833333 | N99: Sem impacto para corte e Lead Prep. Observação considerando utilização do circuito antigo como stock use.
A100: =YEAR(L100) -> 2022 | B100: =WEEKNUM(I100) -> 4 | C100: =WEEKNUM(L100) -> 5 | E100: CR-0115790-01 | F100: Body–MY2023/MVBS | G100: GEM | H100: Naves, William da Silva | I100: 44580 | K100: Marcelo Santos | L100: 44585 | M100: 0.50416667 | N100: CR reprovada, delta Cutsheet não reflete alteração. Está mudando Clip, porém na Cutsheet está mudando splice e multcrimp
...

Sheet Prioridades resposta
A1: prioricade | B1: Programa | C1: Status Planta | D1: CR # | E1: Data Submissão SEM | F1: Envio da CR p/ análise | G1: Fase | H1: MY | I1: Nº Doc | J1: CR "On Hold"? | K1: Status Cotações | L1: Status Produto | M1: Status Processos | N1: Status Meios Montagem | O1: Status Teste Elétrico | P1: Status Corte & Lead Prep | Q1: Status Qualidade | R1: Dias com Eng. Cotações
B2: GEM | C2: Pendente | D2: CR-0183330-00 | E2: 45449 | F2: 45449 | H2: 2025 | I2: Não | J2: Não | K2: OK | L2: OK | M2: OK | N2: OK | O2: OK | P2: OK | Q2: LATE | R2: 24 | S2: =VLOOKUP(D2,'Controle de CR'!E:E,1,0) -> CR-0183330-00
B3: SPIN | C3: Pendente | D3: CR-0185339-00 | E3: 45477 | F3: 45477 | H3: 2025 | I3: Não | J3: Não | K3: OK | L3: OK | M3: OK | N3: OK | O3: OK | P3: LATE | Q3: LATE | R3: 13 | S3: =VLOOKUP(D3,'Controle de CR'!E:E,1,0) -> CR-0185339-00
B4: SPIN | C4: Pendente | D4: CR-0185493-00 | E4: 45481 | F4: 45481 | H4: 2025 | I4: Não | J4: Não | K4: OK | L4: N/A | M4: OK | N4: OK | O4: OK | P4: LATE | Q4: LATE | R4: 8 | S4: =VLOOKUP(D4,'Controle de CR'!E:E,1,0) -> CR-0185493-00
B5: VS30 | C5: Pendente | D5: CR-0190308-00 | E5: 45488 | F5: 45488 | H5: 2024_1 | I5: Não | J5: Não | K5: OK | L5: N/A | M5: OK | N5: OK | O5: OK | P5: LATE | Q5: LATE | R5: 6 | S5: =VLOOKUP(D5,'Controle de CR'!E:E,1,0) -> CR-0190308-00
B6: VS30 | C6: Pendente | D6: CR-0190391-00 | E6: 45490 | F6: 45490 | H6: 2024_1 | I6: Não | J6: Não | K6: OK | L6: OK | M6: ON TIME | N6: OK | O6: OK | P6: ON TIME | Q6: ON TIME | R6: 3 | S6: =VLOOKUP(D6,'Controle de CR'!E:E,1,0) -> CR-0190391-00

Sheet My23.2Vs30
A1: Ano | B1: Recebida Week | C1: Respondida Week | D1: DCN | E1: CR | F1: IP | G1: Projeto | H1: Nome Resp. CR | I1: Data | J1: Hora | K1: Avaliado | L1: Data | M1: Hora | N1: EQUIPAMENTO | O1: LEAD TIME | P1: Restrição | Q1: OBSERVAÇÃO | R1: Inicio do processo | S1: envio de DT e VT | T1: Liberação | U1: Nº RC | V1: Nº PO | W1: APORVAÇÃO DE DT e VT | X1: REQUISIÇÃO | Y1: PO | Z1: DATA DE CEGADA | AA1: VALIDAÇÃO | AB1: APROVAÇÃO DA VALIDAÇÃO | AC1: ENVIO PARA QUALIDADE | AD1: Data de Entrega
E2: CR-0161055-00 | F2: VS30 – SORP – 2023_02 Família: IP WH Tipo: Release Número: VAT2523 | G2: VS30 | H2: Militani, Marcio Pericles | I2: 45156 | J2: 0.35833333 | K2: Marcelo Santos | L2: 45174 | M2: 0.67222222 | N2: Aplicadores | O2: 70 | P2: NOVO | Q2: Aplicador para terminal E09996900 ( 927829-5 ) | R2: =AD2-O2 -> 45203 | S2: enviado para aprovação dia quar 13/12/2023 13:04 | T2: liberado pela Aline dia qua 13/12/2023 15:02 | AD2: 45273
E3: CR-0161055-00 | F3: VS30 – SORP – 2023_02 Família: IP WH Tipo: Release Número: VAT2523 | G3: VS30 | H3: Militani, Marcio Pericles | I3: 45156 | J3: 0.35833333 | K3: Marcelo Santos | L3: 45174 | M3: 0.67222222 | N3: Validações | O3: 60 | P3: NOVO | Q3: 1 validação de terminais E09996900 conforme Norma VS30. | R3: =AD3-O3 -> 45213 | AD3: 45273
E4: CR-0161055-00 | F4: VS30 – SORP – 2023_02 Família: IP WH Tipo: Release Número: VAT2523 | G4: VS30 | H4: Militani, Marcio Pericles | I4: 45156 | J4: 0.35833333 | K4: Marcelo Santos | L4: 45174 | M4: 0.67222222 | N4: Aplicadores | O4: 70 | P4: NOVO | Q4: 1 Aplicador para Terminal Splice CLIP E40086800 | R4: =AD4-O4 -> 45275 | S4: OK | W4: Aprovado para o terminal E40086800 (11/12/2023 às 09:11) | AD4: 45345
A5: 2023 | B5: 33 | C5: 36 | E5: CR-0161055-00 | F5: VS30 – SORP – 2023_02 Família: IP WH Tipo: Release Número: VAT2523 | G5: VS30 | H5: Militani, Marcio Pericles | I5: 45156 | J5: 0.35833333 | K5: Marcelo Santos | L5: 45174 | M5: 0.67222222 | N5: Validações | O5: 60 | P5: NOVO | Q5: 1 validação de terminais Splice CLIP E40086800 Norma VS30. | R5: =AD5-O5 -> 45285 | AD5: 45345
E6: CR-0161055-00 | F6: VS30 – SORP – 2023_02 Família: IP WH Tipo: Release Número: VAT2523 | G6: VS30 | H6: Militani, Marcio Pericles | I6: 45156 | J6: 0.35833333 | K6: Marcelo Santos | L6: 45174 | M6: 0.67222222 | N6: Prensa | O6: 90 | P6: Retrofit CAM | Q6: 1 Prensa mecal de 4 Toneladas com adequação NR12 para Aplicação Terminal Splice CLIP E40086800 (SPLC CLIP,Cu CORE,Sn PLT,390275) | R6: =AD6-O6 -> 45255 | S6: enviado para aprovação dia quar 13/12/2023 13:04 | AD6: 45345
E7: CR-0161082-00 | F7: CR-0161082-00 - Body | G7: VS30 | H7: Militani, Marcio Pericles | I7: 45177 | J7: 0.68472222 | K7: Marcelo Santos | L7: 45183 | M7: 0.75902778 | N7: Aplicadores | O7: 70 | P7: DUPLICAÇÃO | Q7: 1 aplicador TE para terminal E03732200 ( diversidade de Circuitos ) | R7: =AD7-O7 -> 45275 | S7: enviado para aprovação dia quar 13/12/2023 13:04 | T7: liberado pela Aline dia qua 13/12/2023 15:02 | AD7: 45345
E8: CR-0161082-00 | F8: CR-0161082-00 - Body | G8: VS30 | H8: Militani, Marcio Pericles | I8: 45177 | J8: 0.68472222 | K8: Marcelo Santos | L8: 45183 | M8: 0.75902778 | N8: Aplicadores | O8: 70 | P8: DUPLICAÇÃO | Q8: 1 aplicador TE para terminal 3202581Z7 ( diversidade de Circuitos ) | R8: =AD8-O8 -> 45275 | S8: enviado para aprovação dia quar 13/12/2023 13:04 | T8: liberado pela Aline dia qua 13/12/2023 15:02 | AD8: 45345
E9: CR-0161082-00 | F9: CR-0161082-00 - Body | G9: VS30 | H9: Militani, Marcio Pericles | I9: 45177 | J9: 0.68472222 | K9: Marcelo Santos | L9: 45183 | M9: 0.75902778 | N9: Aplicadores | O9: 70 | P9: DUPLICAÇÃO | Q9: 1 aplicador TE para terminal E04004100 ( diversidade de Circuitos ) | R9: =AD9-O9 -> 45275 | S9: enviado para aprovação dia quar 13/12/2023 13:04 | T9: liberado pela Aline dia qua 13/12/2023 15:02 | AD9: 45345
E10: CR-0161082-00 | F10: CR-0161082-00 - Body | G10: VS30 | H10: Militani, Marcio Pericles | I10: 45177 | J10: 0.68472222 | K10: Marcelo Santos | L10: 45183 | M10: 0.75902778 | N10: Aplicadores | O10: 70 | P10: DUPLICAÇÃO | Q10: 1 aplicador TE para terminal E04848200 ( diversidade de Circuitos ) | R10: =AD10-O10 -> 45275 | S10: enviado para aprovação dia quar 13/12/2023 13:04 | T10: liberado pela Aline dia qua 13/12/2023 15:02 | AD10: 45345
A11: 2023 | B11: 34 | C11: 37 | E11: CR-0161091-00 | F11: Projeto: VS30 – SORP – 2023_02 Família: BODY Tipo: Release Número: VAT2623 | G11: VS30 | H11: Militani, Marcio Pericles | I11: 45159 | J11: 0.58194444 | K11: Marcelo Santos | L11: 45184 | M11: 0.3875 | N11: N/A | O11: 30 | P11: - | Q11: Sem impacto para corte e Lead Prep. Condicionado ao investimentos reportado na CR-0161082-00. | R11: =AD11-O11 -> -30
A12: 2023 | B12: 34 | C12: 37 | E12: CR-0161100-00 | F12: VS30 – SORP – 2023_02 Família: BODY Tipo: Release Número: VAT2623 | G12: VS30 | H12: Militani, Marcio Pericles | I12: 45159 | J12: 0.58541667 | K12: Marcelo Santos | L12: 45184 | M12: 0.38958333 | N12: N/A | O12: 30 | P12: - | Q12: Sem impacto para corte e Lead Prep. Condicionado ao investimentos reportado na CR-0161082-00. | R12: =AD12-O12 -> -30
A13: 2023 | B13: 34 | C13: 37 | E13: CR-0161150-00 | F13: VS30 – SORP – 2023_02 Família: BODY Tipo: Release Número: VAT2623 | G13: VS30 | H13: Militani, Marcio Pericles | I13: 45159 | J13: 0.71875 | K13: Marcelo Santos | L13: 45184 | M13: 0.39097222 | N13: N/A | O13: 30 | P13: - | Q13: Sem impacto para corte e Lead Prep. Condicionado ao investimentos reportado na CR-0161082-00. | R13: =AD13-O13 -> -30
A14: 2023 | B14: 34 | C14: 37 | E14: CR-0161274-00 | F14: VS30 – SORP – 2023_02 Família: BODY Tipo: Release Número: VAT2623 | G14: VS30 | H14: Militani, Marcio Pericles | I14: 45160 | J14: 0.70347222 | K14: Marcelo Santos | L14: 45184 | M14: 0.39236111 | N14: N/A | O14: 30 | P14: - | Q14: Sem impacto para corte e Lead Prep. Condicionado ao investimentos reportado na CR-0161082-00. | R14: =AD14-O14 -> -30
A15: 2023 | B15: 34 | C15: 37 | E15: CR-0161281-00 | F15: VS30 – SORP – 2023_02 Família: BODY Tipo: Release Número: VAT2623 | G15: VS30 | H15: Militani, Marcio Pericles | I15: 45162 | J15: 0.41180556 | K15: Marcelo Santos | L15: 45184 | M15: 0.39583333 | N15: N/A | O15: 30 | P15: - | Q15: Sem impacto para corte e Lead Prep. Condicionado ao investimentos reportado na CR-0161082-00. | R15: =AD15-O15 -> -30
A16: 2023 | B16: 34 | C16: 37 | E16: CR-0161391-00 | F16: VS30 – SORP – 2023_02 Família: BODY Tipo: Release Número: VAT2623 | G16: VS30 | H16: Militani, Marcio Pericles | I16: 45162 | J16: 0.39166667 | K16: Marcelo Santos | L16: 45184 | M16: 0.39861111 | N16: N/A | O16: 30 | P16: - | Q16: Sem impacto para corte e Lead Prep. Condicionado ao investimentos reportado na CR-0161082-00. | R16: =AD16-O16 -> -30
A17: 2023 | B17: 35 | C17: 37 | E17: CR-0161685-00 | F17: VS30 – SORP – 2023_02 Família: BODY Tipo: Release Número: VAT2623 | G17: VS30 | H17: Militani, Marcio Pericles | I17: 45170 | J17: 0.69930556 | K17: Marcelo Santos | L17: 45184 | M17: 0.4 | N17: N/A | O17: 30 | P17: - | Q17: Sem impacto para corte e Lead Prep. Condicionado ao investimentos reportado na CR-0161082-00. | R17: =AD17-O17 -> -30
A18: 2023 | B18: 35 | C18: 37 | E18: CR-0162023-00 | F18: VS30 – SORP – 2023_02 Família: BODY Tipo: Release Número: VAT2623 | G18: VS30 | H18: Militani, Marcio Pericles | I18: 45170 | J18: 0.71180556 | K18: Marcelo Santos | L18: 45184 | M18: 0.40138889 | N18: N/A | O18: 30 | P18: - | Q18: Sem impacto para corte e Lead Prep. Condicionado ao investimentos reportado na CR-0161082-00. | R18: =AD18-O18 -> -30
A19: 2023 | B19: 36 | C19: 37 | E19: CR-0161685-01 | F19: VS30 – SORP – 2023_02 Família: BODY Tipo: Release Número: VAT2623 | G19: VS30 | H19: Militani, Marcio Pericles | I19: 45177 | J19: 0.67569444 | K19: Marcelo Santos | L19: 45184 | M19: 0.40347222 | N19: N/A | O19: 30 | P19: - | Q19: Sem impacto para corte e Lead Prep. Condicionado ao investimentos reportado na CR-0161082-00. | R19: =AD19-O19 -> -30
A20: 2023 | B20: 37 | C20: 37 | E20: CR-0162605-00 | F20: VS30 – SORP – 2023_02 Família: BODY Tipo: Release Número: VAT2623 | G20: VS30 | H20: Militani, Marcio Pericles | I20: 45180 | J20: 0.66944444 | K20: Marcelo Santos | L20: 45184 | M20: 0.40486111 | N20: N/A | O20: 30 | P20: - | Q20: Sem impacto para corte e Lead Prep. Condicionado ao investimentos reportado na CR-0161082-00. | R20: =AD20-O20 -> -30
A21: 2023 | B21: 35 | C21: 37 | E21: CR-0161852-00 | F21: VS30 – SORP – 2023_02 Família: BODY Tipo: PFD Número: PFD-VS30-BR907-AEHJ2023_02-2438w | G21: VS30 | H21: Militani, Marcio Pericles | I21: 45169 | J21: 0.42152778 | K21: Marcelo Santos | L21: 45184 | N21: N/A | O21: 30 | P21: - | Q21: Considerar sem impacto para corte e Lead Prep. Scrap R$ 1.667,87 | R21: =AD21-O21 -> -30
A22: 2023 | B22: 35 | C22: 37 | E22: CR-0161862-00 | F22: VS30 – SORP – 2023_02 Família: BODY Tipo: PFD Número: PFD-VS30-BR907-AEHJ2023_02-2437w | G22: VS30 | H22: Militani, Marcio Pericles | I22: 45169 | J22: 0.42430556 | K22: Marcelo Santos | L22: 45184 | M22: 0.5875 | N22: N/A | O22: 30 | P22: - | Q22: Considerar sem impacto para corte e Lead Prep. | R22: =AD22-O22 -> -30
E23: CR-0161082-00 | F23: CR-0161082-00 - Body | G23: VS30 | H23: Militani, Marcio Pericles | I23: 45177 | J23: 0.68472222 | K23: Marcelo Santos | L23: 45183 | M23: 0.75902778 | O23: 30 | P23: - | Q23: 2 caixas de Poleaseal | R23: =AD23-O23 -> -30
A24: 2023 | B24: 34 | C24: 36 | E24: CR-0161083-00 | F24: BODY Tipo: Release Número: VAT2623 | G24: VS30 | H24: Militani, Marcio Pericles | I24: 45159 | J24: 0.56805556 | K24: Marcelo Santos | L24: 45174 | M24: 0.38055556 | O24: 30 | P24: - | Q24: Considerar sem impacto para corte e Lead Prep. Scrap R$ 954,68 | R24: =AD24-O24 -> -30 | S24: N/A | W24: N/A | X24: N/A
A25: 2023 | B25: 36 | C25: 37 | E25: CR-0161082-00 | F25: CR-0161082-00 - Body | G25: VS30 | H25: Militani, Marcio Pericles | I25: 45177 | J25: 0.68472222 | K25: Marcelo Santos | L25: 45183 | M25: 0.75902778 | O25: 30 | P25: - | Q25: 8 rolos de dupla Face | R25: =AD25-O25 -> -30
A26: 2023 | B26: 35 | C26: 37 | E26: CR-0161865-00 | F26: VS30 – SORP – 2023_02 Família: BODY Tipo: PFD Número: PFD-VS30-BR907-AEHJ2023_02-2435w | G26: VS30 | H26: Militani, Marcio Pericles | I26: 45169 | J26: 0.42708333 | K26: Marcelo Santos | L26: 45184 | M26: 0.59583333 | O26: 30 | Q26: Sem impacto para corte e Lead prep. Considerar apenas Scrap devido alteração de comprimento Scrap R$ R$ 1.327,11 | R26: =AD26-O26 -> -30
A27: 2023 | B27: 38 | C27: 39 | E27: CR-0163101-00 | F27: VS30 – SORP – 2023_02 Família: IP WH Tipo: PFD Número: PFD-VS30-BR907-AEHJ2023_02-2433w | G27: VS30 | H27: Militani, Marcio Pericles | I27: 45188 | J27: 0.34444444 | K27: Marcelo Santos | L27: 45197 | M27: 0.73819444 | N27: Equipamento | O27: 90 | P27: DUPLICAÇÃO | Q27: 1 máquina de decape (Komax MIRA ) aproximadamente R$56.500,00 ( investimento necessário para garantir corte do dreno e do cabo marrom no comprimento correto vide anexo ) Scrap. R$ 623,00 | R27: =AD27-O27 -> -90
A28: 2023 | B28: 42 | C28: 43 | E28: CR-0164538-01 | F28: VS30 – SORP – 2023_02 Família: BODY Tipo: PFD Número: PFD-VS30-BR907-AEHJ2023_02-2518 | G28: VS30 | H28: Militani, Marcio Pericles | I28: 45215 | J28: 0.41319444 | K28: Marcelo Santos | L28: 45222 | M28: 0.77013889 | N28: Aplicadores | O28: 70 | P28: DUPLICAÇÃO | Q28: 1 aplicador TE para terminal E00309500.( para uso no lead Prep. Seal Crimp ) Lead Time após liberação da Verba. 78 dias | R28: =AD28-O28 -> -70 | S28: enviado para cotação dia 11/12/2023 às 13:35 h.
A29: 2023 | B29: 42 | C29: 43 | E29: CR-0165462-00 | F29: VS30 – SORP – 2023_02 Família: BODY Tipo: PFD Número: PFD-VS30-BR907-AEHJ2023_02-2434w | G29: VS30 | H29: Militani, Marcio Pericles | I29: 45215 | J29: 0.41597222 | K29: Marcelo Santos | L29: 45224 | M29: 0.62222222 | N29: N/A | Q29: Considerar sem impacto para corte e lead Prep.( Analise feita Base delta Cut disponibilizado.) Alteração comprimento dos Circuitos novos MC7301B, 7404B e 7405B VS30 – SORP – 2023_02. | R29: =AD29-O29 -> 0
A30: 2023 | B30: 43 | C30: 45 | E30: CR-0166091-00 | F30: VS30 – SORP – 2023_02 Família: BODY Tipo: PFD Número: PFD-VS30-BR907-AEHJ2023_02-2533 | G30: VS30 | H30: Militani, Marcio Pericles | I30: 45224 | J30: 0.58958333 | K30: Marcelo Santos | L30: 45241 | M30: 0.31388889 | N30: N/A | Q30: Considerar sem impacto para corte e Lead Prep. Analise feita base documentos fornecido na CR, PFD-VS30-BR907-AEHJ2023_02-2533_LU, BOM-COMPARISON_A9070014899_B04_10107 e DELTA-LABOR-R_A9070014899_B04_10107. | R30: =AD30-O30 -> 0
A31: 2023 | B31: 43 | C31: 45 | E31: CR-0166250-00 | F31: VS30 – SORP – 2023_02 Família: IP WH Tipo: PFD Número: PFD-VS30-BR907-AEHJ2023_02-2533 Assunto: 1. VS30 - WIRING HARNESS IP , 2. PFD-VS30-BR907-AEHJ2023_02-2500 | G31: VS30 | H31: Militani, Marcio Pericles | I31: 45224 | J31: 0.59305556 | K31: Marcelo Santos | L31: 45241 | M31: 0.40416667 | N31: N/A | Q31: Considerar Sem impacto par corte e lead Prep. Analise feita base documentação disponibilizado na CR, BOM-COMPARISON_A9070011599_B05_10120, PFD-VS30-BR907-AEHJ2023_02-2500_LU e DELTA-LABOR_A9070011599_B05_10120 | R31: =AD31-O31 -> 0
A32: 2023 | B32: 43 | C32: 45 | E32: CR-0166494-00 | F32: VS30 – SORP – 2023_02 Família: IP WH Tipo: Issue Número: NA | G32: VS30 | H32: Militani, Marcio Pericles | I32: 45225 | J32: 0.60416667 | K32: Marcelo Santos | L32: 45241 | N32: Validações | O32: 60 | Q32: 1 Validação de crimpagem conforme Norma VS30. conforme informação O fornecedor estou considerando que vamos utilizar mesmo aplicador do terminal 32025YFU. Mesmo Aplicador | R32: =AD32-O32 -> -60
E33: CR-0165593-00 | F33: VS30 – SORP – 2023_02 Família: BODY Tipo: Release Número: VAT2623 Assunto: 1. Release of new | G33: vS30 | H33: Militani, Marcio Pericles | I33: 45240 | J33: 0.51736111 | K33: Marcelo Santos | L33: 45261 | M33: 0.51805556 | N33: Aplicadores | O33: 70 | P33: DUPLICAÇÃO | Q33: 1 aplicador TE para terminal E03355600. ( Será Usado No Lead Prep. necessário devido conflito entre os processos de Corte e lead Prep.) | R33: =AD33-O33 -> -70 | S33: enviado para cotação dia 11/12/2023 às 13:35 h.
E34: CR-0165593-00 | F34: VS30 – SORP – 2023_02 Família: BODY Tipo: Release Número: VAT2623 Assunto: 1. Release of new | G34: vS30 | H34: Militani, Marcio Pericles | I34: 45240 | J34: 0.51736111 | K34: Marcelo Santos | L34: 45261 | M34: 0.51805556 | N34: Aplicadores | O34: 70 | P34: DUPLICAÇÃO | Q34: 1 aplicador TE para terminal E03999200. ( Será Usado No Lead Prep. necessário devido conflito entre os processos de Corte e lead Prep.) | R34: =AD34-O34 -> -70 | S34: enviado para cotação dia 11/12/2023 às 13:35 h.
E35: CR-0165593-00 | F35: VS30 – SORP – 2023_02 Família: BODY Tipo: Release Número: VAT2623 Assunto: 1. Release of new | G35: vS30 | H35: Militani, Marcio Pericles | I35: 45240 | J35: 0.51736111 | K35: Marcelo Santos | L35: 45261 | M35: 0.51805556 | N35: Aplicadores | O35: 70 | P35: DUPLICAÇÃO | Q35: 1 aplicador TE para terminal E04004100. ( Usado no dois lados dos circuitos temos apenas 1 Aplicador ) | R35: =AD35-O35 -> -70 | S35: enviado para cotação dia 11/12/2023 às 13:35 h.
E36: CR-0165593-00 | F36: VS30 – SORP – 2023_02 Família: BODY Tipo: Release Número: VAT2623 Assunto: 1. Release of new | G36: vS30 | H36: Militani, Marcio Pericles | I36: 45240 | J36: 0.51736111 | K36: Marcelo Santos | L36: 45261 | M36: 0.51805556 | N36: Aplicadores | O36: 70 | P36: DUPLICAÇÃO | Q36: 1 Aplicador TE para terminal E04848200. ( Devido Acréscimo de circuitos acima de 8.000mm será distribuído para Maquina Coiler CC64 ) | R36: =AD36-O36 -> -70 | S36: enviado para cotação dia 11/12/2023 às 13:35 h.
E37: CR-0165593-00 | F37: VS30 – SORP – 2023_02 Família: BODY Tipo: Release Número: VAT2623 Assunto: 1. Release of new | G37: vS30 | H37: Militani, Marcio Pericles | I37: 45240 | J37: 0.51736111 | K37: Marcelo Santos | L37: 45261 | M37: 0.51805556 | N37: N/A | Q37: 1 caixa de Polaseal | R37: =AD37-O37 -> 0
E38: CR-0165593-00 | F38: VS30 – SORP – 2023_02 Família: BODY Tipo: Release Número: VAT2623 Assunto: 1. Release of new | G38: vS30 | H38: Militani, Marcio Pericles | I38: 45240 | J38: 0.51736111 | K38: Marcelo Santos | L38: 45261 | M38: 0.51805556 | N38: N/A | Q38: 1 rolo de papel contact. | R38: =AD38-O38 -> 0
A39: 2023 | B39: 45 | C39: 48 | E39: CR-0165593-00 | F39: VS30 – SORP – 2023_02 Família: BODY Tipo: Release Número: VAT2623 Assunto: 1. Release of new | G39: vS30 | H39: Militani, Marcio Pericles | I39: 45240 | J39: 0.51736111 | K39: Marcelo Santos | L39: 45261 | M39: 0.51805556 | N39: N/A | Q39: 1 rolo de Dupla Face | R39: =AD39-O39 -> 0
A40: 2023 | B40: 46 | C40: 49 | E40: CR-0167911-00 | F40: VS30 – SORP – 2023_02 Família: IP WH Tipo: Release Número: VAT2523 | G40: VS30 | H40: Militani, Marcio Pericles | I40: 45246 | J40: 0.68125 | K40: Marcelo Santos | L40: 45268 | M40: 0.60347222 | N40: N/A | Q40: Considerar sem impacto para corte e Lead Prep. | R40: =AD40-O40 -> 0

Sheet Aplicadores MY26
C2: Aplicadores/calhas | D2: Disponivel | E2: Maqs GEM | F2: Carga hrs Gem | G2: Voume dia | H2: Delta | I2: Compra | J2: MY
C3: 32025Y2XV | D3: 0 | E3: 2 | F3: 2.0867029 | G3: 6644.7276 | H3: -2 | I3: 1 | K3: CR-0171416-00 BODY CARBON | M3: CR-0166437-01 BODY | N3: Não Pedir carbon
C4: E04648500 | D4: 0 | E4: 2 | F4: 1.1342066 | G4: 3151.7668 | H4: -2 | I4: 1 | K4: CR-0171416-00 BODY CARBON
C5: E00166100 | D5: 0 | E5: 3 | F5: 1.3960154 | G5: 2410.0197 | H5: -3 | I5: 1 | K5: CR-0171416-00 BODY CARBON | M5: CR-0166437-01 BODY | N5: Não Pedir
C6: E00020633 | D6: 0 | E6: 3 | F6: 0.82667419 | G6: 1493.4207 | H6: -3 | I6: 1 | K6: CR-0171416-00 BODY CARBON | M6: CR-0166437-01 BODY | N6: Não Pedir
C7: 320298235 | D7: 1 | E7: 2 | F7: 0.34074897 | G7: 1192.9199 | H7: -1 | I7: 1 | K7: CR-0171416-00 BODY CARBON | L7: Obsoleto desmontado
C8: E01080600 | D8: 0 | E8: 0 | F8: 0 | G8: 0 | H8: 0 | I8: 1 | K8: CR-0171595-00 IP HARNESS carbon
C9: E05869700 | D9: 0 | E9: 0 | F9: 0 | G9: 0 | H9: 0 | I9: 1 | K9: CR-0171595-00 IP HARNESS carbon
C10: 320298243 | D10: 1 | E10: 0 | F10: 0 | G10: 0 | H10: 1 | I10: 1 | K10: CR-0171595-00 IP HARNESS carbon
C11: 32025Y19G | D11: 0 | E11: 0 | F11: 0 | G11: 5400 | H11: 0 | I11: 1 | K11: CR-0171595-00 IP HARNESS carbon | L11: Desmontado
C12: E27713500 | D12: 0 | E12: =VLOOKUP(C12,'[1]Distr.Aplicadores GEM'!$A:$B,2,0) -> 0 | F12: =VLOOKUP(C12,'[1]Distr.Aplicadores GEM'!$A:$H,8,0) -> 0 | G12: 2244.7614 | H12: =D12-E12 -> 0 | I12: 1 | K12: CR-0171785-01 Rear Lamp Carbon | M12: CR-0162211-00 IP | N12: Não Pedir
C13: E27713500 | D13: 0 | E13: 1 | F13: 0.6393524 | G13: 2244.7614 | H13: -1 | I13: 1 | K13: CR-0171817-01 Liftgate Carbon | M13: CR-0162211-00 IP | N13: Não Pedir
C14: 3202563E7 | D14: 0 | E14: 1 | G14: 0 | H14: -1 | I14: 1 | K14: CR-0171817-01 Liftgate Carbon
C15: E16318100 | D15: 2 | E15: 4 | F15: 7.0213813 | G15: 15940 | H15: -2 | I15: 1 | K15: CR-0172035-00 Liftgate Ext CARBON
C16: E00006853 | D16: 0 | E16: 0 | F16: 0 | G16: 0 | H16: 0 | I16: 1 | K16: CR-0172035-00 Liftgate Ext CARBON
C17: E16491700 | D17: 0 | E17: 0 | F17: 0 | G17: 0 | H17: 0 | I17: 1 | K17: CR-0172035-00 Liftgate Ext CARBON
C18: 3202535K9 | D18: 0 | E18: 0 | F18: 0 | G18: 0 | H18: 0 | I18: 1 | K18: CR-0172035-00 Liftgate Ext CARBON
C19: 32025Y1CW | D19: 0 | E19: 0 | F19: 0 | G19: 0 | H19: 0 | I19: 1 | K19: CR-0172035-00 Liftgate Ext CARBON
C20: 32025Y20B | D20: 0 | E20: 0 | F20: 0 | G20: 0 | H20: 0 | I20: 1 | K20: CR-0172352-00 Front Bumper Carbon
C21: 3202501G8 | D21: 0 | E21: 0 | F21: 0 | G21: 0 | H21: 0 | I21: 1 | J21: 2026 | K21: CR-0162211-00 IP
C22: E32673300 | D22: 0 | E22: 0 | F22: 0 | G22: 0 | H22: 0 | I22: 1 | J22: 2026 | K22: CR-0162211-00 IP
C23: 32025Y36A | D23: 0 | E23: 0 | F23: 0 | G23: 0 | H23: 0 | I23: 1 | J23: 2026 | K23: CR-0162211-00 IP
C24: E27713500 | D24: 0 | E24: 0 | F24: 0 | G24: 0 | H24: 0 | I24: 1 | J24: 2026 | K24: CR-0162211-00 IP
C25: 3204505B1 | D25: 0 | E25: 0 | F25: 0 | G25: 0 | H25: 0 | I25: 5 | J25: 2026 | K25: CR-0166437-01 BODY
C26: 320452329 | D26: 0 | E26: 0 | F26: 0 | G26: 0 | H26: 0 | I26: 1 | J26: 2026 | K26: CR-0166437-01 BODY
C27: 320455AKQ | D27: 0 | E27: 0 | F27: 0 | G27: 0 | H27: 0 | I27: 1 | J27: 2026 | K27: CR-0166437-01 BODY
C28: E37621700 | D28: 0 | E28: 0 | F28: 0 | G28: 0 | H28: 0 | I28: 1 | J28: 2026 | K28: CR-0166437-01 BODY
C29: E00020633 | D29: 0 | E29: 0 | F29: 0 | G29: 0 | H29: 0 | I29: 1 | J29: 2026 | K29: CR-0166437-01 BODY
C30: E00166100 | D30: 0 | E30: 0 | F30: 0 | G30: 0 | H30: 0 | I30: 1 | J30: 2026 | K30: CR-0166437-01 BODY
C31: 3202502F9 | D31: 0 | E31: 0 | F31: 0 | G31: 0 | H31: 0 | I31: 1 | J31: 2026 | K31: CR-0166437-01 BODY
C32: 320263VT6 | D32: 0 | E32: 0 | F32: 0 | G32: 0 | H32: 0 | I32: 1 | J32: 2026 | K32: CR-0166437-01 BODY
C33: 32025Y2XV | D33: 0 | E33: 0 | F33: 0 | G33: 0 | H33: 0 | I33: 1 | J33: 2026 | K33: CR-0166437-01 BODY
C34: 3299571G9 | K34: CR-0171416-00 BODY CARBON
C35: 320452329 | K35: CR-0171416-00 BODY CARBON | L35: CR-0166437-01 BODY | N35: Não Pedir
C36: E10690000 | K36: CR-0172035-00 Liftgate Ext | N36: Não Pedir
C37: 320455A8X | K37: CR-0172352-00 Front Bumper Carbon

Sheet CR MY26
B1: CR # | C1: Fase | D1: Nº Doc | E1: Envio da CR p/ análise | G1: CR "On Hold"?
B2: CR-0160280-00 | C2: MVBs | D2: 4489010 | E2: 45148 | F2: Afeta somente teste eletrico não foi respondido por corte e lead Prep. | G2: Sim | H2: GEM
B3: CR-0160595-00 | C3: MVBs | D3: EWO 4489010 | E3: 45169 | F3: Sem impacto para corte e Lead Prep.( analise feita base Delta CutSheet e BOM Scrap R$ 18.744,40 Alteração de comprimento de circuitos e tubos | G3: Não | H3: GEM
B4: CR-0161022-00 | C4: MVBs | D4: EWO 4489010 | E4: 45169 | F4: Sem impacto para corte e Lead Prep.( analise feita base Delta CutSheet e BOM Scrap R$ 17.489,97 Alteração de comprimento de circuitos e tubos | G4: Não | H4: GEM
B5: CR-0161020-00 | C5: MVBs | D5: EWO 4489010 | E5: 45169 | F5: Sem impacto para corte e Lead Prep.( analise feita base Delta CutSheet e BOM ) Scrap R$ 10.795,34 | G5: Não | H5: GEM
B6: CR-0161019-01 | C6: MVBs | D6: EWO 4489010 | E6: 45169 | F6: Sem impacto para corte e Lead Prep.( analise feita base Delta CutSheet e BOM ) Scrap R$ 10.795,21 CR cancelada | G6: Não | H6: GEM
B7: CR-0161953-00 | C7: MVBs | D7: 4489010 | E7: 45170 | F7: Sem impacto para corte e Lead Prep.( analise feita base Delta CutSheet e BOM ) Scrap R$ 1.382,86 | G7: Não | H7: GEM
B8: CR-0161952-00 | C8: MVBs | D8: 4489010 | E8: 45173 | F8: Sem impacto para corte e Lead Prep.( analise feita base Delta CutSheet e BOM ) Scrap R$ 1.100,34 | G8: Não | H8: GEM
B9: CR-0160595-01 | C9: MVBs | D9: EWO 4489010 | E9: 45202 | F9: Considerar para corte Lead Prep.( Analise feita base Delta Cut Sheet e Delta BOM ) 1 validação conforme Norma GMW17136 para Termo retrátil E02000700 R$ 31.731,33 Scrap Alteração de comprimento considerado 1 dia de lote para Scrap. | G9: Não | H9: GEM
B10: CR-0161019-02 | C10: MVBs | D10: EWO 4489010 | E10: 45202 | F10: #N/A | G10: Não | H10: GEM
B11: CR-0161020-01 | C11: APPV | D11: EWO#4489010 | E11: 45202 | F11: #N/A | G11: Não | H11: GEM
B12: CR-0161022-01 | C12: APPV | D12: EWO 4489010 | E12: 45202 | F12: #N/A | G12: Não | H12: GEM
B13: CR-0162419-00 | C13: APPV | D13: EWO 4489010 | E13: 45212 | F13: #N/A | G13: Não | H13: GEM
B14: CR-0165674-00 | C14: APPV | D14: EWO 4489010 | E14: 45217 | F14: CR CANCELADA | G14: Não | H14: GEM
B15: CR-0165673-00 | C15: APPV | D15: EWO#4489010 | E15: 45217 | F15: #N/A | G15: Não | H15: GEM
B16: CR-0162419-01 | C16: APPV | D16: EWO 4489010 | E16: 45217 | F16: Considerar para Corte e Lead Prep.( implementação condicionado a aprovação das validações conforme Norma GMW 17136 e USCAR 45 ) 1 validações conforme norma GMW17136. 1 validações conforme norma USCAR45. Scrap R$ 5.488,16 16 horas técnicas Necessidade de 150 peças do termo retrátil E02000700 para confecção das amostras para validação. Lead time para Validações e implementação a partir da liberação da verba 83dias | G16: Sim | H16: GEM
B17: CR-0162423-00 | C17: APPV | D17: EWO#4489010 | E17: 45217 | F17: Considerar sem Impacto para Corte e Lead Prep.( Analise realizada base delta Cutsheet 52183579_003 disponibilizado na CR-0162423-00 ) Scrap R$ 6.204,58 | G17: Sim | H17: GEM
B18: CR-0160595-02 | C18: APPV | D18: EWO 4489010 | E18: 45217 | F18: Considerar para corte Lead Prep.( Analise feita base Delta Cut Sheet e Delta BOM, implementação condicionada aos testes e aprovação conforme Norma GMW 17136) 1 validação conforme Norma GMW17136 para Termo retrátil E02000700 R$ 31.731,33 Scrap 6 horas técnicas Alteração de comprimento considerado 1 dia de lote para Scrap. | G18: Sim | H18: GEM
B19: CR-0161019-03 | C19: IVER | D19: EWO 4489010 | E19: 45217 | F19: Sem impacto para corte e Lead Prep. ( Analise feita base Delta Cut Sheet e Delta BOM ) Scrap R$ 7.608,42 Alteração de comprimento considerado 1 dia de lote para Scrap. | G19: Sim | H19: GEM
B20: CR-0161020-02 | C20: IVER | D20: EWO#4489010 | E20: 45217 | F20: Considerar sem impacto para corte Lead Prep.( Analise feita base Delta Cut Sheet e Delta BOM, implementação condicionada aos investimentos reportados na CR-0160595-02, testes e aprovação conforme Norma GMW 17136) Scrap R$ R$ 5.397,92 Alteração de comprimento considerado 1 dia de lote para Scrap. | G20: Sim | H20: GEM
B21: CR-0161022-02 | C21: APPV | D21: EWO 4489010 | E21: 45217 | F21: Considerar sem impacto para corte Lead Prep.( Analise feita base Delta Cut Sheet e Delta BOM, implementação condicionada aos investimentos reportados na CR-0160595-02, testes e aprovação conforme Norma GMW 17136) Scrap R$ 27.223,08 Alteração de comprimento considerado 1 dia de lote para Scrap. | G21: Sim | H21: GEM
B22: CR-0162211-00 | C22: APPV | D22: EWO 4489010 | E22: 45246 | F22: • 4 mini aplicadores • 8 validações conforme norma USCAR21 • 17 validações conforme norma USCAR45 • 2 validações conforme norma USCAR 38 • 31 validações conforme norma GMW17136. • 5 pacotes de polaseal. • 2 Rolos Contact • 6 Rolos dupla face • 40 horas de gráfica. • 1 rolo de vinil ( Para gráfica lear ) • 480 horas técnicas para validações • Scrap R$ R$ 22.832,72 Conforme alinhamento com Logística @Chagas, Robson Dos Santos Foi analisado e encontrado inconsistência em algumas aplicações: Segue abaixo as inconsistências encontradas, e já está sendo tratado pelo ABarbosa@lear.com | G22: Sim | H22: GEM
B23: CR-0164612-00 | C23: APPV | D23: EWO 4489010 | E23: 45247 | F23: • 09 validações conforme norma USCAR 45 • 21 VALIDAÇÕES CONFORME NORMA GMW17136. • Scrap R$21.229,85 | G23: Não | H23: GEM
B24: CR-0166437-00 | C24: MVBs | D24: 4489010 | E24: 45250 | F24: #N/A | G24: Não | H24: GEM
B25: CR-0168267-00 | C25: APPV | D25: 4590640 | E25: 45257 | F25: Descrição: 1. GEM B NARROW BODY HARNESS 52182307 MY26 MVBS Sem necessidade de investimento para engenharia corte/lead prep | G25: Não | H25: GEM
B26: CR-0166437-01 | C26: APPV | D26: 4489010 | E26: 45257 | F26: Favor considerar: • 06 calhas de selo (01 para o selo 320452329 e 5 para o selo 3204505B1) selo novo e volume alto • 06 mini aplicadores • 31 validações conforme norma USCAR21 • 14 validações conforme norma USCAR45 • 05 validações conforme norma USCAR 38 • 26 validações conforme norma GMW17136. • 4 pacotes de polaseal. • 80 horas de gráfica. • Horas técnicas para as validações 400 hs. • Scrap 21.229,85 | G26: Sim | H26: GEM
B27: CR-0168626-00 | C27: APPV | D27: 4489010 | E27: 45257 | F27: Descrição: 1. Esta CR foi criada apenas para analise dos investimentos referente a evolução da CG4210 para os itens mostrados no anexos para o MY26. Só não vamos considerar os circuitos para teste de impedancia (Item 11.5.4) . Devemos Considerar os cabos de antena e USB. As modificações tecnicas do produto serão cotadas através de outras CRs especificas. Sem necessidade de investimento para engenharia corte/lead prep | G27: Sim | H27: GEM
B28: CR-0164612-01 | C28: APPV | D28: EWO 4489010 | E28: 45259 | F28: • 09 validações conforme norma USCAR 45 • 21 VALIDAÇÕES CONFORME NORMA GMW17136. • Scrap R$21.229,85 | G28: Sim | H28: GEM
B29: CR-0168269-00 | C29: MVBs | D29: EWO 4590640 | E29: 45259 | F29: 18 validações conforme Norma USCAR 45 19 validações conforme Norma GMW 17136 3 validações conforme Norma USCAR 38 320 horas técnicas. Analise de Scrap considerando 1 dia de estoque base LCR 1280 Cars dia, @Martins, Guilherme; @Chagas, Robson Dos Santos favor validar os valores e revisar se necessário em anexo circuitos que estão saindo conforme delta cut da CCR-0168269-00 scrap 1 dia LCR 1280 TAKE RATE Scrap circuitos R$ 107.130,14 scrap 1 dia LCR 1280 TAKE RATE Scrap tubo R$ 823,97 scrap 1 dia LCR 1280 TAKE RATE Scrap Splice pronta R$ 34.044,28 scrap 1 dia LCR 1280 TAKE RATE Scrap Multicrimp pronta R$ 2.074,27 scrap 1 dia LCR 1280 TAKE RATE Scrap Termo R$ 2.832,45 Scrap Total R$ 146.905,11 | G29: Não | H29: GEM
B30: CR-0168559-00 | C30: APPV | D30: 4590640 | E30: 45259 | F30: Considerar sem impacto para corte Lead prep. Scrap R$ 113,68 circuito Wire Nb 6817 morrendo. | G30: Não | H30: GEM
B31: CR-0168949-00 | C31: APPV | D31: 4590640 | E31: 45260 | G31: Não | H31: GEM
B32: CR-0168984-00 | C32: APPV | D32: 4489010 | E32: 45261 | F32: 18 validações conforme Norma USCAR 45 | G32: Não | H32: GEM
B33: CR-0168559-01 | C33: MVBs | D33: 4590640 | E33: 45273 | F33: 2 validações conforme norma USCAR 45. 2 validações conforme norma GMW17136 32 Horas técnicas Scrap circuito R$ 113,27 Considerando 1 dia LCR Scrap Splice pronta R$ 1.282,10 Considerando 1 dia LCR Scrap Termo R$ 198,44 Considerando 1 dia LCR Scrap validação Splice R$ R$ 187,95 Conforme alinhado e reunião hoje , favor desconsiderar investimento reportado nessa CR, pois delta cut está gerando informação na Section 4:DELTA SPLICE que não será aplicada. 07-02-2024 | G33: Não | H33: GEM
B34: CR-0171841-00 | C34: APPV | E34: 45302 | F34: Considerar sem impacto para corte e Lead Prep.( Analise realizada base delta Cut Delta BOM.) | G34: Não | H34: GEM
B35: CR-0171865-00 | C35: PPV | D35: ECR4633774 | E35: 45303 | F35: Favor considerar: • Scrap : R$447,92 | G35: Não | H35: GEM
B36: CR-0172163-00 | C36: PPV | D36: TBD | E36: 45308 | F36: Não aplica para corte e Lead Prep | G36: Não | H36: GEM
B37: CR-0172366-00 | C37: PPV | D37: 4634774 | E37: 45308 | F37: Considerar em impacto para corte e Lead Prep. | G37: Não | H37: GEM
B38: CR-0172424-00 | C38: APPV | D38: 4634774 | E38: 45309 | F38: Considerar sem impacto para área de corte lead Prep. | G38: Não | H38: GEM
B39: CR-0172460-00 | C39: APPV | E39: 45310 | F39: #N/A | G39: Não | H39: GEM
B40: CR-0172477-00 | D40: 4634774 | E40: 45310 | F40: #N/A | G40: Não | H40: GEM
B41: CR-0172542-00 | D41: 4634774 | E41: 45313 | F41: #N/A | G41: Não | H41: GEM
B42: CR-0172775-00 | E42: 45315 | F42: Não aplica para corte e Lead Prep | G42: Não | H42: GEM

Sheet MY26 Validações Uscar e GMW
A1: Terminal | B1: Selo | C1: Extra Component PN | D1: CHP USCAR21 | E1: CSA Left | F1: CSA Right | G1: CSA Total | H1: W1 | I1: W2 | J1: W3 | K1: W4 | L1: L1 | M1: L2 | N1: L3 | O1: L4 | P1: L5 | Q1: L6 | R1: L7 | S1: R1 | T1: R2 | U1: R3 | V1: R4 | W1: R5 | X1: R6 | Y1: R7 | Z1: X1 | AA1: X2 | AB1: X3 | AC1: X4 | AD1: X5 | AE1: USCAR38 | AF1: Uscar 45 | AG1: GMW17136 | AH1: USCAR 21 | AI1: Horas tecnicas | AJ1: MY | AK1: CHP
C2: 3299362G2 | E2: 1.2 | F2: 0.5 | G2: 1.7 | L2: 0.35 | M2: 0.5 | N2: 0.35 | S2: 0.5 | AF2: X | AG2: X | AI2: 16 | AK2: =CONCATENATE(A2,"-",B2,"-",C2,"-",E2,"-",F2,"-",G2,"-",H2,"-",I2,"-",J2,"-",K2,"-",L2,"-",M2,"-",N2,"-",O2,"-",P2,"-",Q2,"-",R2,"-",S2,"-",T2,"-",U2,"-",V2,"-",W2,"-",X2,"-",Y2,"-",Z2,"-",AA2,"-",AB2,"-",AC2,"-",AD2) -> --3299362G2-1,2-0,5-1,7-----0,35-0,5-0,35-----0,5----------- | AL2: =VLOOKUP(AK2,Planilha1!B:C,2,0) -> 1 | AM2: CR-0171416-00 BODY CARBON
C3: 3299362G2 | E3: 0.7 | F3: 1 | G3: 1.7 | L3: 0.35 | M3: 0.35 | S3: 0.5 | T3: 0.5 | AG3: X | AI3: 8 | AK3: =CONCATENATE(A3,"-",B3,"-",C3,"-",E3,"-",F3,"-",G3,"-",H3,"-",I3,"-",J3,"-",K3,"-",L3,"-",M3,"-",N3,"-",O3,"-",P3,"-",Q3,"-",R3,"-",S3,"-",T3,"-",U3,"-",V3,"-",W3,"-",X3,"-",Y3,"-",Z3,"-",AA3,"-",AB3,"-",AC3,"-",AD3) -> --3299362G2-0,7-1-1,7-----0,35-0,35------0,5-0,5---------- | AL3: =VLOOKUP(AK3,Planilha1!B:C,2,0) -> 2 | AM3: CR-0171416-00 BODY CARBON
C4: E16718500 | E4: 1.05 | F4: 0.35 | G4: 1.4 | L4: 0.35 | M4: 0.35 | N4: 0.35 | S4: 0.35 | AG4: X | AI4: 8 | AK4: =CONCATENATE(A4,"-",B4,"-",C4,"-",E4,"-",F4,"-",G4,"-",H4,"-",I4,"-",J4,"-",K4,"-",L4,"-",M4,"-",N4,"-",O4,"-",P4,"-",Q4,"-",R4,"-",S4,"-",T4,"-",U4,"-",V4,"-",W4,"-",X4,"-",Y4,"-",Z4,"-",AA4,"-",AB4,"-",AC4,"-",AD4) -> --E16718500-1,05-0,35-1,4-----0,35-0,35-0,35-----0,35----------- | AL4: =VLOOKUP(AK4,Planilha1!B:C,2,0) -> 3 | AM4: CR-0171416-00 BODY CARBON
C5: E16718500 | E5: 1.05 | F5: 0.35 | G5: 1.4 | L5: 0.35 | M5: 0.35 | N5: 0.35 | S5: 0.35 | AG5: X | AI5: 8 | AJ5: 2026 | AK5: =CONCATENATE(A5,"-",B5,"-",C5,"-",E5,"-",F5,"-",G5,"-",H5,"-",I5,"-",J5,"-",K5,"-",L5,"-",M5,"-",N5,"-",O5,"-",P5,"-",Q5,"-",R5,"-",S5,"-",T5,"-",U5,"-",V5,"-",W5,"-",X5,"-",Y5,"-",Z5,"-",AA5,"-",AB5,"-",AC5,"-",AD5) -> --E16718500-1,05-0,35-1,4-----0,35-0,35-0,35-----0,35----------- | AL5: =VLOOKUP(AK5,Planilha1!B:C,2,0) -> 3 | AM5: CR-0166437-01 BODY
C6: E16718500 | E6: 0.35 | F6: 0.7 | G6: 1.05 | L6: 0.35 | S6: 0.35 | T6: 0.35 | AG6: X | AI6: 8 | AK6: =CONCATENATE(A6,"-",B6,"-",C6,"-",E6,"-",F6,"-",G6,"-",H6,"-",I6,"-",J6,"-",K6,"-",L6,"-",M6,"-",N6,"-",O6,"-",P6,"-",Q6,"-",R6,"-",S6,"-",T6,"-",U6,"-",V6,"-",W6,"-",X6,"-",Y6,"-",Z6,"-",AA6,"-",AB6,"-",AC6,"-",AD6) -> --E16718500-0,35-0,7-1,05-----0,35-------0,35-0,35---------- | AL6: =VLOOKUP(AK6,Planilha1!B:C,2,0) -> 4 | AM6: CR-0171416-00 BODY CARBON
C7: E16718500 | E7: 0.35 | F7: 0.7 | G7: 1.05 | L7: 0.35 | S7: 0.35 | T7: 0.35 | AG7: X | AI7: 8 | AK7: =CONCATENATE(A7,"-",B7,"-",C7,"-",E7,"-",F7,"-",G7,"-",H7,"-",I7,"-",J7,"-",K7,"-",L7,"-",M7,"-",N7,"-",O7,"-",P7,"-",Q7,"-",R7,"-",S7,"-",T7,"-",U7,"-",V7,"-",W7,"-",X7,"-",Y7,"-",Z7,"-",AA7,"-",AB7,"-",AC7,"-",AD7) -> --E16718500-0,35-0,7-1,05-----0,35-------0,35-0,35---------- | AL7: =VLOOKUP(AK7,Planilha1!B:C,2,0) -> 4 | AM7: CR-0171595-00 IP HARNESS carbon
C8: 3299362M9 | E8: 3.35 | F8: 4 | G8: 7.35 | L8: 0.35 | M8: 0.5 | N8: 2.5 | S8: 1 | T8: 3 | AF8: X | AG8: X | AI8: 16 | AK8: =CONCATENATE(A8,"-",B8,"-",C8,"-",E8,"-",F8,"-",G8,"-",H8,"-",I8,"-",J8,"-",K8,"-",L8,"-",M8,"-",N8,"-",O8,"-",P8,"-",Q8,"-",R8,"-",S8,"-",T8,"-",U8,"-",V8,"-",W8,"-",X8,"-",Y8,"-",Z8,"-",AA8,"-",AB8,"-",AC8,"-",AD8) -> --3299362M9-3,35-4-7,35-----0,35-0,5-2,5-----1-3---------- | AL8: =VLOOKUP(AK8,Planilha1!B:C,2,0) -> 5 | AM8: CR-0171416-00 BODY CARBON
C9: 3299362M9 | E9: 4.35 | F9: 3 | G9: 7.35 | L9: 1 | M9: 0.35 | N9: 0.5 | O9: 2.5 | S9: 3 | AF9: X | AG9: X | AI9: 16 | AK9: =CONCATENATE(A9,"-",B9,"-",C9,"-",E9,"-",F9,"-",G9,"-",H9,"-",I9,"-",J9,"-",K9,"-",L9,"-",M9,"-",N9,"-",O9,"-",P9,"-",Q9,"-",R9,"-",S9,"-",T9,"-",U9,"-",V9,"-",W9,"-",X9,"-",Y9,"-",Z9,"-",AA9,"-",AB9,"-",AC9,"-",AD9) -> --3299362M9-4,35-3-7,35-----1-0,35-0,5-2,5----3----------- | AL9: =VLOOKUP(AK9,Planilha1!B:C,2,0) -> 6 | AM9: CR-0171416-00 BODY CARBON
C10: E16718500 | E10: 0.5 | F10: 0.85 | G10: 1.35 | L10: 0.5 | S10: 0.5 | T10: 0.35 | AG10: X | AI10: 8 | AK10: =CONCATENATE(A10,"-",B10,"-",C10,"-",E10,"-",F10,"-",G10,"-",H10,"-",I10,"-",J10,"-",K10,"-",L10,"-",M10,"-",N10,"-",O10,"-",P10,"-",Q10,"-",R10,"-",S10,"-",T10,"-",U10,"-",V10,"-",W10,"-",X10,"-",Y10,"-",Z10,"-",AA10,"-",AB10,"-",AC10,"-",AD10) -> --E16718500-0,5-0,85-1,35-----0,5-------0,5-0,35---------- | AL10: =VLOOKUP(AK10,Planilha1!B:C,2,0) -> 7 | AM10: CR-0171416-00 BODY CARBON
C11: E16718500 | E11: 0.5 | F11: 0.85 | G11: 1.35 | L11: 0.5 | S11: 0.5 | T11: 0.35 | AG11: X | AI11: 8 | AJ11: 2026 | AK11: =CONCATENATE(A11,"-",B11,"-",C11,"-",E11,"-",F11,"-",G11,"-",H11,"-",I11,"-",J11,"-",K11,"-",L11,"-",M11,"-",N11,"-",O11,"-",P11,"-",Q11,"-",R11,"-",S11,"-",T11,"-",U11,"-",V11,"-",W11,"-",X11,"-",Y11,"-",Z11,"-",AA11,"-",AB11,"-",AC11,"-",AD11) -> --E16718500-0,5-0,85-1,35-----0,5-------0,5-0,35---------- | AL11: =VLOOKUP(AK11,Planilha1!B:C,2,0) -> 7 | AM11: CR-0168269-00 BODY
C12: E16718500 | E12: 0.5 | F12: 0.85 | G12: 1.35 | L12: 0.5 | S12: 0.5 | T12: 0.35 | AG12: X | AI12: 8 | AJ12: 2026 | AK12: =CONCATENATE(A12,"-",B12,"-",C12,"-",E12,"-",F12,"-",G12,"-",H12,"-",I12,"-",J12,"-",K12,"-",L12,"-",M12,"-",N12,"-",O12,"-",P12,"-",Q12,"-",R12,"-",S12,"-",T12,"-",U12,"-",V12,"-",W12,"-",X12,"-",Y12,"-",Z12,"-",AA12,"-",AB12,"-",AC12,"-",AD12) -> --E16718500-0,5-0,85-1,35-----0,5-------0,5-0,35---------- | AL12: =VLOOKUP(AK12,Planilha1!B:C,2,0) -> 7 | AM12: CR-0166437-01 BODY
C13: E16718500 | E13: 0.5 | F13: 0.85 | G13: 1.35 | L13: 0.5 | S13: 0.5 | T13: 0.35 | AG13: X | AI13: 8 | AJ13: 2026 | AK13: =CONCATENATE(A13,"-",B13,"-",C13,"-",E13,"-",F13,"-",G13,"-",H13,"-",I13,"-",J13,"-",K13,"-",L13,"-",M13,"-",N13,"-",O13,"-",P13,"-",Q13,"-",R13,"-",S13,"-",T13,"-",U13,"-",V13,"-",W13,"-",X13,"-",Y13,"-",Z13,"-",AA13,"-",AB13,"-",AC13,"-",AD13) -> --E16718500-0,5-0,85-1,35-----0,5-------0,5-0,35---------- | AL13: =VLOOKUP(AK13,Planilha1!B:C,2,0) -> 7 | AM13: CR-0164612-01 BODY | AN13: foi considerado na CR 9 validações uscar45 e 21 GMW17136( necesidade 26 GMW17136 e 18 Uscar45)
C14: E16718500 | E14: 0.35 | F14: 0.75 | G14: 1.1 | L14: 0.35 | S14: 0.75 | AF14: X | AG14: X | AI14: 8 | AK14: =CONCATENATE(A14,"-",B14,"-",C14,"-",E14,"-",F14,"-",G14,"-",H14,"-",I14,"-",J14,"-",K14,"-",L14,"-",M14,"-",N14,"-",O14,"-",P14,"-",Q14,"-",R14,"-",S14,"-",T14,"-",U14,"-",V14,"-",W14,"-",X14,"-",Y14,"-",Z14,"-",AA14,"-",AB14,"-",AC14,"-",AD14) -> --E16718500-0,35-0,75-1,1-----0,35-------0,75----------- | AL14: =VLOOKUP(AK14,Planilha1!B:C,2,0) -> 8 | AM14: CR-0171416-00 BODY CARBON
C15: E16718500 | E15: 1.25 | F15: 0.5 | G15: 1.75 | L15: 0.5 | M15: 0.75 | S15: 0.5 | AG15: X | AI15: 8 | AK15: =CONCATENATE(A15,"-",B15,"-",C15,"-",E15,"-",F15,"-",G15,"-",H15,"-",I15,"-",J15,"-",K15,"-",L15,"-",M15,"-",N15,"-",O15,"-",P15,"-",Q15,"-",R15,"-",S15,"-",T15,"-",U15,"-",V15,"-",W15,"-",X15,"-",Y15,"-",Z15,"-",AA15,"-",AB15,"-",AC15,"-",AD15) -> --E16718500-1,25-0,5-1,75-----0,5-0,75------0,5----------- | AL15: =VLOOKUP(AK15,Planilha1!B:C,2,0) -> 9 | AM15: CR-0171416-00 BODY CARBON
C16: E16718500 | E16: 1.25 | F16: 0.5 | G16: 1.75 | L16: 0.5 | M16: 0.75 | S16: 0.5 | AG16: X | AI16: 8 | AJ16: 2026 | AK16: =CONCATENATE(A16,"-",B16,"-",C16,"-",E16,"-",F16,"-",G16,"-",H16,"-",I16,"-",J16,"-",K16,"-",L16,"-",M16,"-",N16,"-",O16,"-",P16,"-",Q16,"-",R16,"-",S16,"-",T16,"-",U16,"-",V16,"-",W16,"-",X16,"-",Y16,"-",Z16,"-",AA16,"-",AB16,"-",AC16,"-",AD16) -> --E16718500-1,25-0,5-1,75-----0,5-0,75------0,5----------- | AL16: =VLOOKUP(AK16,Planilha1!B:C,2,0) -> 9 | AM16: CR-0164612-01 BODY | AN16: foi considerado na CR 9 validações uscar45 e 21 GMW17136( necesidade 26 GMW17136 e 18 Uscar45)
C17: E16718500 | E17: 0.85 | F17: 0.35 | G17: 1.2 | L17: 0.5 | S17: 0.35 | X17: 0.35 | AF17: X | AG17: X | AI17: 16 | AK17: =CONCATENATE(A17,"-",B17,"-",C17,"-",E17,"-",F17,"-",G17,"-",H17,"-",I17,"-",J17,"-",K17,"-",L17,"-",M17,"-",N17,"-",O17,"-",P17,"-",Q17,"-",R17,"-",S17,"-",T17,"-",U17,"-",V17,"-",W17,"-",X17,"-",Y17,"-",Z17,"-",AA17,"-",AB17,"-",AC17,"-",AD17) -> --E16718500-0,85-0,35-1,2-----0,5-------0,35-----0,35------ | AL17: =VLOOKUP(AK17,Planilha1!B:C,2,0) -> 10 | AM17: CR-0171416-00 BODY CARBON
C18: E16718500 | E18: 0.5 | F18: 1.85 | G18: 2.35 | L18: 0.5 | S18: 0.5 | T18: 0.5 | U18: 0.5 | V18: 0.35 | AF18: X | AG18: X | AI18: 16 | AK18: =CONCATENATE(A18,"-",B18,"-",C18,"-",E18,"-",F18,"-",G18,"-",H18,"-",I18,"-",J18,"-",K18,"-",L18,"-",M18,"-",N18,"-",O18,"-",P18,"-",Q18,"-",R18,"-",S18,"-",T18,"-",U18,"-",V18,"-",W18,"-",X18,"-",Y18,"-",Z18,"-",AA18,"-",AB18,"-",AC18,"-",AD18) -> --E16718500-0,5-1,85-2,35-----0,5-------0,5-0,5-0,5-0,35-------- | AL18: =VLOOKUP(AK18,Planilha1!B:C,2,0) -> 11 | AM18: CR-0171416-00 BODY CARBON
C19: 3299362M9 | E19: 6.25 | F19: 0.5 | G19: 6.75 | L19: 1.5 | M19: 0.5 | N19: 0.75 | O19: 2 | S19: 0.5 | X19: 1.5 | AF19: X | AG19: X | AI19: 16 | AK19: =CONCATENATE(A19,"-",B19,"-",C19,"-",E19,"-",F19,"-",G19,"-",H19,"-",I19,"-",J19,"-",K19,"-",L19,"-",M19,"-",N19,"-",O19,"-",P19,"-",Q19,"-",R19,"-",S19,"-",T19,"-",U19,"-",V19,"-",W19,"-",X19,"-",Y19,"-",Z19,"-",AA19,"-",AB19,"-",AC19,"-",AD19) -> --3299362M9-6,25-0,5-6,75-----1,5-0,5-0,75-2----0,5-----1,5------ | AL19: =VLOOKUP(AK19,Planilha1!B:C,2,0) -> 12 | AM19: CR-0171416-00 BODY CARBON
C20: E16725300 | E20: 1.35 | F20: 1.9 | G20: 3.25 | L20: 0.35 | M20: 1 | S20: 0.35 | T20: 0.35 | U20: 0.35 | V20: 0.5 | W20: 0.35 | AF20: X | AG20: X | AI20: 16 | AK20: =CONCATENATE(A20,"-",B20,"-",C20,"-",E20,"-",F20,"-",G20,"-",H20,"-",I20,"-",J20,"-",K20,"-",L20,"-",M20,"-",N20,"-",O20,"-",P20,"-",Q20,"-",R20,"-",S20,"-",T20,"-",U20,"-",V20,"-",W20,"-",X20,"-",Y20,"-",Z20,"-",AA20,"-",AB20,"-",AC20,"-",AD20) -> --E16725300-1,35-1,9-3,25-----0,35-1------0,35-0,35-0,35-0,5-0,35------- | AL20: =VLOOKUP(AK20,Planilha1!B:C,2,0) -> 13 | AM20: CR-0171595-00 IP HARNESS carbon
C21: E16725300 | E21: 1.35 | F21: 1.9 | G21: 3.25 | L21: 0.35 | M21: 1 | S21: 0.35 | T21: 0.35 | U21: 0.35 | V21: 0.5 | W21: 0.35 | AF21: X | AG21: X | AI21: 16 | AJ21: 2026 | AK21: =CONCATENATE(A21,"-",B21,"-",C21,"-",E21,"-",F21,"-",G21,"-",H21,"-",I21,"-",J21,"-",K21,"-",L21,"-",M21,"-",N21,"-",O21,"-",P21,"-",Q21,"-",R21,"-",S21,"-",T21,"-",U21,"-",V21,"-",W21,"-",X21,"-",Y21,"-",Z21,"-",AA21,"-",AB21,"-",AC21,"-",AD21) -> --E16725300-1,35-1,9-3,25-----0,35-1------0,35-0,35-0,35-0,5-0,35------- | AL21: =VLOOKUP(AK21,Planilha1!B:C,2,0) -> 13 | AM21: CR-0170489-00 IP
C22: E16725300 | E22: 1.75 | F22: 4 | G22: 5.75 | L22: 1 | M22: 0.75 | S22: 0.5 | T22: 0.5 | U22: 3 | AF22: X | AG22: X | AI22: 16 | AK22: =CONCATENATE(A22,"-",B22,"-",C22,"-",E22,"-",F22,"-",G22,"-",H22,"-",I22,"-",J22,"-",K22,"-",L22,"-",M22,"-",N22,"-",O22,"-",P22,"-",Q22,"-",R22,"-",S22,"-",T22,"-",U22,"-",V22,"-",W22,"-",X22,"-",Y22,"-",Z22,"-",AA22,"-",AB22,"-",AC22,"-",AD22) -> --E16725300-1,75-4-5,75-----1-0,75------0,5-0,5-3--------- | AL22: =VLOOKUP(AK22,Planilha1!B:C,2,0) -> 14 | AM22: CR-0171595-00 IP HARNESS carbon
C23: E16725300 | E23: 1.75 | F23: 9 | G23: 10.75 | L23: 1 | M23: 0.75 | S23: 2.5 | T23: 0.5 | U23: 0.5 | V23: 2.5 | W23: 3 | AF23: X | AG23: X | AI23: 16 | AK23: =CONCATENATE(A23,"-",B23,"-",C23,"-",E23,"-",F23,"-",G23,"-",H23,"-",I23,"-",J23,"-",K23,"-",L23,"-",M23,"-",N23,"-",O23,"-",P23,"-",Q23,"-",R23,"-",S23,"-",T23,"-",U23,"-",V23,"-",W23,"-",X23,"-",Y23,"-",Z23,"-",AA23,"-",AB23,"-",AC23,"-",AD23) -> --E16725300-1,75-9-10,75-----1-0,75------2,5-0,5-0,5-2,5-3------- | AL23: =VLOOKUP(AK23,Planilha1!B:C,2,0) -> 15 | AM23: CR-0171595-00 IP HARNESS carbon
C24: E01120300 | E24: 2.5 | F24: 15 | G24: 17.5 | L24: 2.5 | S24: 2.5 | T24: 2.5 | U24: 2.5 | V24: 2.5 | W24: 2.5 | X24: 2.5 | AF24: X | AG24: X | AI24: 16 | AK24: =CONCATENATE(A24,"-",B24,"-",C24,"-",E24,"-",F24,"-",G24,"-",H24,"-",I24,"-",J24,"-",K24,"-",L24,"-",M24,"-",N24,"-",O24,"-",P24,"-",Q24,"-",R24,"-",S24,"-",T24,"-",U24,"-",V24,"-",W24,"-",X24,"-",Y24,"-",Z24,"-",AA24,"-",AB24,"-",AC24,"-",AD24) -> --E01120300-2,5-15-17,5-----2,5-------2,5-2,5-2,5-2,5-2,5-2,5------ | AL24: =VLOOKUP(AK24,Planilha1!B:C,2,0) -> 16 | AM24: CR-0171595-00 IP HARNESS carbon
C25: E01120300 | E25: 2.5 | F25: 15 | G25: 17.5 | L25: 2.5 | S25: 2.5 | T25: 2.5 | U25: 2.5 | V25: 2.5 | W25: 2.5 | X25: 2.5 | AF25: X | AG25: X | AI25: 16 | AJ25: 2026 | AK25: =CONCATENATE(A25,"-",B25,"-",C25,"-",E25,"-",F25,"-",G25,"-",H25,"-",I25,"-",J25,"-",K25,"-",L25,"-",M25,"-",N25,"-",O25,"-",P25,"-",Q25,"-",R25,"-",S25,"-",T25,"-",U25,"-",V25,"-",W25,"-",X25,"-",Y25,"-",Z25,"-",AA25,"-",AB25,"-",AC25,"-",AD25) -> --E01120300-2,5-15-17,5-----2,5-------2,5-2,5-2,5-2,5-2,5-2,5------ | AL25: =VLOOKUP(AK25,Planilha1!B:C,2,0) -> 16 | AM25: CR-0170489-00 IP
C26: E16725300 | E26: 1.25 | F26: 1.05 | G26: 2.3 | L26: 0.75 | M26: 0.5 | S26: 0.35 | T26: 0.35 | U26: 0.35 | AF26: X | AG26: X | AI26: 16 | AK26: =CONCATENATE(A26,"-",B26,"-",C26,"-",E26,"-",F26,"-",G26,"-",H26,"-",I26,"-",J26,"-",K26,"-",L26,"-",M26,"-",N26,"-",O26,"-",P26,"-",Q26,"-",R26,"-",S26,"-",T26,"-",U26,"-",V26,"-",W26,"-",X26,"-",Y26,"-",Z26,"-",AA26,"-",AB26,"-",AC26,"-",AD26) -> --E16725300-1,25-1,05-2,3-----0,75-0,5------0,35-0,35-0,35--------- | AL26: =VLOOKUP(AK26,Planilha1!B:C,2,0) -> 17 | AM26: CR-0171595-00 IP HARNESS carbon
C27: E16725300 | E27: 1.25 | F27: 1.05 | G27: 2.3 | L27: 0.75 | M27: 0.5 | S27: 0.35 | T27: 0.35 | U27: 0.35 | AF27: X | AG27: X | AI27: 16 | AJ27: 2026 | AK27: =CONCATENATE(A27,"-",B27,"-",C27,"-",E27,"-",F27,"-",G27,"-",H27,"-",I27,"-",J27,"-",K27,"-",L27,"-",M27,"-",N27,"-",O27,"-",P27,"-",Q27,"-",R27,"-",S27,"-",T27,"-",U27,"-",V27,"-",W27,"-",X27,"-",Y27,"-",Z27,"-",AA27,"-",AB27,"-",AC27,"-",AD27) -> --E16725300-1,25-1,05-2,3-----0,75-0,5------0,35-0,35-0,35--------- | AL27: =VLOOKUP(AK27,Planilha1!B:C,2,0) -> 17 | AM27: CR-0162211-00 IP
C28: E16725300 | E28: 1.25 | F28: 1.05 | G28: 2.3 | L28: 0.75 | M28: 0.5 | S28: 0.35 | T28: 0.35 | U28: 0.35 | AF28: X | AG28: X | AI28: 16 | AJ28: 2026 | AK28: =CONCATENATE(A28,"-",B28,"-",C28,"-",E28,"-",F28,"-",G28,"-",H28,"-",I28,"-",J28,"-",K28,"-",L28,"-",M28,"-",N28,"-",O28,"-",P28,"-",Q28,"-",R28,"-",S28,"-",T28,"-",U28,"-",V28,"-",W28,"-",X28,"-",Y28,"-",Z28,"-",AA28,"-",AB28,"-",AC28,"-",AD28) -> --E16725300-1,25-1,05-2,3-----0,75-0,5------0,35-0,35-0,35--------- | AL28: =VLOOKUP(AK28,Planilha1!B:C,2,0) -> 17 | AM28: CR-0170489-00 IP
C29: E16725300 | E29: 1.25 | F29: 1.75 | G29: 3 | L29: 0.75 | M29: 0.5 | S29: 0.35 | T29: 0.35 | U29: 0.35 | V29: 0.35 | W29: 0.35 | AF29: X | AG29: X | AI29: 16 | AK29: =CONCATENATE(A29,"-",B29,"-",C29,"-",E29,"-",F29,"-",G29,"-",H29,"-",I29,"-",J29,"-",K29,"-",L29,"-",M29,"-",N29,"-",O29,"-",P29,"-",Q29,"-",R29,"-",S29,"-",T29,"-",U29,"-",V29,"-",W29,"-",X29,"-",Y29,"-",Z29,"-",AA29,"-",AB29,"-",AC29,"-",AD29) -> --E16725300-1,25-1,75-3-----0,75-0,5------0,35-0,35-0,35-0,35-0,35------- | AL29: =VLOOKUP(AK29,Planilha1!B:C,2,0) -> 18 | AM29: CR-0171595-00 IP HARNESS carbon
C30: E16725300 | E30: 1.25 | F30: 1.75 | G30: 3 | L30: 0.75 | M30: 0.5 | S30: 0.35 | T30: 0.35 | U30: 0.35 | V30: 0.35 | W30: 0.35 | AF30: X | AG30: X | AI30: 16 | AJ30: 2026 | AK30: =CONCATENATE(A30,"-",B30,"-",C30,"-",E30,"-",F30,"-",G30,"-",H30,"-",I30,"-",J30,"-",K30,"-",L30,"-",M30,"-",N30,"-",O30,"-",P30,"-",Q30,"-",R30,"-",S30,"-",T30,"-",U30,"-",V30,"-",W30,"-",X30,"-",Y30,"-",Z30,"-",AA30,"-",AB30,"-",AC30,"-",AD30) -> --E16725300-1,25-1,75-3-----0,75-0,5------0,35-0,35-0,35-0,35-0,35------- | AL30: =VLOOKUP(AK30,Planilha1!B:C,2,0) -> 18 | AM30: CR-0162211-00 IP
C31: E16725300 | E31: 1.25 | F31: 1.75 | G31: 3 | L31: 0.75 | M31: 0.5 | S31: 0.35 | T31: 0.35 | U31: 0.35 | V31: 0.35 | W31: 0.35 | AF31: X | AG31: X | AI31: 16 | AJ31: 2026 | AK31: =CONCATENATE(A31,"-",B31,"-",C31,"-",E31,"-",F31,"-",G31,"-",H31,"-",I31,"-",J31,"-",K31,"-",L31,"-",M31,"-",N31,"-",O31,"-",P31,"-",Q31,"-",R31,"-",S31,"-",T31,"-",U31,"-",V31,"-",W31,"-",X31,"-",Y31,"-",Z31,"-",AA31,"-",AB31,"-",AC31,"-",AD31) -> --E16725300-1,25-1,75-3-----0,75-0,5------0,35-0,35-0,35-0,35-0,35------- | AL31: =VLOOKUP(AK31,Planilha1!B:C,2,0) -> 18 | AM31: CR-0170489-00 IP
C32: E16725300 | E32: 1.25 | F32: 2.1 | G32: 3.35 | L32: 0.75 | M32: 0.5 | S32: 0.35 | T32: 0.35 | U32: 0.35 | V32: 0.35 | W32: 0.35 | X32: 0.35 | AF32: X | AG32: X | AI32: 16 | AK32: =CONCATENATE(A32,"-",B32,"-",C32,"-",E32,"-",F32,"-",G32,"-",H32,"-",I32,"-",J32,"-",K32,"-",L32,"-",M32,"-",N32,"-",O32,"-",P32,"-",Q32,"-",R32,"-",S32,"-",T32,"-",U32,"-",V32,"-",W32,"-",X32,"-",Y32,"-",Z32,"-",AA32,"-",AB32,"-",AC32,"-",AD32) -> --E16725300-1,25-2,1-3,35-----0,75-0,5------0,35-0,35-0,35-0,35-0,35-0,35------ | AL32: =VLOOKUP(AK32,Planilha1!B:C,2,0) -> 19 | AM32: CR-0171595-00 IP HARNESS carbon
C33: E16725300 | E33: 1.25 | F33: 2.1 | G33: 3.35 | L33: 0.75 | M33: 0.5 | S33: 0.35 | T33: 0.35 | U33: 0.35 | V33: 0.35 | W33: 0.35 | X33: 0.35 | AF33: X | AG33: X | AI33: 16 | AJ33: 2026 | AK33: =CONCATENATE(A33,"-",B33,"-",C33,"-",E33,"-",F33,"-",G33,"-",H33,"-",I33,"-",J33,"-",K33,"-",L33,"-",M33,"-",N33,"-",O33,"-",P33,"-",Q33,"-",R33,"-",S33,"-",T33,"-",U33,"-",V33,"-",W33,"-",X33,"-",Y33,"-",Z33,"-",AA33,"-",AB33,"-",AC33,"-",AD33) -> --E16725300-1,25-2,1-3,35-----0,75-0,5------0,35-0,35-0,35-0,35-0,35-0,35------ | AL33: =VLOOKUP(AK33,Planilha1!B:C,2,0) -> 19 | AM33: CR-0170489-00 IP
C34: E16725300 | E34: 0.5 | F34: 3 | G34: 3.5 | L34: 0.5 | S34: 2.5 | T34: 0.5 | AF34: X | AG34: X | AI34: 16 | AK34: =CONCATENATE(A34,"-",B34,"-",C34,"-",E34,"-",F34,"-",G34,"-",H34,"-",I34,"-",J34,"-",K34,"-",L34,"-",M34,"-",N34,"-",O34,"-",P34,"-",Q34,"-",R34,"-",S34,"-",T34,"-",U34,"-",V34,"-",W34,"-",X34,"-",Y34,"-",Z34,"-",AA34,"-",AB34,"-",AC34,"-",AD34) -> --E16725300-0,5-3-3,5-----0,5-------2,5-0,5---------- | AL34: =VLOOKUP(AK34,Planilha1!B:C,2,0) -> 20 | AM34: CR-0171595-00 IP HARNESS carbon
C35: 3299362G2 | E35: 0.35 | F35: 0.7 | G35: 1.05 | L35: 0.35 | S35: 0.35 | T35: 0.35 | AG35: X | AI35: 8 | AK35: =CONCATENATE(A35,"-",B35,"-",C35,"-",E35,"-",F35,"-",G35,"-",H35,"-",I35,"-",J35,"-",K35,"-",L35,"-",M35,"-",N35,"-",O35,"-",P35,"-",Q35,"-",R35,"-",S35,"-",T35,"-",U35,"-",V35,"-",W35,"-",X35,"-",Y35,"-",Z35,"-",AA35,"-",AB35,"-",AC35,"-",AD35) -> --3299362G2-0,35-0,7-1,05-----0,35-------0,35-0,35---------- | AL35: =VLOOKUP(AK35,Planilha1!B:C,2,0) -> 21 | AM35: CR-0171817-01 Liftgate Carbon
C36: 3299362G2 | E36: 2.85 | F36: 4 | G36: 6.85 | L36: 0.35 | M36: 2.5 | S36: 2.5 | T36: 0.5 | U36: 1 | AF36: X | AG36: X | AI36: 16 | AK36: =CONCATENATE(A36,"-",B36,"-",C36,"-",E36,"-",F36,"-",G36,"-",H36,"-",I36,"-",J36,"-",K36,"-",L36,"-",M36,"-",N36,"-",O36,"-",P36,"-",Q36,"-",R36,"-",S36,"-",T36,"-",U36,"-",V36,"-",W36,"-",X36,"-",Y36,"-",Z36,"-",AA36,"-",AB36,"-",AC36,"-",AD36) -> --3299362G2-2,85-4-6,85-----0,35-2,5------2,5-0,5-1--------- | AL36: =VLOOKUP(AK36,Planilha1!B:C,2,0) -> 22 | AM36: CR-0171817-01 Liftgate Carbon
C37: E02000700 | E37: 0.35 | F37: 1.05 | G37: 1.4 | L37: 0.35 | S37: 0.35 | T37: 0.35 | U37: 0.35 | AG37: X | AI37: 8 | AK37: =CONCATENATE(A37,"-",B37,"-",C37,"-",E37,"-",F37,"-",G37,"-",H37,"-",I37,"-",J37,"-",K37,"-",L37,"-",M37,"-",N37,"-",O37,"-",P37,"-",Q37,"-",R37,"-",S37,"-",T37,"-",U37,"-",V37,"-",W37,"-",X37,"-",Y37,"-",Z37,"-",AA37,"-",AB37,"-",AC37,"-",AD37) -> --E02000700-0,35-1,05-1,4-----0,35-------0,35-0,35-0,35--------- | AL37: =VLOOKUP(AK37,Planilha1!B:C,2,0) -> 23 | AM37: CR-0172035-00 Liftgate Ext
C38: E02000700 | E38: 0.35 | F38: 0.7 | G38: 1.05 | L38: 0.35 | S38: 0.35 | T38: 0.35 | AG38: X | AI38: 8 | AK38: =CONCATENATE(A38,"-",B38,"-",C38,"-",E38,"-",F38,"-",G38,"-",H38,"-",I38,"-",J38,"-",K38,"-",L38,"-",M38,"-",N38,"-",O38,"-",P38,"-",Q38,"-",R38,"-",S38,"-",T38,"-",U38,"-",V38,"-",W38,"-",X38,"-",Y38,"-",Z38,"-",AA38,"-",AB38,"-",AC38,"-",AD38) -> --E02000700-0,35-0,7-1,05-----0,35-------0,35-0,35---------- | AL38: =VLOOKUP(AK38,Planilha1!B:C,2,0) -> 24 | AM38: CR-0172035-00 Liftgate Ext
C39: E02000700 | E39: 1.05 | F39: 1.05 | G39: 2.1 | L39: 0.35 | M39: 0.35 | N39: 0.35 | S39: 0.35 | T39: 0.35 | U39: 0.35 | AG39: X | AI39: 8 | AK39: =CONCATENATE(A39,"-",B39,"-",C39,"-",E39,"-",F39,"-",G39,"-",H39,"-",I39,"-",J39,"-",K39,"-",L39,"-",M39,"-",N39,"-",O39,"-",P39,"-",Q39,"-",R39,"-",S39,"-",T39,"-",U39,"-",V39,"-",W39,"-",X39,"-",Y39,"-",Z39,"-",AA39,"-",AB39,"-",AC39,"-",AD39) -> --E02000700-1,05-1,05-2,1-----0,35-0,35-0,35-----0,35-0,35-0,35--------- | AL39: =VLOOKUP(AK39,Planilha1!B:C,2,0) -> 25 | AM39: CR-0172102-00 Rear Bumper Carbon
C40: E02000700 | E40: 1.05 | F40: 0.35 | G40: 1.4 | L40: 0.35 | M40: 0.35 | N40: 0.35 | S40: 0.35 | AG40: X | AI40: 8 | AK40: =CONCATENATE(A40,"-",B40,"-",C40,"-",E40,"-",F40,"-",G40,"-",H40,"-",I40,"-",J40,"-",K40,"-",L40,"-",M40,"-",N40,"-",O40,"-",P40,"-",Q40,"-",R40,"-",S40,"-",T40,"-",U40,"-",V40,"-",W40,"-",X40,"-",Y40,"-",Z40,"-",AA40,"-",AB40,"-",AC40,"-",AD40) -> --E02000700-1,05-0,35-1,4-----0,35-0,35-0,35-----0,35----------- | AL40: =VLOOKUP(AK40,Planilha1!B:C,2,0) -> 26 | AM40: CR-0172102-00 Rear Bumper Carbon
C41: E02000700 | E41: 1.4 | F41: 0.7 | G41: 2.1 | L41: 0.35 | M41: 0.35 | N41: 0.35 | O41: 0.35 | S41: 0.35 | T41: 0.35 | AG41: X | AI41: 8 | AK41: =CONCATENATE(A41,"-",B41,"-",C41,"-",E41,"-",F41,"-",G41,"-",H41,"-",I41,"-",J41,"-",K41,"-",L41,"-",M41,"-",N41,"-",O41,"-",P41,"-",Q41,"-",R41,"-",S41,"-",T41,"-",U41,"-",V41,"-",W41,"-",X41,"-",Y41,"-",Z41,"-",AA41,"-",AB41,"-",AC41,"-",AD41) -> --E02000700-1,4-0,7-2,1-----0,35-0,35-0,35-0,35----0,35-0,35---------- | AL41: =VLOOKUP(AK41,Planilha1!B:C,2,0) -> 27 | AM41: CR-0172102-00 Rear Bumper Carbon
C42: E02000700 | E42: 0.5 | F42: 1.25 | G42: 1.75 | L42: 0.5 | S42: 0.5 | T42: 0.75 | AG42: X | AI42: 8 | AK42: =CONCATENATE(A42,"-",B42,"-",C42,"-",E42,"-",F42,"-",G42,"-",H42,"-",I42,"-",J42,"-",K42,"-",L42,"-",M42,"-",N42,"-",O42,"-",P42,"-",Q42,"-",R42,"-",S42,"-",T42,"-",U42,"-",V42,"-",W42,"-",X42,"-",Y42,"-",Z42,"-",AA42,"-",AB42,"-",AC42,"-",AD42) -> --E02000700-0,5-1,25-1,75-----0,5-------0,5-0,75---------- | AL42: =VLOOKUP(AK42,Planilha1!B:C,2,0) -> 28 | AM42: CR-0172352-00 Front Bumper Carbon
C43: E02000700 | E43: 1 | F43: 0.5 | G43: 1.5 | L43: 0.5 | M43: 0.5 | S43: 0.5 | AG43: X | AI43: 8 | AK43: =CONCATENATE(A43,"-",B43,"-",C43,"-",E43,"-",F43,"-",G43,"-",H43,"-",I43,"-",J43,"-",K43,"-",L43,"-",M43,"-",N43,"-",O43,"-",P43,"-",Q43,"-",R43,"-",S43,"-",T43,"-",U43,"-",V43,"-",W43,"-",X43,"-",Y43,"-",Z43,"-",AA43,"-",AB43,"-",AC43,"-",AD43) -> --E02000700-1-0,5-1,5-----0,5-0,5------0,5----------- | AL43: =VLOOKUP(AK43,Planilha1!B:C,2,0) -> 29 | AM43: CR-0172352-00 Front Bumper Carbon
C44: E02000700 | E44: 1.05 | F44: 1.4 | G44: 2.45 | L44: 0.35 | M44: 0.35 | N44: 0.35 | S44: 0.35 | T44: 0.35 | U44: 0.35 | V44: 0.35 | AG44: X | AI44: 8 | AK44: =CONCATENATE(A44,"-",B44,"-",C44,"-",E44,"-",F44,"-",G44,"-",H44,"-",I44,"-",J44,"-",K44,"-",L44,"-",M44,"-",N44,"-",O44,"-",P44,"-",Q44,"-",R44,"-",S44,"-",T44,"-",U44,"-",V44,"-",W44,"-",X44,"-",Y44,"-",Z44,"-",AA44,"-",AB44,"-",AC44,"-",AD44) -> --E02000700-1,05-1,4-2,45-----0,35-0,35-0,35-----0,35-0,35-0,35-0,35-------- | AL44: =VLOOKUP(AK44,Planilha1!B:C,2,0) -> 30 | AM44: CR-0172352-00 Front Bumper Carbon
C45: E02000700 | E45: 1 | F45: 0.5 | G45: 1.5 | L45: 0.5 | M45: 0.5 | S45: 0.5 | AG45: X | AI45: 8 | AJ45: 2026 | AK45: =CONCATENATE(A45,"-",B45,"-",C45,"-",E45,"-",F45,"-",G45,"-",H45,"-",I45,"-",J45,"-",K45,"-",L45,"-",M45,"-",N45,"-",O45,"-",P45,"-",Q45,"-",R45,"-",S45,"-",T45,"-",U45,"-",V45,"-",W45,"-",X45,"-",Y45,"-",Z45,"-",AA45,"-",AB45,"-",AC45,"-",AD45) -> --E02000700-1-0,5-1,5-----0,5-0,5-- ----0,5----------- | AL45: =VLOOKUP(AK45,Planilha1!B:C,2,0) -> 31 | AM45: CR-0160595-02 ENGINE
C46: E02000700 | E46: 1250 | F46: 0.5 | G46: 1.75 | L46: 0.5 | M46: 0.75 | S46: 0.5 | AF46: X | AG46: X | AI46: 16 | AJ46: 2026 | AK46: =CONCATENATE(A46,"-",B46,"-",C46,"-",E46,"-",F46,"-",G46,"-",H46,"-",I46,"-",J46,"-",K46,"-",L46,"-",M46,"-",N46,"-",O46,"-",P46,"-",Q46,"-",R46,"-",S46,"-",T46,"-",U46,"-",V46,"-",W46,"-",X46,"-",Y46,"-",Z46,"-",AA46,"-",AB46,"-",AC46,"-",AD46) -> --E02000700-1250-0,5-1,75-----0,5-0,75------0,5----------- | AL46: =VLOOKUP(AK46,Planilha1!B:C,2,0) -> 32 | AM46: CR-0162419-01 FRONT BUMPER
E47: 0 | F47: 0.35 | G47: 0.35 | S47: 0.35 | AF47: X | AG47: X | AI47: 16 | AJ47: 2026 | AK47: =CONCATENATE(A47,"-",B47,"-",C47,"-",E47,"-",F47,"-",G47,"-",H47,"-",I47,"-",J47,"-",K47,"-",L47,"-",M47,"-",N47,"-",O47,"-",P47,"-",Q47,"-",R47,"-",S47,"-",T47,"-",U47,"-",V47,"-",W47,"-",X47,"-",Y47,"-",Z47,"-",AA47,"-",AB47,"-",AC47,"-",AD47) -> ---0-0,35-0,35------------0,35----------- | AL47: =VLOOKUP(AK47,Planilha1!B:C,2,0) -> 33 | AM47: CR-0162211-00 IP
C48: E16718500 | E48: 1.25 | F48: 0.5 | G48: 1.75 | L48: 0.75 | M48: 0.5 | S48: 0.5 | AF48: X | AG48: X | AI48: 16 | AJ48: 2026 | AK48: =CONCATENATE(A48,"-",B48,"-",C48,"-",E48,"-",F48,"-",G48,"-",H48,"-",I48,"-",J48,"-",K48,"-",L48,"-",M48,"-",N48,"-",O48,"-",P48,"-",Q48,"-",R48,"-",S48,"-",T48,"-",U48,"-",V48,"-",W48,"-",X48,"-",Y48,"-",Z48,"-",AA48,"-",AB48,"-",AC48,"-",AD48) -> --E16718500-1,25-0,5-1,75-----0,75-0,5------0,5----------- | AL48: =VLOOKUP(AK48,Planilha1!B:C,2,0) -> 34 | AM48: CR-0162211-00 IP
C49: E16718500 | E49: 0.75 | F49: 1 | G49: 1.75 | L49: 0.75 | S49: 0.5 | T49: 0.5 | AF49: X | AG49: X | AI49: 16 | AJ49: 2026 | AK49: =CONCATENATE(A49,"-",B49,"-",C49,"-",E49,"-",F49,"-",G49,"-",H49,"-",I49,"-",J49,"-",K49,"-",L49,"-",M49,"-",N49,"-",O49,"-",P49,"-",Q49,"-",R49,"-",S49,"-",T49,"-",U49,"-",V49,"-",W49,"-",X49,"-",Y49,"-",Z49,"-",AA49,"-",AB49,"-",AC49,"-",AD49) -> --E16718500-0,75-1-1,75-----0,75-------0,5-0,5---------- | AL49: =VLOOKUP(AK49,Planilha1!B:C,2,0) -> 35 | AM49: CR-0162211-00 IP
C50: E16718500 | E50: 0.75 | F50: 1 | G50: 1.75 | L50: 0.75 | S50: 0.5 | T50: 0.5 | AF50: X | AG50: X | AI50: 16 | AJ50: 2026 | AK50: =CONCATENATE(A50,"-",B50,"-",C50,"-",E50,"-",F50,"-",G50,"-",H50,"-",I50,"-",J50,"-",K50,"-",L50,"-",M50,"-",N50,"-",O50,"-",P50,"-",Q50,"-",R50,"-",S50,"-",T50,"-",U50,"-",V50,"-",W50,"-",X50,"-",Y50,"-",Z50,"-",AA50,"-",AB50,"-",AC50,"-",AD50) -> --E16718500-0,75-1-1,75-----0,75-------0,5-0,5---------- | AL50: =VLOOKUP(AK50,Planilha1!B:C,2,0) -> 35 | AM50: CR-0162211-00 IP
C51: E16718500 | E51: 0.75 | F51: 1 | G51: 1.75 | L51: 0.75 | S51: 0.5 | T51: 0.5 | AF51: X | AG51: X | AI51: 16 | AJ51: 2026 | AK51: =CONCATENATE(A51,"-",B51,"-",C51,"-",E51,"-",F51,"-",G51,"-",H51,"-",I51,"-",J51,"-",K51,"-",L51,"-",M51,"-",N51,"-",O51,"-",P51,"-",Q51,"-",R51,"-",S51,"-",T51,"-",U51,"-",V51,"-",W51,"-",X51,"-",Y51,"-",Z51,"-",AA51,"-",AB51,"-",AC51,"-",AD51) -> --E16718500-0,75-1-1,75-----0,75-------0,5-0,5---------- | AL51: =VLOOKUP(AK51,Planilha1!B:C,2,0) -> 35 | AM51: CR-0170489-00 IP
C52: E16718500 | E52: 0.5 | F52: 2.25 | G52: 2.75 | L52: 0.5 | S52: 0.5 | T52: 0.5 | U52: 0.75 | AF52: X | AG52: X | AI52: 16 | AJ52: 2026 | AK52: =CONCATENATE(A52,"-",B52,"-",C52,"-",E52,"-",F52,"-",G52,"-",H52,"-",I52,"-",J52,"-",K52,"-",L52,"-",M52,"-",N52,"-",O52,"-",P52,"-",Q52,"-",R52,"-",S52,"-",T52,"-",U52,"-",V52,"-",W52,"-",X52,"-",Y52,"-",Z52,"-",AA52,"-",AB52,"-",AC52,"-",AD52) -> --E16718500-0,5-2,25-2,75-----0,5-------0,5-0,5-0,75--------- | AL52: =VLOOKUP(AK52,Planilha1!B:C,2,0) -> 36 | AM52: CR-0162211-00 IP
C53: E16718500 | E53: 1.5 | F53: 0.75 | G53: 2.25 | L53: 0.5 | M53: 0.5 | N53: 0.5 | S53: 0.75 | AF53: X | AG53: X | AI53: 16 | AJ53: 2026 | AK53: =CONCATENATE(A53,"-",B53,"-",C53,"-",E53,"-",F53,"-",G53,"-",H53,"-",I53,"-",J53,"-",K53,"-",L53,"-",M53,"-",N53,"-",O53,"-",P53,"-",Q53,"-",R53,"-",S53,"-",T53,"-",U53,"-",V53,"-",W53,"-",X53,"-",Y53,"-",Z53,"-",AA53,"-",AB53,"-",AC53,"-",AD53) -> --E16718500-1,5-0,75-2,25-----0,5-0,5-0,5-----0,75----------- | AL53: =VLOOKUP(AK53,Planilha1!B:C,2,0) -> 37 | AM53: CR-0162211-00 IP
C54: E16725300 | E54: 1.25 | F54: 0.7 | G54: 1.95 | L54: 0.75 | M54: 0.5 | S54: 0.35 | T54: 0.35 | AF54: X | AG54: X | AI54: 16 | AJ54: 2026 | AK54: =CONCATENATE(A54,"-",B54,"-",C54,"-",E54,"-",F54,"-",G54,"-",H54,"-",I54,"-",J54,"-",K54,"-",L54,"-",M54,"-",N54,"-",O54,"-",P54,"-",Q54,"-",R54,"-",S54,"-",T54,"-",U54,"-",V54,"-",W54,"-",X54,"-",Y54,"-",Z54,"-",AA54,"-",AB54,"-",AC54,"-",AD54) -> --E16725300-1,25-0,7-1,95-----0,75-0,5------0,35-0,35---------- | AL54: =VLOOKUP(AK54,Planilha1!B:C,2,0) -> 38 | AM54: CR-0162211-00 IP
C55: E16725300 | E55: 1.25 | F55: 0.7 | G55: 1.95 | L55: 0.75 | M55: 0.5 | S55: 0.35 | T55: 0.35 | AF55: X | AG55: X | AI55: 16 | AJ55: 2026 | AK55: =CONCATENATE(A55,"-",B55,"-",C55,"-",E55,"-",F55,"-",G55,"-",H55,"-",I55,"-",J55,"-",K55,"-",L55,"-",M55,"-",N55,"-",O55,"-",P55,"-",Q55,"-",R55,"-",S55,"-",T55,"-",U55,"-",V55,"-",W55,"-",X55,"-",Y55,"-",Z55,"-",AA55,"-",AB55,"-",AC55,"-",AD55) -> --E16725300-1,25-0,7-1,95-----0,75-0,5------0,35-0,35---------- | AL55: =VLOOKUP(AK55,Planilha1!B:C,2,0) -> 38 | AM55: CR-0170489-00 IP
C56: E16725300 | E56: 1.25 | F56: 1.4 | G56: 2.65 | L56: 0.75 | M56: 0.5 | S56: 0.35 | T56: 0.35 | U56: 0.35 | V56: 0.35 | AF56: X | AG56: X | AI56: 16 | AJ56: 2026 | AK56: =CONCATENATE(A56,"-",B56,"-",C56,"-",E56,"-",F56,"-",G56,"-",H56,"-",I56,"-",J56,"-",K56,"-",L56,"-",M56,"-",N56,"-",O56,"-",P56,"-",Q56,"-",R56,"-",S56,"-",T56,"-",U56,"-",V56,"-",W56,"-",X56,"-",Y56,"-",Z56,"-",AA56,"-",AB56,"-",AC56,"-",AD56) -> --E16725300-1,25-1,4-2,65-----0,75-0,5------0,35-0,35-0,35-0,35-------- | AL56: =VLOOKUP(AK56,Planilha1!B:C,2,0) -> 39 | AM56: CR-0162211-00 IP
C57: E16725300 | E57: 1.25 | F57: 1.4 | G57: 2.65 | L57: 0.75 | M57: 0.5 | S57: 0.35 | T57: 0.35 | U57: 0.35 | V57: 0.35 | AF57: X | AG57: X | AI57: 16 | AJ57: 2026 | AK57: =CONCATENATE(A57,"-",B57,"-",C57,"-",E57,"-",F57,"-",G57,"-",H57,"-",I57,"-",J57,"-",K57,"-",L57,"-",M57,"-",N57,"-",O57,"-",P57,"-",Q57,"-",R57,"-",S57,"-",T57,"-",U57,"-",V57,"-",W57,"-",X57,"-",Y57,"-",Z57,"-",AA57,"-",AB57,"-",AC57,"-",AD57) -> --E16725300-1,25-1,4-2,65-----0,75-0,5------0,35-0,35-0,35-0,35-------- | AL57: =VLOOKUP(AK57,Planilha1!B:C,2,0) -> 39 | AM57: CR-0162211-00 IP
C58: E16725300 | E58: 1.25 | F58: 1.4 | G58: 2.65 | L58: 0.75 | M58: 0.5 | S58: 0.35 | T58: 0.35 | U58: 0.35 | V58: 0.35 | AF58: X | AG58: X | AI58: 16 | AJ58: 2026 | AK58: =CONCATENATE(A58,"-",B58,"-",C58,"-",E58,"-",F58,"-",G58,"-",H58,"-",I58,"-",J58,"-",K58,"-",L58,"-",M58,"-",N58,"-",O58,"-",P58,"-",Q58,"-",R58,"-",S58,"-",T58,"-",U58,"-",V58,"-",W58,"-",X58,"-",Y58,"-",Z58,"-",AA58,"-",AB58,"-",AC58,"-",AD58) -> --E16725300-1,25-1,4-2,65-----0,75-0,5------0,35-0,35-0,35-0,35-------- | AL58: =VLOOKUP(AK58,Planilha1!B:C,2,0) -> 39 | AM58: CR-0170489-00 IP
C59: E16725300 | E59: 1.25 | F59: 0.35 | G59: 1.6 | L59: 0.75 | M59: 0.5 | S59: 0.35 | AF59: X | AG59: X | AI59: 16 | AJ59: 2026 | AK59: =CONCATENATE(A59,"-",B59,"-",C59,"-",E59,"-",F59,"-",G59,"-",H59,"-",I59,"-",J59,"-",K59,"-",L59,"-",M59,"-",N59,"-",O59,"-",P59,"-",Q59,"-",R59,"-",S59,"-",T59,"-",U59,"-",V59,"-",W59,"-",X59,"-",Y59,"-",Z59,"-",AA59,"-",AB59,"-",AC59,"-",AD59) -> --E16725300-1,25-0,35-1,6-----0,75-0,5------0,35----------- | AL59: =VLOOKUP(AK59,Planilha1!B:C,2,0) -> 40 | AM59: CR-0162211-00 IP
C60: E16725300 | E60: 1.1 | F60: 1.2 | G60: 2.3 | L60: 0.35 | M60: 0.75 | S60: 0.35 | T60: 0.35 | U60: 0.5 | AF60: X | AG60: X | AI60: 16 | AJ60: 2026 | AK60: =CONCATENATE(A60,"-",B60,"-",C60,"-",E60,"-",F60,"-",G60,"-",H60,"-",I60,"-",J60,"-",K60,"-",L60,"-",M60,"-",N60,"-",O60,"-",P60,"-",Q60,"-",R60,"-",S60,"-",T60,"-",U60,"-",V60,"-",W60,"-",X60,"-",Y60,"-",Z60,"-",AA60,"-",AB60,"-",AC60,"-",AD60) -> --E16725300-1,1-1,2-2,3-----0,35-0,75------0,35-0,35-0,5--------- | AL60: =VLOOKUP(AK60,Planilha1!B:C,2,0) -> 41 | AM60: CR-0162211-00 IP
C61: E16725300 | E61: 1.1 | F61: 1.2 | G61: 2.3 | L61: 0.35 | M61: 0.75 | S61: 0.35 | T61: 0.35 | U61: 0.5 | AF61: X | AG61: X | AI61: 16 | AJ61: 2026 | AK61: =CONCATENATE(A61,"-",B61,"-",C61,"-",E61,"-",F61,"-",G61,"-",H61,"-",I61,"-",J61,"-",K61,"-",L61,"-",M61,"-",N61,"-",O61,"-",P61,"-",Q61,"-",R61,"-",S61,"-",T61,"-",U61,"-",V61,"-",W61,"-",X61,"-",Y61,"-",Z61,"-",AA61,"-",AB61,"-",AC61,"-",AD61) -> --E16725300-1,1-1,2-2,3-----0,35-0,75------0,35-0,35-0,5--------- | AL61: =VLOOKUP(AK61,Planilha1!B:C,2,0) -> 41 | AM61: CR-0170489-00 IP
C62: E16725300 | E62: 1.1 | F62: 0.85 | G62: 1.95 | L62: 0.35 | M62: 0.75 | S62: 0.35 | T62: 0.5 | AF62: X | AG62: X | AI62: 16 | AJ62: 2026 | AK62: =CONCATENATE(A62,"-",B62,"-",C62,"-",E62,"-",F62,"-",G62,"-",H62,"-",I62,"-",J62,"-",K62,"-",L62,"-",M62,"-",N62,"-",O62,"-",P62,"-",Q62,"-",R62,"-",S62,"-",T62,"-",U62,"-",V62,"-",W62,"-",X62,"-",Y62,"-",Z62,"-",AA62,"-",AB62,"-",AC62,"-",AD62) -> --E16725300-1,1-0,85-1,95-----0,35-0,75------0,35-0,5---------- | AL62: =VLOOKUP(AK62,Planilha1!B:C,2,0) -> 42 | AM62: CR-0162211-00 IP
C63: E16718500 | E63: 1.85 | F63: 0 | G63: 1.85 | L63: 0.75 | M63: 0.75 | N63: 0.35 | AF63: X | AG63: X | AI63: 16 | AJ63: 2026 | AK63: =CONCATENATE(A63,"-",B63,"-",C63,"-",E63,"-",F63,"-",G63,"-",H63,"-",I63,"-",J63,"-",K63,"-",L63,"-",M63,"-",N63,"-",O63,"-",P63,"-",Q63,"-",R63,"-",S63,"-",T63,"-",U63,"-",V63,"-",W63,"-",X63,"-",Y63,"-",Z63,"-",AA63,"-",AB63,"-",AC63,"-",AD63) -> --E16718500-1,85-0-1,85-----0,75-0,75-0,35---------------- | AL63: =VLOOKUP(AK63,Planilha1!B:C,2,0) -> 43 | AM63: CR-0162211-00 IP
C64: E16725300 | E64: 0 | F64: 3 | G64: 3 | S64: 2.5 | T64: 0.5 | AF64: X | AG64: X | AI64: 16 | AJ64: 2026 | AK64: =CONCATENATE(A64,"-",B64,"-",C64,"-",E64,"-",F64,"-",G64,"-",H64,"-",I64,"-",J64,"-",K64,"-",L64,"-",M64,"-",N64,"-",O64,"-",P64,"-",Q64,"-",R64,"-",S64,"-",T64,"-",U64,"-",V64,"-",W64,"-",X64,"-",Y64,"-",Z64,"-",AA64,"-",AB64,"-",AC64,"-",AD64) -> --E16725300-0-3-3------------2,5-0,5---------- | AL64: =VLOOKUP(AK64,Planilha1!B:C,2,0) -> 44 | AM64: CR-0162211-00 IP
C65: E16725300 | E65: 3 | F65: 0 | G65: 3 | L65: 2.5 | M65: 0.5 | AF65: X | AG65: X | AI65: 16 | AJ65: 2026 | AK65: =CONCATENATE(A65,"-",B65,"-",C65,"-",E65,"-",F65,"-",G65,"-",H65,"-",I65,"-",J65,"-",K65,"-",L65,"-",M65,"-",N65,"-",O65,"-",P65,"-",Q65,"-",R65,"-",S65,"-",T65,"-",U65,"-",V65,"-",W65,"-",X65,"-",Y65,"-",Z65,"-",AA65,"-",AB65,"-",AC65,"-",AD65) -> --E16725300-3-0-3-----2,5-0,5----------------- | AL65: =VLOOKUP(AK65,Planilha1!B:C,2,0) -> 45 | AM65: CR-0162211-00 IP
C66: E16718500 | E66: 1 | F66: 0.5 | G66: 1.5 | L66: 0.5 | M66: 0.5 | S66: 0.5 | AG66: X | AI66: 8 | AJ66: 2026 | AK66: =CONCATENATE(A66,"-",B66,"-",C66,"-",E66,"-",F66,"-",G66,"-",H66,"-",I66,"-",J66,"-",K66,"-",L66,"-",M66,"-",N66,"-",O66,"-",P66,"-",Q66,"-",R66,"-",S66,"-",T66,"-",U66,"-",V66,"-",W66,"-",X66,"-",Y66,"-",Z66,"-",AA66,"-",AB66,"-",AC66,"-",AD66) -> --E16718500-1-0,5-1,5-----0,5-0,5------0,5----------- | AL66: =VLOOKUP(AK66,Planilha1!B:C,2,0) -> 46 | AM66: CR-0162211-00 IP
C67: E16718500 | E67: 1 | F67: 0.5 | G67: 1.5 | L67: 0.5 | M67: 0.5 | S67: 0.5 | AG67: X | AI67: 8 | AJ67: 2026 | AK67: =CONCATENATE(A67,"-",B67,"-",C67,"-",E67,"-",F67,"-",G67,"-",H67,"-",I67,"-",J67,"-",K67,"-",L67,"-",M67,"-",N67,"-",O67,"-",P67,"-",Q67,"-",R67,"-",S67,"-",T67,"-",U67,"-",V67,"-",W67,"-",X67,"-",Y67,"-",Z67,"-",AA67,"-",AB67,"-",AC67,"-",AD67) -> --E16718500-1-0,5-1,5-----0,5-0,5------0,5----------- | AL67: =VLOOKUP(AK67,Planilha1!B:C,2,0) -> 46 | AM67: CR-0162211-00 IP
C68: E16718500 | E68: 1 | F68: 0.5 | G68: 1.5 | L68: 0.5 | M68: 0.5 | S68: 0.5 | AF68: X | AG68: X | AI68: 16 | AJ68: 2026 | AK68: =CONCATENATE(A68,"-",B68,"-",C68,"-",E68,"-",F68,"-",G68,"-",H68,"-",I68,"-",J68,"-",K68,"-",L68,"-",M68,"-",N68,"-",O68,"-",P68,"-",Q68,"-",R68,"-",S68,"-",T68,"-",U68,"-",V68,"-",W68,"-",X68,"-",Y68,"-",Z68,"-",AA68,"-",AB68,"-",AC68,"-",AD68) -> --E16718500-1-0,5-1,5-----0,5-0,5------0,5----------- | AL68: =VLOOKUP(AK68,Planilha1!B:C,2,0) -> 46 | AM68: CR-0164612-01 BODY | AN68: foi considerado na CR 9 validações uscar45 e 21 GMW17136( necesidade 26 GMW17136 e 18 Uscar45)
C69: E16718500 | E69: 0.35 | F69: 0.35 | G69: 0.7 | L69: 0.35 | S69: 0.35 | AG69: X | AI69: 8 | AJ69: 2026 | AK69: =CONCATENATE(A69,"-",B69,"-",C69,"-",E69,"-",F69,"-",G69,"-",H69,"-",I69,"-",J69,"-",K69,"-",L69,"-",M69,"-",N69,"-",O69,"-",P69,"-",Q69,"-",R69,"-",S69,"-",T69,"-",U69,"-",V69,"-",W69,"-",X69,"-",Y69,"-",Z69,"-",AA69,"-",AB69,"-",AC69,"-",AD69) -> --E16718500-0,35-0,35-0,7-----0,35-------0,35----------- | AL69: =VLOOKUP(AK69,Planilha1!B:C,2,0) -> 47 | AM69: CR-0162211-00 IP
C70: E16718500 | E70: 0.35 | F70: 0.35 | G70: 0.7 | L70: 0.35 | S70: 0.35 | AG70: X | AI70: 8 | AJ70: 2026 | AK70: =CONCATENATE(A70,"-",B70,"-",C70,"-",E70,"-",F70,"-",G70,"-",H70,"-",I70,"-",J70,"-",K70,"-",L70,"-",M70,"-",N70,"-",O70,"-",P70,"-",Q70,"-",R70,"-",S70,"-",T70,"-",U70,"-",V70,"-",W70,"-",X70,"-",Y70,"-",Z70,"-",AA70,"-",AB70,"-",AC70,"-",AD70) -> --E16718500-0,35-0,35-0,7-----0,35-------0,35----------- | AL70: =VLOOKUP(AK70,Planilha1!B:C,2,0) -> 47 | AM70: CR-0168269-00 BODY
C71: E16718500 | E71: 0.5 | F71: 1 | G71: 1.5 | L71: 0.5 | S71: 0.5 | T71: 0.5 | AG71: X | AI71: 8 | AJ71: 2026 | AK71: =CONCATENATE(A71,"-",B71,"-",C71,"-",E71,"-",F71,"-",G71,"-",H71,"-",I71,"-",J71,"-",K71,"-",L71,"-",M71,"-",N71,"-",O71,"-",P71,"-",Q71,"-",R71,"-",S71,"-",T71,"-",U71,"-",V71,"-",W71,"-",X71,"-",Y71,"-",Z71,"-",AA71,"-",AB71,"-",AC71,"-",AD71) -> --E16718500-0,5-1-1,5-----0,5-------0,5-0,5---------- | AL71: =VLOOKUP(AK71,Planilha1!B:C,2,0) -> 48 | AM71: CR-0162211-00 IP
C72: E16718500 | E72: 0.5 | F72: 1 | G72: 1.5 | L72: 0.5 | S72: 0.5 | T72: 0.5 | AG72: X | AI72: 8 | AJ72: 2026 | AK72: =CONCATENATE(A72,"-",B72,"-",C72,"-",E72,"-",F72,"-",G72,"-",H72,"-",I72,"-",J72,"-",K72,"-",L72,"-",M72,"-",N72,"-",O72,"-",P72,"-",Q72,"-",R72,"-",S72,"-",T72,"-",U72,"-",V72,"-",W72,"-",X72,"-",Y72,"-",Z72,"-",AA72,"-",AB72,"-",AC72,"-",AD72) -> --E16718500-0,5-1-1,5-----0,5-------0,5-0,5---------- | AL72: =VLOOKUP(AK72,Planilha1!B:C,2,0) -> 48 | AM72: CR-0162211-00 IP
C73: E16718500 | E73: 0 | F73: 1.75 | G73: 1.75 | S73: 0.5 | T73: 0.75 | U73: 0.5 | AG73: X | AI73: 8 | AJ73: 2026 | AK73: =CONCATENATE(A73,"-",B73,"-",C73,"-",E73,"-",F73,"-",G73,"-",H73,"-",I73,"-",J73,"-",K73,"-",L73,"-",M73,"-",N73,"-",O73,"-",P73,"-",Q73,"-",R73,"-",S73,"-",T73,"-",U73,"-",V73,"-",W73,"-",X73,"-",Y73,"-",Z73,"-",AA73,"-",AB73,"-",AC73,"-",AD73) -> --E16718500-0-1,75-1,75------------0,5-0,75-0,5--------- | AL73: =VLOOKUP(AK73,Planilha1!B:C,2,0) -> 49 | AM73: CR-0162211-00 IP
C74: E16725300 | E74: 1.35 | F74: 1.55 | G74: 2.9 | L74: 0.35 | M74: 1 | S74: 0.35 | T74: 0.35 | U74: 0.35 | V74: 0.5 | AG74: X | AI74: 8 | AJ74: 2026 | AK74: =CONCATENATE(A74,"-",B74,"-",C74,"-",E74,"-",F74,"-",G74,"-",H74,"-",I74,"-",J74,"-",K74,"-",L74,"-",M74,"-",N74,"-",O74,"-",P74,"-",Q74,"-",R74,"-",S74,"-",T74,"-",U74,"-",V74,"-",W74,"-",X74,"-",Y74,"-",Z74,"-",AA74,"-",AB74,"-",AC74,"-",AD74) -> --E16725300-1,35-1,55-2,9-----0,35-1------0,35-0,35-0,35-0,5-------- | AL74: =VLOOKUP(AK74,Planilha1!B:C,2,0) -> 50 | AM74: CR-0162211-00 IP
C75: E16725300 | E75: 1.35 | F75: 1.55 | G75: 2.9 | L75: 0.35 | M75: 1 | S75: 0.35 | T75: 0.35 | U75: 0.35 | V75: 0.5 | AF75: X | AG75: X | AI75: 16 | AJ75: 2026 | AK75: =CONCATENATE(A75,"-",B75,"-",C75,"-",E75,"-",F75,"-",G75,"-",H75,"-",I75,"-",J75,"-",K75,"-",L75,"-",M75,"-",N75,"-",O75,"-",P75,"-",Q75,"-",R75,"-",S75,"-",T75,"-",U75,"-",V75,"-",W75,"-",X75,"-",Y75,"-",Z75,"-",AA75,"-",AB75,"-",AC75,"-",AD75) -> --E16725300-1,35-1,55-2,9-----0,35-1------0,35-0,35-0,35-0,5-------- | AL75: =VLOOKUP(AK75,Planilha1!B:C,2,0) -> 50 | AM75: CR-0170489-00 IP
C76: E16718500 | E76: 1.4 | F76: 1.05 | G76: 2.45 | L76: 0.35 | M76: 0.35 | N76: 0.35 | O76: 0.35 | S76: 0.35 | T76: 0.35 | U76: 0.35 | AG76: X | AI76: 8 | AJ76: 2026 | AK76: =CONCATENATE(A76,"-",B76,"-",C76,"-",E76,"-",F76,"-",G76,"-",H76,"-",I76,"-",J76,"-",K76,"-",L76,"-",M76,"-",N76,"-",O76,"-",P76,"-",Q76,"-",R76,"-",S76,"-",T76,"-",U76,"-",V76,"-",W76,"-",X76,"-",Y76,"-",Z76,"-",AA76,"-",AB76,"-",AC76,"-",AD76) -> --E16718500-1,4-1,05-2,45-----0,35-0,35-0,35-0,35----0,35-0,35-0,35--------- | AL76: =VLOOKUP(AK76,Planilha1!B:C,2,0) -> 51 | AM76: CR-0162211-00 IP
C77: E16718500 | E77: 1.4 | F77: 1.05 | G77: 2.45 | L77: 0.35 | M77: 0.35 | N77: 0.35 | O77: 0.35 | S77: 0.35 | T77: 0.35 | U77: 0.35 | AG77: X | AI77: 8 | AJ77: 2026 | AK77: =CONCATENATE(A77,"-",B77,"-",C77,"-",E77,"-",F77,"-",G77,"-",H77,"-",I77,"-",J77,"-",K77,"-",L77,"-",M77,"-",N77,"-",O77,"-",P77,"-",Q77,"-",R77,"-",S77,"-",T77,"-",U77,"-",V77,"-",W77,"-",X77,"-",Y77,"-",Z77,"-",AA77,"-",AB77,"-",AC77,"-",AD77) -> --E16718500-1,4-1,05-2,45-----0,35-0,35-0,35-0,35----0,35-0,35-0,35--------- | AL77: =VLOOKUP(AK77,Planilha1!B:C,2,0) -> 51 | AM77: CR-0162211-00 IP
C78: E16718500 | E78: 1.05 | F78: 1.05 | G78: 2.1 | L78: 0.35 | M78: 0.35 | N78: 0.35 | S78: 0.35 | T78: 0.35 | U78: 0.35 | AG78: X | AI78: 8 | AJ78: 2026 | AK78: =CONCATENATE(A78,"-",B78,"-",C78,"-",E78,"-",F78,"-",G78,"-",H78,"-",I78,"-",J78,"-",K78,"-",L78,"-",M78,"-",N78,"-",O78,"-",P78,"-",Q78,"-",R78,"-",S78,"-",T78,"-",U78,"-",V78,"-",W78,"-",X78,"-",Y78,"-",Z78,"-",AA78,"-",AB78,"-",AC78,"-",AD78) -> --E16718500-1,05-1,05-2,1-----0,35-0,35-0,35-----0,35-0,35-0,35--------- | AL78: =VLOOKUP(AK78,Planilha1!B:C,2,0) -> 52 | AM78: CR-0162211-00 IP
C79: E16718500 | E79: 1.05 | F79: 1.05 | G79: 2.1 | L79: 0.35 | M79: 0.35 | N79: 0.35 | S79: 0.35 | T79: 0.35 | U79: 0.35 | AG79: X | AI79: 8 | AJ79: 2026 | AK79: =CONCATENATE(A79,"-",B79,"-",C79,"-",E79,"-",F79,"-",G79,"-",H79,"-",I79,"-",J79,"-",K79,"-",L79,"-",M79,"-",N79,"-",O79,"-",P79,"-",Q79,"-",R79,"-",S79,"-",T79,"-",U79,"-",V79,"-",W79,"-",X79,"-",Y79,"-",Z79,"-",AA79,"-",AB79,"-",AC79,"-",AD79) -> --E16718500-1,05-1,05-2,1-----0,35-0,35-0,35-----0,35-0,35-0,35--------- | AL79: =VLOOKUP(AK79,Planilha1!B:C,2,0) -> 52 | AM79: CR-0162211-00 IP
A80: 3202585H5 | D80: 3202585H5-65763-0,35--USCAR21 | G80: 0.35 | AH80: X | AI80: 8 | AJ80: 2026 | AK80: =CONCATENATE(A80,"-",B80,"-",C80,"-",E80,"-",F80,"-",G80,"-",H80,"-",I80,"-",J80,"-",K80,"-",L80,"-",M80,"-",N80,"-",O80,"-",P80,"-",Q80,"-",R80,"-",S80,"-",T80,"-",U80,"-",V80,"-",W80,"-",X80,"-",Y80,"-",Z80,"-",AA80,"-",AB80,"-",AC80,"-",AD80) -> 3202585H5-----0,35----------------------- | AL80: =VLOOKUP(AK80,Planilha1!B:C,2,0) -> 53 | AM80: CR-0162211-00 IP
A81: E02656000 | D81: E02656000-65769-0,75--USCAR21 | G81: 0.75 | AH81: X | AI81: 8 | AJ81: 2026 | AK81: =CONCATENATE(A81,"-",B81,"-",C81,"-",E81,"-",F81,"-",G81,"-",H81,"-",I81,"-",J81,"-",K81,"-",L81,"-",M81,"-",N81,"-",O81,"-",P81,"-",Q81,"-",R81,"-",S81,"-",T81,"-",U81,"-",V81,"-",W81,"-",X81,"-",Y81,"-",Z81,"-",AA81,"-",AB81,"-",AC81,"-",AD81) -> E02656000-----0,75----------------------- | AL81: =VLOOKUP(AK81,Planilha1!B:C,2,0) -> 54 | AM81: CR-0162211-00 IP
A82: E02656000 | D82: E02656000-65860-0,75--USCAR21 | G82: 0.75 | AH82: X | AI82: 8 | AJ82: 2026 | AK82: =CONCATENATE(A82,"-",B82,"-",C82,"-",E82,"-",F82,"-",G82,"-",H82,"-",I82,"-",J82,"-",K82,"-",L82,"-",M82,"-",N82,"-",O82,"-",P82,"-",Q82,"-",R82,"-",S82,"-",T82,"-",U82,"-",V82,"-",W82,"-",X82,"-",Y82,"-",Z82,"-",AA82,"-",AB82,"-",AC82,"-",AD82) -> E02656000-----0,75----------------------- | AL82: =VLOOKUP(AK82,Planilha1!B:C,2,0) -> 54 | AM82: CR-0162211-00 IP
A83: E05363600 | D83: E05363600-65763-0,75--USCAR21 | G83: 0.75 | AH83: X | AI83: 8 | AJ83: 2026 | AK83: =CONCATENATE(A83,"-",B83,"-",C83,"-",E83,"-",F83,"-",G83,"-",H83,"-",I83,"-",J83,"-",K83,"-",L83,"-",M83,"-",N83,"-",O83,"-",P83,"-",Q83,"-",R83,"-",S83,"-",T83,"-",U83,"-",V83,"-",W83,"-",X83,"-",Y83,"-",Z83,"-",AA83,"-",AB83,"-",AC83,"-",AD83) -> E05363600-----0,75----------------------- | AL83: =VLOOKUP(AK83,Planilha1!B:C,2,0) -> 55 | AM83: CR-0162211-00 IP
A84: E02719100 | D84: E02719100-65763-0,5--USCAR21 | G84: 0.5 | AH84: X | AI84: 8 | AJ84: 2026 | AK84: =CONCATENATE(A84,"-",B84,"-",C84,"-",E84,"-",F84,"-",G84,"-",H84,"-",I84,"-",J84,"-",K84,"-",L84,"-",M84,"-",N84,"-",O84,"-",P84,"-",Q84,"-",R84,"-",S84,"-",T84,"-",U84,"-",V84,"-",W84,"-",X84,"-",Y84,"-",Z84,"-",AA84,"-",AB84,"-",AC84,"-",AD84) -> E02719100-----0,5----------------------- | AL84: =VLOOKUP(AK84,Planilha1!B:C,2,0) -> 56 | AM84: CR-0162211-00 IP
A85: E02719100 | D85: E02719100-65763-0,5--USCAR21 | G85: 0.5 | AH85: X | AI85: 8 | AJ85: 2026 | AK85: =CONCATENATE(A85,"-",B85,"-",C85,"-",E85,"-",F85,"-",G85,"-",H85,"-",I85,"-",J85,"-",K85,"-",L85,"-",M85,"-",N85,"-",O85,"-",P85,"-",Q85,"-",R85,"-",S85,"-",T85,"-",U85,"-",V85,"-",W85,"-",X85,"-",Y85,"-",Z85,"-",AA85,"-",AB85,"-",AC85,"-",AD85) -> E02719100-----0,5----------------------- | AL85: =VLOOKUP(AK85,Planilha1!B:C,2,0) -> 56 | AM85: CR-0166437-01 BODY | AN85: Nt validação com bitola 0.50
A86: E04410900 | D86: E04410900-65766-0,35--USCAR21 | G86: 0.35 | AH86: X | AI86: 8 | AJ86: 2026 | AK86: =CONCATENATE(A86,"-",B86,"-",C86,"-",E86,"-",F86,"-",G86,"-",H86,"-",I86,"-",J86,"-",K86,"-",L86,"-",M86,"-",N86,"-",O86,"-",P86,"-",Q86,"-",R86,"-",S86,"-",T86,"-",U86,"-",V86,"-",W86,"-",X86,"-",Y86,"-",Z86,"-",AA86,"-",AB86,"-",AC86,"-",AD86) -> E04410900-----0,35----------------------- | AL86: =VLOOKUP(AK86,Planilha1!B:C,2,0) -> 57 | AM86: CR-0162211-00 IP
A87: 32025Y3B8 | D87: 32025Y3B8-65860-0,75--USCAR21 | G87: 0.75 | AH87: X | AI87: 8 | AJ87: 2026 | AK87: =CONCATENATE(A87,"-",B87,"-",C87,"-",E87,"-",F87,"-",G87,"-",H87,"-",I87,"-",J87,"-",K87,"-",L87,"-",M87,"-",N87,"-",O87,"-",P87,"-",Q87,"-",R87,"-",S87,"-",T87,"-",U87,"-",V87,"-",W87,"-",X87,"-",Y87,"-",Z87,"-",AA87,"-",AB87,"-",AC87,"-",AD87) -> 32025Y3B8-----0,75----------------------- | AL87: =VLOOKUP(AK87,Planilha1!B:C,2,0) -> 58 | AM87: CR-0162211-00 IP
A88: E03844600 | D88: E03844600-65766-0,35--USCAR21 | G88: 0.35 | AH88: X | AI88: 8 | AJ88: 2026 | AK88: =CONCATENATE(A88,"-",B88,"-",C88,"-",E88,"-",F88,"-",G88,"-",H88,"-",I88,"-",J88,"-",K88,"-",L88,"-",M88,"-",N88,"-",O88,"-",P88,"-",Q88,"-",R88,"-",S88,"-",T88,"-",U88,"-",V88,"-",W88,"-",X88,"-",Y88,"-",Z88,"-",AA88,"-",AB88,"-",AC88,"-",AD88) -> E03844600-----0,35----------------------- | AL88: =VLOOKUP(AK88,Planilha1!B:C,2,0) -> 59 | AM88: CR-0162211-00 IP
A89: E15132900 | C89: 3299365JY | G89: 3.25 | H89: 1 | I89: 1 | J89: 0.75 | K89: 0.5 | AE89: X | AG89: X | AI89: 16 | AJ89: 2026 | AK89: =CONCATENATE(A89,"-",B89,"-",C89,"-",E89,"-",F89,"-",G89,"-",H89,"-",I89,"-",J89,"-",K89,"-",L89,"-",M89,"-",N89,"-",O89,"-",P89,"-",Q89,"-",R89,"-",S89,"-",T89,"-",U89,"-",V89,"-",W89,"-",X89,"-",Y89,"-",Z89,"-",AA89,"-",AB89,"-",AC89,"-",AD89) -> E15132900--3299365JY---3,25-1-1-0,75-0,5------------------- | AL89: =VLOOKUP(AK89,Planilha1!B:C,2,0) -> 60 | AM89: CR-0162211-00 IP
A90: E15132900 | C90: 3299365JY | G90: 3.25 | H90: 1 | I90: 1 | J90: 0.75 | K90: 0.5 | AE90: X | AG90: X | AI90: 16 | AJ90: 2026 | AK90: =CONCATENATE(A90,"-",B90,"-",C90,"-",E90,"-",F90,"-",G90,"-",H90,"-",I90,"-",J90,"-",K90,"-",L90,"-",M90,"-",N90,"-",O90,"-",P90,"-",Q90,"-",R90,"-",S90,"-",T90,"-",U90,"-",V90,"-",W90,"-",X90,"-",Y90,"-",Z90,"-",AA90,"-",AB90,"-",AC90,"-",AD90) -> E15132900--3299365JY---3,25-1-1-0,75-0,5------------------- | AL90: =VLOOKUP(AK90,Planilha1!B:C,2,0) -> 60 | AM90: CR-0170489-00 IP
A91: E15132900 | C91: 3299365JY | G91: 2.75 | H91: 1 | I91: 1 | J91: 0.75 | AE91: X | AG91: X | AI91: 16 | AJ91: 2026 | AK91: =CONCATENATE(A91,"-",B91,"-",C91,"-",E91,"-",F91,"-",G91,"-",H91,"-",I91,"-",J91,"-",K91,"-",L91,"-",M91,"-",N91,"-",O91,"-",P91,"-",Q91,"-",R91,"-",S91,"-",T91,"-",U91,"-",V91,"-",W91,"-",X91,"-",Y91,"-",Z91,"-",AA91,"-",AB91,"-",AC91,"-",AD91) -> E15132900--3299365JY---2,75-1-1-0,75-------------------- | AL91: =VLOOKUP(AK91,Planilha1!B:C,2,0) -> 61 | AM91: CR-0162211-00 IP
A92: E15132900 | C92: 3299365JY | G92: 2.75 | H92: 1 | I92: 1 | J92: 0.75 | AE92: X | AG92: X | AI92: 16 | AJ92: 2026 | AK92: =CONCATENATE(A92,"-",B92,"-",C92,"-",E92,"-",F92,"-",G92,"-",H92,"-",I92,"-",J92,"-",K92,"-",L92,"-",M92,"-",N92,"-",O92,"-",P92,"-",Q92,"-",R92,"-",S92,"-",T92,"-",U92,"-",V92,"-",W92,"-",X92,"-",Y92,"-",Z92,"-",AA92,"-",AB92,"-",AC92,"-",AD92) -> E15132900--3299365JY---2,75-1-1-0,75-------------------- | AL92: =VLOOKUP(AK92,Planilha1!B:C,2,0) -> 61 | AM92: CR-0170489-00 IP
C93: 3299362M9 | E93: 1.5 | F93: 2.5 | G93: 4 | L93: 1.5 | S93: 2 | T93: 0.5 | AF93: X | AG93: X | AI93: 16 | AJ93: 2026 | AK93: =CONCATENATE(A93,"-",B93,"-",C93,"-",E93,"-",F93,"-",G93,"-",H93,"-",I93,"-",J93,"-",K93,"-",L93,"-",M93,"-",N93,"-",O93,"-",P93,"-",Q93,"-",R93,"-",S93,"-",T93,"-",U93,"-",V93,"-",W93,"-",X93,"-",Y93,"-",Z93,"-",AA93,"-",AB93,"-",AC93,"-",AD93) -> --3299362M9-1,5-2,5-4-----1,5-------2-0,5---------- | AL93: =VLOOKUP(AK93,Planilha1!B:C,2,0) -> 62 | AM93: CR-0168269-00 BODY
C94: E16718500 | E94: 1.5 | F94: 1.5 | G94: 3 | L94: 0.75 | M94: 0.75 | S94: 0.75 | T94: 0.75 | AF94: X | AG94: X | AI94: 16 | AJ94: 2026 | AK94: =CONCATENATE(A94,"-",B94,"-",C94,"-",E94,"-",F94,"-",G94,"-",H94,"-",I94,"-",J94,"-",K94,"-",L94,"-",M94,"-",N94,"-",O94,"-",P94,"-",Q94,"-",R94,"-",S94,"-",T94,"-",U94,"-",V94,"-",W94,"-",X94,"-",Y94,"-",Z94,"-",AA94,"-",AB94,"-",AC94,"-",AD94) -> --E16718500-1,5-1,5-3-----0,75-0,75------0,75-0,75---------- | AL94: =VLOOKUP(AK94,Planilha1!B:C,2,0) -> 63 | AM94: CR-0168269-00 BODY
C95: 3299362M9 | E95: 0 | F95: 3 | G95: 3 | S95: 3 | AF95: X | AG95: X | AI95: 16 | AJ95: 2026 | AK95: =CONCATENATE(A95,"-",B95,"-",C95,"-",E95,"-",F95,"-",G95,"-",H95,"-",I95,"-",J95,"-",K95,"-",L95,"-",M95,"-",N95,"-",O95,"-",P95,"-",Q95,"-",R95,"-",S95,"-",T95,"-",U95,"-",V95,"-",W95,"-",X95,"-",Y95,"-",Z95,"-",AA95,"-",AB95,"-",AC95,"-",AD95) -> --3299362M9-0-3-3------------3----------- | AL95: =VLOOKUP(AK95,Planilha1!B:C,2,0) -> 64 | AM95: CR-0168269-00 BODY
C96: 3299362M9 | E96: 3.5 | F96: 3 | G96: 6.5 | L96: 0.5 | M96: 0.5 | N96: 2.5 | S96: 3 | AF96: X | AG96: X | AI96: 16 | AJ96: 2026 | AK96: =CONCATENATE(A96,"-",B96,"-",C96,"-",E96,"-",F96,"-",G96,"-",H96,"-",I96,"-",J96,"-",K96,"-",L96,"-",M96,"-",N96,"-",O96,"-",P96,"-",Q96,"-",R96,"-",S96,"-",T96,"-",U96,"-",V96,"-",W96,"-",X96,"-",Y96,"-",Z96,"-",AA96,"-",AB96,"-",AC96,"-",AD96) -> --3299362M9-3,5-3-6,5-----0,5-0,5-2,5-----3----------- | AL96: =VLOOKUP(AK96,Planilha1!B:C,2,0) -> 65 | AM96: CR-0168269-00 BODY
C97: 3299362M9 | E97: 4.5 | F97: 3 | G97: 7.5 | L97: 1 | M97: 0.5 | N97: 0.5 | O97: 2.5 | S97: 3 | AF97: X | AG97: X | AI97: 16 | AJ97: 2026 | AK97: =CONCATENATE(A97,"-",B97,"-",C97,"-",E97,"-",F97,"-",G97,"-",H97,"-",I97,"-",J97,"-",K97,"-",L97,"-",M97,"-",N97,"-",O97,"-",P97,"-",Q97,"-",R97,"-",S97,"-",T97,"-",U97,"-",V97,"-",W97,"-",X97,"-",Y97,"-",Z97,"-",AA97,"-",AB97,"-",AC97,"-",AD97) -> --3299362M9-4,5-3-7,5-----1-0,5-0.5-2,5----3----------- | AL97: =VLOOKUP(AK97,Planilha1!B:C,2,0) -> 66 | AM97: CR-0168269-00 BODY
C98: 3299362M9 | E98: 4.5 | F98: 3 | G98: 7.5 | L98: 1 | M98: 0.5 | N98: 0.5 | O98: 2.5 | S98: 3 | AF98: X | AG98: X | AI98: 16 | AJ98: 2026 | AK98: =CONCATENATE(A98,"-",B98,"-",C98,"-",E98,"-",F98,"-",G98,"-",H98,"-",I98,"-",J98,"-",K98,"-",L98,"-",M98,"-",N98,"-",O98,"-",P98,"-",Q98,"-",R98,"-",S98,"-",T98,"-",U98,"-",V98,"-",W98,"-",X98,"-",Y98,"-",Z98,"-",AA98,"-",AB98,"-",AC98,"-",AD98) -> --3299362M9-4,5-3-7,5-----1-0,5-0,5-2,5----3----------- | AL98: =VLOOKUP(AK98,Planilha1!B:C,2,0) -> 67 | AM98: CR-0168269-00 BODY
C99: 3299362M9 | E99: 4.5 | F99: 3 | G99: 7.5 | L99: 1 | M99: 0.5 | N99: 0.5 | O99: 2.5 | S99: 3 | AF99: X | AG99: X | AI99: 16 | AJ99: 2026 | AK99: =CONCATENATE(A99,"-",B99,"-",C99,"-",E99,"-",F99,"-",G99,"-",H99,"-",I99,"-",J99,"-",K99,"-",L99,"-",M99,"-",N99,"-",O99,"-",P99,"-",Q99,"-",R99,"-",S99,"-",T99,"-",U99,"-",V99,"-",W99,"-",X99,"-",Y99,"-",Z99,"-",AA99,"-",AB99,"-",AC99,"-",AD99) -> --3299362M9-4,5-3-7,5-----1-0,5-0,5-2,5----3----------- | AL99: =VLOOKUP(AK99,Planilha1!B:C,2,0) -> 67 | AM99: CR-0164612-01 BODY | AN99: foi considerado na CR 9 validações uscar45 e 21 GMW17136( necesidade 26 GMW17136 e 18 Uscar45)
C100: 3299362M9 | E100: 3.5 | F100: 4 | G100: 7.5 | L100: 0.5 | M100: 0.5 | N100: 2.5 | S100: 1 | T100: 3 | AF100: X | AG100: X | AI100: 16 | AJ100: 2026 | AK100: =CONCATENATE(A100,"-",B100,"-",C100,"-",E100,"-",F100,"-",G100,"-",H100,"-",I100,"-",J100,"-",K100,"-",L100,"-",M100,"-",N100,"-",O100,"-",P100,"-",Q100,"-",R100,"-",S100,"-",T100,"-",U100,"-",V100,"-",W100,"-",X100,"-",Y100,"-",Z100,"-",AA100,"-",AB100,"-",AC100,"-",AD100) -> --3299362M9-3,5-4-7,5-----0,5-0,5-2,5-----1-3---------- | AL100: =VLOOKUP(AK100,Planilha1!B:C,2,0) -> 68 | AM100: CR-0168269-00 BODY
...

Sheet Planilha1
B1: CHP USCAR45, uscar38 USCAR 21 | C1: Nº
B2: --3299362G2-1,2-0,5-1,7-----0,35-0,5-0,35-----0,5----------- | C2: 1 | N2: --3299362G2-1,2-0,5-1,7-----0,35-0,5-0,35-----0,5----------- | O2: 1
B3: --3299362G2-0,7-1-1,7-----0,35-0,35------0,5-0,5---------- | C3: 2 | N3: --3299362G2-0,7-1-1,7-----0,35-0,35------0,5-0,5---------- | O3: 2
B4: --E16718500-1,05-0,35-1,4-----0,35-0,35-0,35-----0,35----------- | C4: 3 | N4: --E16718500-1,05-0,35-1,4-----0,35-0,35-0,35-----0,35----------- | O4: 3
B5: --E16718500-0,35-0,7-1,05-----0,35-------0,35-0,35---------- | C5: 4 | N5: --E16718500-0,35-0,7-1,05-----0,35-------0,35-0,35---------- | O5: 4
B6: --3299362M9-3,35-4-7,35-----0,35-0,5-2,5-----1-3---------- | C6: 5 | N6: --3299362M9-3,35-4-7,35-----0,35-0,5-2,5-----1-3---------- | O6: 5
B7: --3299362M9-4,35-3-7,35-----1-0,35-0,5-2,5----3----------- | C7: 6 | N7: --3299362M9-4,35-3-7,35-----1-0,35-0,5-2,5----3----------- | O7: 6
B8: --E16718500-0,5-0,85-1,35-----0,5-------0,5-0,35---------- | C8: 7 | N8: --E16718500-0,5-0,85-1,35-----0,5-------0,5-0,35---------- | O8: 7
B9: --E16718500-0,35-0,75-1,1-----0,35-------0,75----------- | C9: 8 | N9: --E16718500-0,35-0,75-1,1-----0,35-------0,75----------- | O9: 8
B10: --E16718500-1,25-0,5-1,75-----0,5-0,75------0,5----------- | C10: 9 | N10: --E16718500-1,25-0,5-1,75-----0,5-0,75------0,5----------- | O10: 9
B11: --E16718500-0,85-0,35-1,2-----0,5-------0,35-----0,35------ | C11: 10 | N11: --E16718500-0,85-0,35-1,2-----0,5-------0,35-----0,35------ | O11: 10
B12: --E16718500-0,5-1,85-2,35-----0,5-------0,5-0,5-0,5-0,35-------- | C12: 11 | N12: --E16718500-0,5-1,85-2,35-----0,5-------0,5-0,5-0,5-0,35-------- | O12: 11
B13: --3299362M9-6,25-0,5-6,75-----1,5-0,5-0,75-2----0,5-----1,5------ | C13: 12 | N13: --3299362M9-6,25-0,5-6,75-----1,5-0,5-0,75-2----0,5-----1,5------ | O13: 12
... B166: 3202585H5-----0,7-0,35-0,35--------------------- | C166: 165 | N166: 3202585H5-----0,7-0,35-0,35--------------------- | O166: 165

Sheet Planilha2
L3: 45458
L4: =COUNTIF(I:I,L3) -> 23
C6: R | D6: PROGRAMA | E6: ECR | F6: PLANTA | G6: CORTE & LEAD PREP.
C7: 0 | D7: CR-0181209-01 | E7: GEM - SAO | F7: 4683765 | G7: PENDENTE | H7: LATE | I7: =VLOOKUP(D7,'Controle de CR'!E:L,8,0) -> 45458
C8: 0 | D8: CR-0180221-00 | E8: GEM - SAO | F8: 4677205 | G8: PENDENTE | H8: LATE | I8: =VLOOKUP(D8,'Controle de CR'!E:L,8,0) -> #N/A
C9: 0 | D9: CR-0179947-00 | E9: GEM - SAO | F9: 4677205 | G9: PENDENTE | H9: LATE | I9: =VLOOKUP(D9,'Controle de CR'!E:L,8,0) -> 45458
C10: 0 | D10: CR-0179950-00 | E10: GEM - SAO | F10: 4677205 | G10: PENDENTE | H10: LATE | I10: =VLOOKUP(D10,'Controle de CR'!E:L,8,0) -> 45458
C11: 0 | D11: CR-0180470-00 | E11: GEM - SAO | F11: 4677205 | G11: PENDENTE | H11: LATE | I11: =VLOOKUP(D11,'Controle de CR'!E:L,8,0) -> 45458
C12: 0 | D12: CR-0180472-00 | E12: GEM - SAO | F12: 4677205 | G12: PENDENTE | H12: LATE | I12: =VLOOKUP(D12,'Controle de CR'!E:L,8,0) -> 45458
C13: 0 | D13: CR-0180938-00 | E13: GEM - SAO | F13: 4677205 | G13: PENDENTE | H13: LATE | I13: =VLOOKUP(D13,'Controle de CR'!E:L,8,0) -> 45458
C14: 0 | D14: CR-0180929-00 | E14: GEM - SAO | F14: 4677205 | G14: PENDENTE | H14: LATE | I14: =VLOOKUP(D14,'Controle de CR'!E:L,8,0) -> 45458
C15: 0 | D15: CR-0180939-00 | E15: GEM - SAO | F15: 4677205 | G15: PENDENTE | H15: LATE | I15: =VLOOKUP(D15,'Controle de CR'!E:L,8,0) -> 45460
C16: 0 | D16: CR-0179866-00 | E16: GEM - SAO | F16: 4677205 | G16: PENDENTE | H16: LATE | I16: =VLOOKUP(D16,'Controle de CR'!E:L,8,0) -> 45458
C17: 0 | D17: CR-0181008-00 | E17: GEM - SAO | F17: 4677205 | G17: PENDENTE | H17: LATE | I17: =VLOOKUP(D17,'Controle de CR'!E:L,8,0) -> 45458
C18: 0 | D18: CR-0180979-00 | E18: GEM - SAO | F18: 4677205 | G18: PENDENTE | H18: LATE | I18: =VLOOKUP(D18,'Controle de CR'!E:L,8,0) -> 45458
... C36: 0 | D36: CR-0181157-00 | E36: GEM - SAO | F36: 4677211 | G36: PENDENTE | H36: LATE | I36: =VLOOKUP(D36,'Controle de CR'!E:L,8,0) -> 45457
C37: 0 | D37: CR-0181623-01 | E37: GEM - SAO | F37: ECR4677212 | G37: PENDENTE | H37: LATE | I37: =VLOOKUP(D37,'Controle de CR'!E:L,8,0) -> 45462
C38: 0 | D38: CR-0181647-01 | E38: GEM - SAO | F38: ECR4677212 | G38: PENDENTE | H38: LATE | I38: =VLOOKUP(D38,'Controle de CR'!E:L,8,0) -> 45462
C39: 0 | D39: CR-0181958-00 | E39: GEM - SAO | F39: ECR4677212 | G39: PENDENTE | H39: LATE | I39: =VLOOKUP(D39,'Controle de CR'!E:L,8,0) -> 45458
C40: 0 | D40: CR-0181647-00 | E40: GEM - SAO | F40: ECR4677212 | G40: PENDENTE | H40: LATE | I40: =VLOOKUP(D40,'Controle de CR'!E:L,8,0) -> 45462
C41: 0 | D41: CR-0183607-00 | E41: SPIN - SAO | F41: 4704121 | G41: PENDENTE | H41: ALERT | I41: =VLOOKUP(D41,'Controle de CR'!E:L,8,0) -> 45464
C42: 0 | D42: CR-0183633-00 | E42: SPIN - SAO | F42: 4704121 | G42: PENDENTE | H42: ON TIME | I42: =VLOOKUP(D42,'Controle de CR'!E:L,8,0) -> 45458
C43: 1 | D43: CR-0182918-00 | E43: GEM - SAO | F43: SCR#280873 | G43: PENDENTE | H43: LATE | I43: =VLOOKUP(D43,'Controle de CR'!E:L,8,0) -> #N/A
C44: 1 | D44: CR-0182777-00 | E44: SPIN - SAO | F44: 281397 | G44: PENDENTE | H44: LATE | I44: =VLOOKUP(D44,'Controle de CR'!E:L,8,0) -> 45472
C45: 1 | D45: CR-0179328-00 | E45: SPIN - SAO | F45: 282624 | G45: PENDENTE | H45: LATE | I45: =VLOOKUP(D45,'Controle de CR'!E:L,8,0) -> 45472
C46: 1 | D46: CR-0175702-01 | E46: SPIN - SAO | F46: 4632694 | G46: PENDENTE | H46: LATE | I46: =VLOOKUP(D46,'Controle de CR'!E:L,8,0) -> 45458
C47: 1 | D47: CR-0178778-00 | E47: SPIN - SAO | F47: 4677753 | G47: PENDENTE | H47: LATE | I47: =VLOOKUP(D47,'Controle de CR'!E:L,8,0) -> 45427.38
C48: 1 | D48: CR-0178967-00 | E48: SPIN - SAO | F48: 4677753 | G48: PENDENTE | H48: LATE | I48: =VLOOKUP(D48,'Controle de CR'!E:L,8,0) -> #N/A
C49: 1 | D49: CR-0177765-01 | E49: SPIN - SAO | F49: Customer Request | G49: PENDENTE | H49: LATE | I49: =VLOOKUP(D49,'Controle de CR'!E:L,8,0) -> 45458
